Workbook
Name FarmName: LISTS!$B$6
Name ExpiryWarnDays: LISTS!$B$7
Name L_FeedTypes: tFeedTypes[[Feed Type]]
Name L_Drugs: tDrugs[[Drug Name]]
Name L_Units: tUnits[[Unit]]
Name L_Animals: tAnimalTypes[[Animal Type]]
Name L_Products: tProducts[[Product]]
Name L_ExpCat: tExpCat[[Expense Category]]
Name L_Pay: tPayMethods[[Payment Method]]
Name L_Causes: tCauses[[Mortality Cause]]
Name L_Meas: tMeasTypes[[Measurement Type]]
Name L_Reasons: tDrugReasons[[Drug Reason]]
Name L_MoveTypes: tMoveTypes[[Movement Type]]
Name L_CashTypes: tCashTypes[[Cash Type]]
Name L_Staff: tStaff[[Staff]]
Name L_Customers: tCustomers[[Customer]]
Name L_Suppliers: tSuppliers[[Supplier]]
Name L_Pens: tPens[[Pen ID]]
Name L_Batches: tBatches[[Batch ID]]
Name L_PensGen: OFFSET(HELPER!$A$2,0,0,COUNTA(tPens[[Pen ID]])+1,1)
Name L_PenFilter: OFFSET(HELPER!$B$2,0,0,COUNTA(tPens[[Pen ID]])+1,1)
Name L_BatchFilter: OFFSET(HELPER!$C$2,0,0,COUNTA(tBatches[[Batch ID]])+1,1)
Name L_AnimalFilter: OFFSET(HELPER!$D$2,0,0,COUNTA(tAnimalTypes[[Animal Type]])+1,1)
Name DStart: HELPER!$G$2
Name DEnd: HELPER!$G$3
Name FPen: HELPER!$G$4
Name FBatch: HELPER!$G$5
Name FAnimal: HELPER!$G$6
Name FilterText: HELPER!$G$7
Name TrendStart: TRENDS!$C$4
Name DB_Period: DASHBOARD!$D$5
Name DB_From: DASHBOARD!$D$6
Name DB_To: DASHBOARD!$D$7
Name DB_Pen: DASHBOARD!$D$8
Name DB_Batch: DASHBOARD!$D$9
Name DB_Animal: DASHBOARD!$D$10

Sheet README
B1: FARM ACCOUNTING & INVENTORY MANAGEMENT SYSTEM
B2: Enter transactions once. Everything else is calculated automatically.
B5: WHAT THIS WORKBOOK DOES
B6: Flow | C6: Purchase -> Inventory (store) -> Issue / Usage -> Pen & Batch -> Production -> Sale -> Profitability
B7: Hierarchy | C7: Farm -> Pen (permanent physical house, e.g. P001) -> Batch (one production cycle in a pen, e.g. BROILER-SEP-001) -> Transactions. A pen keeps its ID for life; batches come and go.
B8: Key idea | C8: Purchases are NOT charged to a pen. They go into the store. Cost reaches a pen/batch only when you record an ISSUE (feed) or USAGE (drug). One purchase can therefore be shared by any number of pens.
B9: No daily rows | C9: Record only what happened. If nothing happened in a pen today, enter nothing for it.
B11: COLOURS & CELLS
B12: Green header | C12: Input column - type or pick from the dropdown.
B13: Grey header / grey cell | C13: Automatic formula - do not type. New rows fill these in by themselves.
B14: Yellow cell | C14: A setting or filter you may change (DASHBOARD filters, LISTS settings, TRENDS first month).
B15: Check column | C15: Every log ends with a Check column: OK or a plain-English warning (red). CHECKS sheet counts them.
B16: Protected sheets | C16: DASHBOARD, INVENTORY, BATCH_PROFITABILITY, REPORTS, TRENDS and CHECKS are protected (no password) so formulas are not overwritten. Review > Unprotect Sheet if you must edit.
B18: SHEETS
B19: DASHBOARD | C19: Main page. Farm status, financial & production summary, mortality, charts and pen comparison. Filter by period (Today / This Week / This Month / This Year / All Time / Custom), pen, batch, animal.
B20: PEN_REGISTER | C20: List of pens. You enter ID, name, location, animal type. Current batch, stock and status are automatic.
B21: BATCH_REGISTER | C21: One row per batch/cycle. You enter ID, pen, start date, initial quantity, status (& closing date). Current quantity = initial + transfers in - deaths - animals sold - transfers out.
B22: FEED_PURCHASES | C22: Every feed purchase (bags x bag size = kg; bags x price = cost).
B23: FEED_ISSUES | C23: Feed taken from the store to a pen/batch. Cost per kg is automatic (weighted average).
B24: DRUG_PURCHASES | C24: Every drug/vaccine purchase, with expiry date and lot number. Expiry warnings are automatic.
B25: DRUG_USAGE | C25: Each administration per pen/batch with dosage and quantity. Cost is automatic.
B26: MORTALITY_LOG | C26: Deaths - only on days they happen. Record the observed/recorded cause (use Unknown if unsure).
B27: PRODUCTION_LOG | C27: Weighings (average weight, number sampled) and output such as egg collection.
B28: SALES | C28: Sales linked to pen & batch (or GENERAL for farm-wide items like manure).
B29: OTHER_EXPENSES | C29: Chicks/stock purchase, labour, electricity, repairs ... Pen ID or GENERAL; add Batch ID to charge a batch.
B30: CASHBOOK | C30: Actual money in/out with running balance. Cash is not the same as profit (see below).
... B37: LISTS | C37: Master lists for all dropdowns (feed types + reorder levels, drugs + units, products, categories ...) and settings.
B39: HOW TO ...
B40: Add a new pen | C40: PEN_REGISTER: type the new Pen ID (e.g. P007) in the first empty row under the table, then name, location, animal type. Never reuse or rename an ID that already has records.
B41: Start a new batch | C41: BATCH_REGISTER: new row with a unique Batch ID (e.g. BROILER-OCT-001), Pen ID, animal type, start date, initial quantity, Status = Active. Record the chick cost on OTHER_EXPENSES with the Batch ID.
B42: Close a batch | C42: Set Status = Closed and enter the Closing Date. Do NOT delete anything - the batch's history stays in every report and the pen shows Empty, ready for the next batch.
B43: Record a purchase | C43: FEED_PURCHASES (feed type, bags, bag size, price per bag) or DRUG_PURCHASES (drug, quantity in its stock unit, unit cost, expiry, lot no.). Also enter the payment in CASHBOOK unless bought on Credit.
B44: Issue feed | C44: FEED_ISSUES: date, feed type, pen, batch, kg. Example: 500 kg bought once, then P001 40 kg, P002 60 kg, P003 35 kg, P004 50 kg = four issue rows. If an issue exceeds the store, the Check column warns you.
B45: Record drug usage | C45: DRUG_USAGE: date, drug, pen, batch, reason, dosage text, total quantity used. Same drug in 3 pens = 3 rows.
B46: Record mortality | C46: MORTALITY_LOG: date, pen, batch, number of deaths, cause. Stock updates automatically.
B47: Record a sale | C47: SALES: date, pen, batch, product, quantity, unit price, customer, payment method. Live-animal products reduce batch stock automatically (set per product on LISTS). Add receipt to CASHBOOK.
B48: Record an expense | C48: OTHER_EXPENSES: category, description, Pen ID or GENERAL, Batch ID if it belongs to one batch, amount.
B49: Add a dropdown item | C49: LISTS: type the new item directly under the relevant list - dropdowns grow automatically.
B51: READING THE DASHBOARD
B52: Filters | C52: Choose Period, Pen, Batch and Animal Type in the yellow cells. All cards, the pen comparison, TRENDS and REPORTS follow them.
B53: Current status | C53: Live stock, active pens/batches and store value as of today.
B54: Financial | C54: Purchases (cash spent on stock) are shown separately from COST (what was consumed). Profit/Loss = Sales - (feed issued + drugs used + other expenses) for the filter.
B55: Pen comparison | C55: Factual figures per pen for the period. No ranking - interpret them yourself. GENERAL = farm-wide costs.
B57: COSTING & ACCOUNTING RULES
B58: Costing method | C58: Moving weighted average (fixed - never changes silently). Each purchase re-averages the stock in store: (stock on hand x old average + purchase cost) / (stock on hand + quantity bought). Example: 100 kg in store @ ₦500 and 200 kg bought @ ₦600 -> (100x500 + 200x600) / 300 = ₦566.67 per kg. Every issue is costed at the average in force on its date; later purchases never change earlier issues.
B59: Purchase order | C59: Keep FEED_PURCHASES and DRUG_PURCHASES in date order (the average is built row by row). A late-entered old invoice must be inserted in its date position (right-click > Insert > Table Rows Above); the Check column flags rows out of order.
B60: Inventory value | C60: Purchased cost - cost already charged to pens. Purchases therefore always equal consumption + stock in store.
B61: Purchase vs consumption | C61: Buying ₦500,000 of feed is NOT a ₦500,000 batch cost. It becomes cost only as it is issued. Unused drugs stay in inventory.
B62: Cash vs profit | C62: CASHBOOK shows money actually received/paid (incl. credit settlements, capital, loans). Profit uses consumption. CHECKS reconciles the cashbook with the logs.
B63: Overheads | C63: GENERAL expenses (e.g. farm electricity) are in farm totals, not allocated to batches. Pen-level costs without a batch are in pen totals only. Add a Batch ID to include a cost in batch profitability.
B64: Units | C64: Feed is always stored in kg. Each drug has one Stock Unit (LISTS) - enter purchase and usage quantities in that unit.
B66: HISTORY, SCALE & GOOD PRACTICE
B67: History | C67: Never delete or overwrite old records when a batch closes. Closed batches stay in BATCH_PROFITABILITY for comparison.
B68: Growth | C68: Logs are Excel Tables: they grow automatically and every formula uses whole-table references, so 5 or 50 pens and tens of thousands of rows need no formula changes. Report sheets show up to 60 pens, 300 batches, 20 feed types and 50 drugs (extend with the generator script if ever needed).
B69: IDs | C69: Record IDs (FP-00001 ...) are numbered by row. Do not sort the logs - use the filter arrows to view subsets.
B70: Dates | C70: Enter dates as DD/MM/YYYY. Invalid dates, text in number fields and negative amounts are rejected.
B72: SAMPLE DATA
B73: What it is | C73: All example rows are marked 'SAMPLE DATA' in Notes (pens P001-P006, six batches incl. one closed batch in P006, a 20-bag x 25 kg Starter purchase shared across P001-P004, one drug used in three pens at different dosages).
B74: Remove it | C74: Delete the sample rows in each log (select rows inside the table > right-click > Delete > Table Rows), then PEN_REGISTER / BATCH_REGISTER rows, then edit LISTS. Keep at least the table headers.

Sheet PEN_REGISTER
A1: PEN REGISTER
A2: Physical pens (permanent). Current batch, stock and status are calculated from BATCH_REGISTER. A pen keeps its ID for life; batches come and go.
A3: ■ GREEN header = you enter / select ■ GREY header = automatic (do not type) Add a new record by typing in the first empty row directly under the table.
A4: Pen ID | B4: Pen Name | C4: Farm/Location | D4: Animal Type | E4: Current Batch ID | F4: Start Date | G4: Initial Stock | H4: Current Stock | I4: Status | J4: Pen Closed | K4: Notes | L4: Check
A5: P001 | B5: Broiler House 1 | C5: Main Farm | D5: Broiler | E5: =IF(COUNTIFS(tBatches[[Pen ID]],tPens[[#This Row],[Pen ID]],tBatches[[Status]],"Active")=0,"",IF(COUNTIFS(tBatches[[Pen ID]],tPens[[#This Row],[Pen ID]],tBatches[[Status]],"Active")=1,INDEX(tBatches[[Batch ID]],MATCH(tPens[[#This Row],[Pen ID]],tBatches[[Active Pen Key]],0)),INDEX(tBatches[[Batch ID]],MATCH(tPens[[#This Row],[Pen ID]],tBatches[[Active Pen Key]],0))&" +"&(COUNTIFS(tBatches[[Pen ID]],tPens[[#This Row],[Pen ID]],tBatches[[Status]],"Active")-1)&" more")) | F5: =IF(COUNTIFS(tBatches[[Pen ID]],tPens[[#This Row],[Pen ID]],tBatches[[Status]],"Active")=0,"",_xlfn.MINIFS(tBatches[[Batch Start Date]],tBatches[[Pen ID]],tPens[[#This Row],[Pen ID]],tBatches[[Status]],"Active")) | G5: =SUMIFS(tBatches[[Initial Quantity]],tBatches[[Pen ID]],tPens[[#This Row],[Pen ID]],tBatches[[Status]],"Active") | H5: =SUMIFS(tBatches[[Current Quantity]],tBatches[[Pen ID]],tPens[[#This Row],[Pen ID]],tBatches[[Status]],"Active") | I5: =IF(tPens[[#This Row],[Pen ID]]="","",IF(tPens[[#This Row],[Pen Closed]]="Yes","Closed",IF(COUNTIFS(tBatches[[Pen ID]],tPens[[#This Row],[Pen ID]],tBatches[[Status]],"Active")>0,"Active","Empty"))) | J5: No | K5: SAMPLE DATA - delete or replace | L5: =IF(AND(tPens[[#This Row],[Pen ID]]=""),"",IF(COUNTIF(tPens[[Pen ID]],tPens[[#This Row],[Pen ID]])>1,"Duplicate Pen ID",IF(tPens[[#This Row],[Pen ID]]="GENERAL","GENERAL is reserved - use another ID",IF(AND(tPens[[#This Row],[Pen Closed]]="Yes",COUNTIFS(tBatches[[Pen ID]],tPens[[#This Row],[Pen ID]],tBatches[[Status]],"Active")>0),"Pen marked closed but has an active batch","OK"))))
A6: P002 | B6: Broiler House 2 | C6: Main Farm | D6: Broiler | E6: =IF(COUNTIFS(tBatches[[Pen ID]],tPens[[#This Row],[Pen ID]],tBatches[[Status]],"Active")=0,"",IF(COUNTIFS(tBatches[[Pen ID]],tPens[[#This Row],[Pen ID]],tBatches[[Status]],"Active")=1,INDEX(tBatches[[Batch ID]],MATCH(tPens[[#This Row],[Pen ID]],tBatches[[Active Pen Key]],0)),INDEX(tBatches[[Batch ID]],MATCH(tPens[[#This Row],[Pen ID]],tBatches[[Active Pen Key]],0))&" +"&(COUNTIFS(tBatches[[Pen ID]],tPens[[#This Row],[Pen ID]],tBatches[[Status]],"Active")-1)&" more")) | F6: =IF(COUNTIFS(tBatches[[Pen ID]],tPens[[#This Row],[Pen ID]],tBatches[[Status]],"Active")=0,"",_xlfn.MINIFS(tBatches[[Batch Start Date]],tBatches[[Pen ID]],tPens[[#This Row],[Pen ID]],tBatches[[Status]],"Active")) | G6: =SUMIFS(tBatches[[Initial Quantity]],tBatches[[Pen ID]],tPens[[#This Row],[Pen ID]],tBatches[[Status]],"Active") | H6: =SUMIFS(tBatches[[Current Quantity]],tBatches[[Pen ID]],tPens[[#This Row],[Pen ID]],tBatches[[Status]],"Active") | I6: =IF(tPens[[#This Row],[Pen ID]]="","",IF(tPens[[#This Row],[Pen Closed]]="Yes","Closed",IF(COUNTIFS(tBatches[[Pen ID]],tPens[[#This Row],[Pen ID]],tBatches[[Status]],"Active")>0,"Active","Empty"))) | J6: No | K6: SAMPLE DATA - delete or replace | L6: =IF(AND(tPens[[#This Row],[Pen ID]]=""),"",IF(COUNTIF(tPens[[Pen ID]],tPens[[#This Row],[Pen ID]])>1,"Duplicate Pen ID",IF(tPens[[#This Row],[Pen ID]]="GENERAL","GENERAL is reserved - use another ID",IF(AND(tPens[[#This Row],[Pen Closed]]="Yes",COUNTIFS(tBatches[[Pen ID]],tPens[[#This Row],[Pen ID]],tBatches[[Status]],"Active")>0),"Pen marked closed but has an active batch","OK"))))
A7: P003 | B7: Broiler House 3 | C7: Main Farm | D7: Broiler | E7: =IF(COUNTIFS(tBatches[[Pen ID]],tPens[[#This Row],[Pen ID]],tBatches[[Status]],"Active")=0,"",IF(COUNTIFS(tBatches[[Pen ID]],tPens[[#This Row],[Pen ID]],tBatches[[Status]],"Active")=1,INDEX(tBatches[[Batch ID]],MATCH(tPens[[#This Row],[Pen ID]],tBatches[[Active Pen Key]],0)),INDEX(tBatches[[Batch ID]],MATCH(tPens[[#This Row],[Pen ID]],tBatches[[Active Pen Key]],0))&" +"&(COUNTIFS(tBatches[[Pen ID]],tPens[[#This Row],[Pen ID]],tBatches[[Status]],"Active")-1)&" more")) | F7: =IF(COUNTIFS(tBatches[[Pen ID]],tPens[[#This Row],[Pen ID]],tBatches[[Status]],"Active")=0,"",_xlfn.MINIFS(tBatches[[Batch Start Date]],tBatches[[Pen ID]],tPens[[#This Row],[Pen ID]],tBatches[[Status]],"Active")) | G7: =SUMIFS(tBatches[[Initial Quantity]],tBatches[[Pen ID]],tPens[[#This Row],[Pen ID]],tBatches[[Status]],"Active") | H7: =SUMIFS(tBatches[[Current Quantity]],tBatches[[Pen ID]],tPens[[#This Row],[Pen ID]],tBatches[[Status]],"Active") | I7: =IF(tPens[[#This Row],[Pen ID]]="","",IF(tPens[[#This Row],[Pen Closed]]="Yes","Closed",IF(COUNTIFS(tBatches[[Pen ID]],tPens[[#This Row],[Pen ID]],tBatches[[Status]],"Active")>0,"Active","Empty"))) | J7: No | K7: SAMPLE DATA - delete or replace | L7: =IF(AND(tPens[[#This Row],[Pen ID]]=""),"",IF(COUNTIF(tPens[[Pen ID]],tPens[[#This Row],[Pen ID]])>1,"Duplicate Pen ID",IF(tPens[[#This Row],[Pen ID]]="GENERAL","GENERAL is reserved - use another ID",IF(AND(tPens[[#This Row],[Pen Closed]]="Yes",COUNTIFS(tBatches[[Pen ID]],tPens[[#This Row],[Pen ID]],tBatches[[Status]],"Active")>0),"Pen marked closed but has an active batch","OK"))))
A8: P004 | B8: Broiler House 4 | C8: Main Farm | D8: Broiler | E8: =IF(COUNTIFS(tBatches[[Pen ID]],tPens[[#This Row],[Pen ID]],tBatches[[Status]],"Active")=0,"",IF(COUNTIFS(tBatches[[Pen ID]],tPens[[#This Row],[Pen ID]],tBatches[[Status]],"Active")=1,INDEX(tBatches[[Batch ID]],MATCH(tPens[[#This Row],[Pen ID]],tBatches[[Active Pen Key]],0)),INDEX(tBatches[[Batch ID]],MATCH(tPens[[#This Row],[Pen ID]],tBatches[[Active Pen Key]],0))&" +"&(COUNTIFS(tBatches[[Pen ID]],tPens[[#This Row],[Pen ID]],tBatches[[Status]],"Active")-1)&" more")) | F8: =IF(COUNTIFS(tBatches[[Pen ID]],tPens[[#This Row],[Pen ID]],tBatches[[Status]],"Active")=0,"",_xlfn.MINIFS(tBatches[[Batch Start Date]],tBatches[[Pen ID]],tPens[[#This Row],[Pen ID]],tBatches[[Status]],"Active")) | G8: =SUMIFS(tBatches[[Initial Quantity]],tBatches[[Pen ID]],tPens[[#This Row],[Pen ID]],tBatches[[Status]],"Active") | H8: =SUMIFS(tBatches[[Current Quantity]],tBatches[[Pen ID]],tPens[[#This Row],[Pen ID]],tBatches[[Status]],"Active") | I8: =IF(tPens[[#This Row],[Pen ID]]="","",IF(tPens[[#This Row],[Pen Closed]]="Yes","Closed",IF(COUNTIFS(tBatches[[Pen ID]],tPens[[#This Row],[Pen ID]],tBatches[[Status]],"Active")>0,"Active","Empty"))) | J8: No | K8: SAMPLE DATA - delete or replace | L8: =IF(AND(tPens[[#This Row],[Pen ID]]=""),"",IF(COUNTIF(tPens[[Pen ID]],tPens[[#This Row],[Pen ID]])>1,"Duplicate Pen ID",IF(tPens[[#This Row],[Pen ID]]="GENERAL","GENERAL is reserved - use another ID",IF(AND(tPens[[#This Row],[Pen Closed]]="Yes",COUNTIFS(tBatches[[Pen ID]],tPens[[#This Row],[Pen ID]],tBatches[[Status]],"Active")>0),"Pen marked closed but has an active batch","OK"))))
A9: P005 | B9: Layer House 1 | C9: Main Farm | D9: Layer | E9: =IF(COUNTIFS(tBatches[[Pen ID]],tPens[[#This Row],[Pen ID]],tBatches[[Status]],"Active")=0,"",IF(COUNTIFS(tBatches[[Pen ID]],tPens[[#This Row],[Pen ID]],tBatches[[Status]],"Active")=1,INDEX(tBatches[[Batch ID]],MATCH(tPens[[#This Row],[Pen ID]],tBatches[[Active Pen Key]],0)),INDEX(tBatches[[Batch ID]],MATCH(tPens[[#This Row],[Pen ID]],tBatches[[Active Pen Key]],0))&" +"&(COUNTIFS(tBatches[[Pen ID]],tPens[[#This Row],[Pen ID]],tBatches[[Status]],"Active")-1)&" more")) | F9: =IF(COUNTIFS(tBatches[[Pen ID]],tPens[[#This Row],[Pen ID]],tBatches[[Status]],"Active")=0,"",_xlfn.MINIFS(tBatches[[Batch Start Date]],tBatches[[Pen ID]],tPens[[#This Row],[Pen ID]],tBatches[[Status]],"Active")) | G9: =SUMIFS(tBatches[[Initial Quantity]],tBatches[[Pen ID]],tPens[[#This Row],[Pen ID]],tBatches[[Status]],"Active") | H9: =SUMIFS(tBatches[[Current Quantity]],tBatches[[Pen ID]],tPens[[#This Row],[Pen ID]],tBatches[[Status]],"Active") | I9: =IF(tPens[[#This Row],[Pen ID]]="","",IF(tPens[[#This Row],[Pen Closed]]="Yes","Closed",IF(COUNTIFS(tBatches[[Pen ID]],tPens[[#This Row],[Pen ID]],tBatches[[Status]],"Active")>0,"Active","Empty"))) | J9: No | K9: SAMPLE DATA - delete or replace | L9: =IF(AND(tPens[[#This Row],[Pen ID]]=""),"",IF(COUNTIF(tPens[[Pen ID]],tPens[[#This Row],[Pen ID]])>1,"Duplicate Pen ID",IF(tPens[[#This Row],[Pen ID]]="GENERAL","GENERAL is reserved - use another ID",IF(AND(tPens[[#This Row],[Pen Closed]]="Yes",COUNTIFS(tBatches[[Pen ID]],tPens[[#This Row],[Pen ID]],tBatches[[Status]],"Active")>0),"Pen marked closed but has an active batch","OK"))))
A10: P006 | B10: Broiler House 5 | C10: Annex | D10: Broiler | E10: =IF(COUNTIFS(tBatches[[Pen ID]],tPens[[#This Row],[Pen ID]],tBatches[[Status]],"Active")=0,"",IF(COUNTIFS(tBatches[[Pen ID]],tPens[[#This Row],[Pen ID]],tBatches[[Status]],"Active")=1,INDEX(tBatches[[Batch ID]],MATCH(tPens[[#This Row],[Pen ID]],tBatches[[Active Pen Key]],0)),INDEX(tBatches[[Batch ID]],MATCH(tPens[[#This Row],[Pen ID]],tBatches[[Active Pen Key]],0))&" +"&(COUNTIFS(tBatches[[Pen ID]],tPens[[#This Row],[Pen ID]],tBatches[[Status]],"Active")-1)&" more")) | F10: =IF(COUNTIFS(tBatches[[Pen ID]],tPens[[#This Row],[Pen ID]],tBatches[[Status]],"Active")=0,"",_xlfn.MINIFS(tBatches[[Batch Start Date]],tBatches[[Pen ID]],tPens[[#This Row],[Pen ID]],tBatches[[Status]],"Active")) | G10: =SUMIFS(tBatches[[Initial Quantity]],tBatches[[Pen ID]],tPens[[#This Row],[Pen ID]],tBatches[[Status]],"Active") | H10: =SUMIFS(tBatches[[Current Quantity]],tBatches[[Pen ID]],tPens[[#This Row],[Pen ID]],tBatches[[Status]],"Active") | I10: =IF(tPens[[#This Row],[Pen ID]]="","",IF(tPens[[#This Row],[Pen Closed]]="Yes","Closed",IF(COUNTIFS(tBatches[[Pen ID]],tPens[[#This Row],[Pen ID]],tBatches[[Status]],"Active")>0,"Active","Empty"))) | J10: No | K10: SAMPLE DATA - delete or replace | L10: =IF(AND(tPens[[#This Row],[Pen ID]]=""),"",IF(COUNTIF(tPens[[Pen ID]],tPens[[#This Row],[Pen ID]])>1,"Duplicate Pen ID",IF(tPens[[#This Row],[Pen ID]]="GENERAL","GENERAL is reserved - use another ID",IF(AND(tPens[[#This Row],[Pen Closed]]="Yes",COUNTIFS(tBatches[[Pen ID]],tPens[[#This Row],[Pen ID]],tBatches[[Status]],"Active")>0),"Pen marked closed but has an active batch","OK"))))

Sheet BATCH_REGISTER
A1: BATCH REGISTER
A2: One row per production cycle. A batch lives in one pen. When finished set Status = Closed and enter the Closing Date - its history is kept for ever and the pen becomes free for a new batch.
A3: ■ GREEN header = you enter / select ■ GREY header = automatic (do not type) Add a new record by typing in the first empty row directly under the table.
A4: Batch ID | B4: Pen ID | C4: Animal Type | D4: Batch Start Date | E4: Initial Quantity | F4: Source/Supplier | G4: Breed/Type | H4: Current Quantity | I4: Closing Date | J4: Status | K4: Notes | L4: Transfers In / Added | M4: Deaths | N4: Heads Sold | O4: Transfers Out | P4: Total Placed | Q4: Age (days) | R4: Active Pen Key | S4: Check
A5: BROILER-SEP-001 | B5: P001 | C5: Broiler | D5: 46266 | E5: 500 | F5: Hatchery (sample) | G5: Cobb 500 | H5: =tBatches[[#This Row],[Total Placed]]-tBatches[[#This Row],[Deaths]]-tBatches[[#This Row],[Heads Sold]]-tBatches[[#This Row],[Transfers Out]] | J5: Active | K5: SAMPLE DATA - delete or replace | L5: =SUMIFS(tMoves[[Quantity In]],tMoves[[Batch ID]],tBatches[[#This Row],[Batch ID]]) | M5: =SUMIFS(tMort[[Number of Deaths]],tMort[[Batch ID]],tBatches[[#This Row],[Batch ID]]) | N5: =SUMIFS(tSales[[Heads Removed]],tSales[[Batch ID]],tBatches[[#This Row],[Batch ID]]) | O5: =SUMIFS(tMoves[[Quantity Out]],tMoves[[Batch ID]],tBatches[[#This Row],[Batch ID]]) | P5: =N(tBatches[[#This Row],[Initial Quantity]])+tBatches[[#This Row],[Transfers In / Added]] | Q5: =IF(NOT(ISNUMBER(tBatches[[#This Row],[Batch Start Date]])),"",IF(N(tBatches[[#This Row],[Closing Date]])>0,tBatches[[#This Row],[Closing Date]],TODAY())-tBatches[[#This Row],[Batch Start Date]]+1) | R5: =IF(tBatches[[#This Row],[Status]]="Active",tBatches[[#This Row],[Pen ID]],"") | S5: =IF(AND(tBatches[[#This Row],[Batch ID]]="",tBatches[[#This Row],[Pen ID]]=""),"",IF(tBatches[[#This Row],[Batch ID]]="","Missing Batch ID",IF(COUNTIF(tBatches[[Batch ID]],tBatches[[#This Row],[Batch ID]])>1,"Duplicate Batch ID",IF(COUNTIF(tPens[[Pen ID]],tBatches[[#This Row],[Pen ID]])=0,"Pen is not in PEN_REGISTER",IF(NOT(ISNUMBER(tBatches[[#This Row],[Batch Start Date]])),"Missing start date",IF(N(tBatches[[#This Row],[Initial Quantity]])<=0,"Initial quantity must be > 0",IF(tBatches[[#This Row],[Status]]="","Missing status",IF(tBatches[[#This Row],[Current Quantity]]<0,"Negative stock - more deaths/sales than animals",IF(AND(tBatches[[#This Row],[Status]]="Closed",N(tBatches[[#This Row],[Closing Date]])=0),"Closed batch needs a closing date",IF(AND(tBatches[[#This Row],[Status]]="Closed",tBatches[[#This Row],[Current Quantity]]>0),"Closed with "&tBatches[[#This Row],[Current Quantity]]&" animals unaccounted for",IF(AND(N(tBatches[[#This Row],[Closing Date]])>0,N(tBatches[[#This Row],[Closing Date]])<tBatches[[#This Row],[Batch Start Date]]),"Closing date is before start date","OK")))))))))))
A6: BROILER-SEP-002 | B6: P002 | C6: Broiler | D6: 46266 | E6: 600 | F6: Hatchery (sample) | G6: Ross 308 | H6: =tBatches[[#This Row],[Total Placed]]-tBatches[[#This Row],[Deaths]]-tBatches[[#This Row],[Heads Sold]]-tBatches[[#This Row],[Transfers Out]] | J6: Active | K6: SAMPLE DATA - delete or replace | L6: =SUMIFS(tMoves[[Quantity In]],tMoves[[Batch ID]],tBatches[[#This Row],[Batch ID]]) | M6: =SUMIFS(tMort[[Number of Deaths]],tMort[[Batch ID]],tBatches[[#This Row],[Batch ID]]) | N6: =SUMIFS(tSales[[Heads Removed]],tSales[[Batch ID]],tBatches[[#This Row],[Batch ID]]) | O6: =SUMIFS(tMoves[[Quantity Out]],tMoves[[Batch ID]],tBatches[[#This Row],[Batch ID]]) | P6: =N(tBatches[[#This Row],[Initial Quantity]])+tBatches[[#This Row],[Transfers In / Added]] | Q6: =IF(NOT(ISNUMBER(tBatches[[#This Row],[Batch Start Date]])),"",IF(N(tBatches[[#This Row],[Closing Date]])>0,tBatches[[#This Row],[Closing Date]],TODAY())-tBatches[[#This Row],[Batch Start Date]]+1) | R6: =IF(tBatches[[#This Row],[Status]]="Active",tBatches[[#This Row],[Pen ID]],"") | S6: =IF(AND(tBatches[[#This Row],[Batch ID]]="",tBatches[[#This Row],[Pen ID]]=""),"",IF(tBatches[[#This Row],[Batch ID]]="","Missing Batch ID",IF(COUNTIF(tBatches[[Batch ID]],tBatches[[#This Row],[Batch ID]])>1,"Duplicate Batch ID",IF(COUNTIF(tPens[[Pen ID]],tBatches[[#This Row],[Pen ID]])=0,"Pen is not in PEN_REGISTER",IF(NOT(ISNUMBER(tBatches[[#This Row],[Batch Start Date]])),"Missing start date",IF(N(tBatches[[#This Row],[Initial Quantity]])<=0,"Initial quantity must be > 0",IF(tBatches[[#This Row],[Status]]="","Missing status",IF(tBatches[[#This Row],[Current Quantity]]<0,"Negative stock - more deaths/sales than animals",IF(AND(tBatches[[#This Row],[Status]]="Closed",N(tBatches[[#This Row],[Closing Date]])=0),"Closed batch needs a closing date",IF(AND(tBatches[[#This Row],[Status]]="Closed",tBatches[[#This Row],[Current Quantity]]>0),"Closed with "&tBatches[[#This Row],[Current Quantity]]&" animals unaccounted for",IF(AND(N(tBatches[[#This Row],[Closing Date]])>0,N(tBatches[[#This Row],[Closing Date]])<tBatches[[#This Row],[Batch Start Date]]),"Closing date is before start date","OK")))))))))))
A7: BROILER-SEP-003 | B7: P003 | C7: Broiler | D7: 46267 | E7: 450 | F7: Hatchery (sample) | G7: Cobb 500 | H7: =tBatches[[#This Row],[Total Placed]]-tBatches[[#This Row],[Deaths]]-tBatches[[#This Row],[Heads Sold]]-tBatches[[#This Row],[Transfers Out]] | J7: Active | K7: SAMPLE DATA - delete or replace | L7: =SUMIFS(tMoves[[Quantity In]],tMoves[[Batch ID]],tBatches[[#This Row],[Batch ID]]) | M7: =SUMIFS(tMort[[Number of Deaths]],tMort[[Batch ID]],tBatches[[#This Row],[Batch ID]]) | N7: =SUMIFS(tSales[[Heads Removed]],tSales[[Batch ID]],tBatches[[#This Row],[Batch ID]]) | O7: =SUMIFS(tMoves[[Quantity Out]],tMoves[[Batch ID]],tBatches[[#This Row],[Batch ID]]) | P7: =N(tBatches[[#This Row],[Initial Quantity]])+tBatches[[#This Row],[Transfers In / Added]] | Q7: =IF(NOT(ISNUMBER(tBatches[[#This Row],[Batch Start Date]])),"",IF(N(tBatches[[#This Row],[Closing Date]])>0,tBatches[[#This Row],[Closing Date]],TODAY())-tBatches[[#This Row],[Batch Start Date]]+1) | R7: =IF(tBatches[[#This Row],[Status]]="Active",tBatches[[#This Row],[Pen ID]],"") | S7: =IF(AND(tBatches[[#This Row],[Batch ID]]="",tBatches[[#This Row],[Pen ID]]=""),"",IF(tBatches[[#This Row],[Batch ID]]="","Missing Batch ID",IF(COUNTIF(tBatches[[Batch ID]],tBatches[[#This Row],[Batch ID]])>1,"Duplicate Batch ID",IF(COUNTIF(tPens[[Pen ID]],tBatches[[#This Row],[Pen ID]])=0,"Pen is not in PEN_REGISTER",IF(NOT(ISNUMBER(tBatches[[#This Row],[Batch Start Date]])),"Missing start date",IF(N(tBatches[[#This Row],[Initial Quantity]])<=0,"Initial quantity must be > 0",IF(tBatches[[#This Row],[Status]]="","Missing status",IF(tBatches[[#This Row],[Current Quantity]]<0,"Negative stock - more deaths/sales than animals",IF(AND(tBatches[[#This Row],[Status]]="Closed",N(tBatches[[#This Row],[Closing Date]])=0),"Closed batch needs a closing date",IF(AND(tBatches[[#This Row],[Status]]="Closed",tBatches[[#This Row],[Current Quantity]]>0),"Closed with "&tBatches[[#This Row],[Current Quantity]]&" animals unaccounted for",IF(AND(N(tBatches[[#This Row],[Closing Date]])>0,N(tBatches[[#This Row],[Closing Date]])<tBatches[[#This Row],[Batch Start Date]]),"Closing date is before start date","OK")))))))))))
A8: BROILER-SEP-004 | B8: P004 | C8: Broiler | D8: 46267 | E8: 550 | F8: Hatchery (sample) | G8: Arbor Acres | H8: =tBatches[[#This Row],[Total Placed]]-tBatches[[#This Row],[Deaths]]-tBatches[[#This Row],[Heads Sold]]-tBatches[[#This Row],[Transfers Out]] | J8: Active | K8: SAMPLE DATA - delete or replace | L8: =SUMIFS(tMoves[[Quantity In]],tMoves[[Batch ID]],tBatches[[#This Row],[Batch ID]]) | M8: =SUMIFS(tMort[[Number of Deaths]],tMort[[Batch ID]],tBatches[[#This Row],[Batch ID]]) | N8: =SUMIFS(tSales[[Heads Removed]],tSales[[Batch ID]],tBatches[[#This Row],[Batch ID]]) | O8: =SUMIFS(tMoves[[Quantity Out]],tMoves[[Batch ID]],tBatches[[#This Row],[Batch ID]]) | P8: =N(tBatches[[#This Row],[Initial Quantity]])+tBatches[[#This Row],[Transfers In / Added]] | Q8: =IF(NOT(ISNUMBER(tBatches[[#This Row],[Batch Start Date]])),"",IF(N(tBatches[[#This Row],[Closing Date]])>0,tBatches[[#This Row],[Closing Date]],TODAY())-tBatches[[#This Row],[Batch Start Date]]+1) | R8: =IF(tBatches[[#This Row],[Status]]="Active",tBatches[[#This Row],[Pen ID]],"") | S8: =IF(AND(tBatches[[#This Row],[Batch ID]]="",tBatches[[#This Row],[Pen ID]]=""),"",IF(tBatches[[#This Row],[Batch ID]]="","Missing Batch ID",IF(COUNTIF(tBatches[[Batch ID]],tBatches[[#This Row],[Batch ID]])>1,"Duplicate Batch ID",IF(COUNTIF(tPens[[Pen ID]],tBatches[[#This Row],[Pen ID]])=0,"Pen is not in PEN_REGISTER",IF(NOT(ISNUMBER(tBatches[[#This Row],[Batch Start Date]])),"Missing start date",IF(N(tBatches[[#This Row],[Initial Quantity]])<=0,"Initial quantity must be > 0",IF(tBatches[[#This Row],[Status]]="","Missing status",IF(tBatches[[#This Row],[Current Quantity]]<0,"Negative stock - more deaths/sales than animals",IF(AND(tBatches[[#This Row],[Status]]="Closed",N(tBatches[[#This Row],[Closing Date]])=0),"Closed batch needs a closing date",IF(AND(tBatches[[#This Row],[Status]]="Closed",tBatches[[#This Row],[Current Quantity]]>0),"Closed with "&tBatches[[#This Row],[Current Quantity]]&" animals unaccounted for",IF(AND(N(tBatches[[#This Row],[Closing Date]])>0,N(tBatches[[#This Row],[Closing Date]])<tBatches[[#This Row],[Batch Start Date]]),"Closing date is before start date","OK")))))))))))
A9: LAYER-JUN-001 | B9: P005 | C9: Layer | D9: 46174 | E9: 400 | F9: Hatchery (sample) | G9: Isa Brown (point-of-lay) | H9: =tBatches[[#This Row],[Total Placed]]-tBatches[[#This Row],[Deaths]]-tBatches[[#This Row],[Heads Sold]]-tBatches[[#This Row],[Transfers Out]] | J9: Active | K9: SAMPLE DATA - delete or replace | L9: =SUMIFS(tMoves[[Quantity In]],tMoves[[Batch ID]],tBatches[[#This Row],[Batch ID]]) | M9: =SUMIFS(tMort[[Number of Deaths]],tMort[[Batch ID]],tBatches[[#This Row],[Batch ID]]) | N9: =SUMIFS(tSales[[Heads Removed]],tSales[[Batch ID]],tBatches[[#This Row],[Batch ID]]) | O9: =SUMIFS(tMoves[[Quantity Out]],tMoves[[Batch ID]],tBatches[[#This Row],[Batch ID]]) | P9: =N(tBatches[[#This Row],[Initial Quantity]])+tBatches[[#This Row],[Transfers In / Added]] | Q9: =IF(NOT(ISNUMBER(tBatches[[#This Row],[Batch Start Date]])),"",IF(N(tBatches[[#This Row],[Closing Date]])>0,tBatches[[#This Row],[Closing Date]],TODAY())-tBatches[[#This Row],[Batch Start Date]]+1) | R9: =IF(tBatches[[#This Row],[Status]]="Active",tBatches[[#This Row],[Pen ID]],"") | S9: =IF(AND(tBatches[[#This Row],[Batch ID]]="",tBatches[[#This Row],[Pen ID]]=""),"",IF(tBatches[[#This Row],[Batch ID]]="","Missing Batch ID",IF(COUNTIF(tBatches[[Batch ID]],tBatches[[#This Row],[Batch ID]])>1,"Duplicate Batch ID",IF(COUNTIF(tPens[[Pen ID]],tBatches[[#This Row],[Pen ID]])=0,"Pen is not in PEN_REGISTER",IF(NOT(ISNUMBER(tBatches[[#This Row],[Batch Start Date]])),"Missing start date",IF(N(tBatches[[#This Row],[Initial Quantity]])<=0,"Initial quantity must be > 0",IF(tBatches[[#This Row],[Status]]="","Missing status",IF(tBatches[[#This Row],[Current Quantity]]<0,"Negative stock - more deaths/sales than animals",IF(AND(tBatches[[#This Row],[Status]]="Closed",N(tBatches[[#This Row],[Closing Date]])=0),"Closed batch needs a closing date",IF(AND(tBatches[[#This Row],[Status]]="Closed",tBatches[[#This Row],[Current Quantity]]>0),"Closed with "&tBatches[[#This Row],[Current Quantity]]&" animals unaccounted for",IF(AND(N(tBatches[[#This Row],[Closing Date]])>0,N(tBatches[[#This Row],[Closing Date]])<tBatches[[#This Row],[Batch Start Date]]),"Closing date is before start date","OK")))))))))))
A10: BROILER-JUL-001 | B10: P006 | C10: Broiler | D10: 46204 | E10: 300 | F10: Hatchery (sample) | G10: Cobb 500 | H10: =tBatches[[#This Row],[Total Placed]]-tBatches[[#This Row],[Deaths]]-tBatches[[#This Row],[Heads Sold]]-tBatches[[#This Row],[Transfers Out]] | I10: 46252 | J10: Closed | K10: SAMPLE DATA - delete or replace. Closed batch: history kept, pen P006 now Empty and can take a new batch. | L10: =SUMIFS(tMoves[[Quantity In]],tMoves[[Batch ID]],tBatches[[#This Row],[Batch ID]]) | M10: =SUMIFS(tMort[[Number of Deaths]],tMort[[Batch ID]],tBatches[[#This Row],[Batch ID]]) | N10: =SUMIFS(tSales[[Heads Removed]],tSales[[Batch ID]],tBatches[[#This Row],[Batch ID]]) | O10: =SUMIFS(tMoves[[Quantity Out]],tMoves[[Batch ID]],tBatches[[#This Row],[Batch ID]]) | P10: =N(tBatches[[#This Row],[Initial Quantity]])+tBatches[[#This Row],[Transfers In / Added]] | Q10: =IF(NOT(ISNUMBER(tBatches[[#This Row],[Batch Start Date]])),"",IF(N(tBatches[[#This Row],[Closing Date]])>0,tBatches[[#This Row],[Closing Date]],TODAY())-tBatches[[#This Row],[Batch Start Date]]+1) | R10: =IF(tBatches[[#This Row],[Status]]="Active",tBatches[[#This Row],[Pen ID]],"") | S10: =IF(AND(tBatches[[#This Row],[Batch ID]]="",tBatches[[#This Row],[Pen ID]]=""),"",IF(tBatches[[#This Row],[Batch ID]]="","Missing Batch ID",IF(COUNTIF(tBatches[[Batch ID]],tBatches[[#This Row],[Batch ID]])>1,"Duplicate Batch ID",IF(COUNTIF(tPens[[Pen ID]],tBatches[[#This Row],[Pen ID]])=0,"Pen is not in PEN_REGISTER",IF(NOT(ISNUMBER(tBatches[[#This Row],[Batch Start Date]])),"Missing start date",IF(N(tBatches[[#This Row],[Initial Quantity]])<=0,"Initial quantity must be > 0",IF(tBatches[[#This Row],[Status]]="","Missing status",IF(tBatches[[#This Row],[Current Quantity]]<0,"Negative stock - more deaths/sales than animals",IF(AND(tBatches[[#This Row],[Status]]="Closed",N(tBatches[[#This Row],[Closing Date]])=0),"Closed batch needs a closing date",IF(AND(tBatches[[#This Row],[Status]]="Closed",tBatches[[#This Row],[Current Quantity]]>0),"Closed with "&tBatches[[#This Row],[Current Quantity]]&" animals unaccounted for",IF(AND(N(tBatches[[#This Row],[Closing Date]])>0,N(tBatches[[#This Row],[Closing Date]])<tBatches[[#This Row],[Batch Start Date]]),"Closing date is before start date","OK")))))))))))

Sheet FEED_PURCHASES
A1: FEED PURCHASES
A2: Record each purchase ONCE. Feed goes into the store (INVENTORY) - it only becomes a pen/batch cost when it is issued on FEED_ISSUES. Inventory unit = kg.
A3: ■ GREEN header = you enter / select ■ GREY header = automatic (do not type) Add a new record by typing in the first empty row directly under the table.
A4: Date | B4: Purchase ID | C4: Feed Type | D4: Supplier | E4: Quantity in Bags | F4: Bag Size in kg | G4: Total Quantity in kg | H4: Price per Bag | I4: Total Cost | J4: Cost per kg | K4: Payment Method | L4: Reference | M4: Notes | N4: Purchase No. of Type | O4: Stock Before Purchase kg | P4: Avg Cost per kg After Purchase | Q4: Check
A5: 46204 | B5: ="FP-"&TEXT(ROW()-ROW(tFeedPur[[#Headers],[Date]]),"00000") | C5: Starter | D5: Feed Supplier A (sample) | E5: 12 | F5: 25 | G5: =N(tFeedPur[[#This Row],[Quantity in Bags]])*N(tFeedPur[[#This Row],[Bag Size in kg]]) | H5: 14000 | I5: =N(tFeedPur[[#This Row],[Quantity in Bags]])*N(tFeedPur[[#This Row],[Price per Bag]]) | J5: =IFERROR(tFeedPur[[#This Row],[Total Cost]]/tFeedPur[[#This Row],[Total Quantity in kg]],0) | K5: Transfer | L5: INV-1001 | M5: SAMPLE DATA - delete or replace | N5: =COUNTIF(INDEX(tFeedPur[[Feed Type]],1):tFeedPur[[#This Row],[Feed Type]],tFeedPur[[#This Row],[Feed Type]]) | O5: =MAX(0,IF((ROW()-ROW(tFeedPur[[#Headers],[Date]]))=1,0,SUMIFS(INDEX(tFeedPur[[Total Quantity in kg]],1):INDEX(tFeedPur[[Total Quantity in kg]],(ROW()-ROW(tFeedPur[[#Headers],[Date]]))-1),INDEX(tFeedPur[[Feed Type]],1):INDEX(tFeedPur[[Feed Type]],(ROW()-ROW(tFeedPur[[#Headers],[Date]]))-1),tFeedPur[[#This Row],[Feed Type]]))-SUMIFS(tFeedIss[[Quantity Issued in kg]],tFeedIss[[Feed Type]],tFeedPur[[#This Row],[Feed Type]],tFeedIss[[Date]],"<"&tFeedPur[[#This Row],[Date]])) | P5: =IFERROR((tFeedPur[[#This Row],[Stock Before Purchase kg]]*IF(tFeedPur[[#This Row],[Purchase No. of Type]]=1,0,LOOKUP(2,1/(INDEX(tFeedPur[[Feed Type]],1):INDEX(tFeedPur[[Feed Type]],(ROW()-ROW(tFeedPur[[#Headers],[Date]]))-1)=tFeedPur[[#This Row],[Feed Type]]),INDEX(tFeedPur[[Avg Cost per kg After Purchase]],1):INDEX(tFeedPur[[Avg Cost per kg After Purchase]],(ROW()-ROW(tFeedPur[[#Headers],[Date]]))-1)))+N(tFeedPur[[#This Row],[Total Cost]]))/(tFeedPur[[#This Row],[Stock Before Purchase kg]]+N(tFeedPur[[#This Row],[Total Quantity in kg]])),IF(tFeedPur[[#This Row],[Purchase No. of Type]]=1,0,LOOKUP(2,1/(INDEX(tFeedPur[[Feed Type]],1):INDEX(tFeedPur[[Feed Type]],(ROW()-ROW(tFeedPur[[#Headers],[Date]]))-1)=tFeedPur[[#This Row],[Feed Type]]),INDEX(tFeedPur[[Avg Cost per kg After Purchase]],1):INDEX(tFeedPur[[Avg Cost per kg After Purchase]],(ROW()-ROW(tFeedPur[[#Headers],[Date]]))-1)))) | Q5: =IF(AND(tFeedPur[[#This Row],[Date]]="",tFeedPur[[#This Row],[Feed Type]]="",tFeedPur[[#This Row],[Quantity in Bags]]=""),"",IF(tFeedPur[[#This Row],[Date]]="","Missing date",IF(NOT(ISNUMBER(tFeedPur[[#This Row],[Date]])),"Date is not a valid date",IF(AND((ROW()-ROW(tFeedPur[[#Headers],[Date]]))>1,tFeedPur[[#This Row],[Date]]<INDEX(tFeedPur[[Date]],MAX(1,(ROW()-ROW(tFeedPur[[#Headers],[Date]]))-1))),"Out of date order - insert this row after earlier purchases",IF(tFeedPur[[#This Row],[Feed Type]]="","Missing feed type",IF(COUNTIF(tFeedTypes[[Feed Type]],tFeedPur[[#This Row],[Feed Type]])=0,"Feed type not in LISTS",IF(N(tFeedPur[[#This Row],[Quantity in Bags]])<=0,"Bags must be greater than 0",IF(N(tFeedPur[[#This Row],[Bag Size in kg]])<=0,"Missing bag size",IF(tFeedPur[[#This Row],[Price per Bag]]="","Missing price",IF(tFeedPur[[#This Row],[Payment Method]]="","Missing payment method","OK"))))))))))
A6: 46204 | B6: ="FP-"&TEXT(ROW()-ROW(tFeedPur[[#Headers],[Date]]),"00000") | C6: Layer Mash | D6: Feed Supplier A (sample) | E6: 20 | F6: 25 | G6: =N(tFeedPur[[#This Row],[Quantity in Bags]])*N(tFeedPur[[#This Row],[Bag Size in kg]]) | H6: 13500 | I6: =N(tFeedPur[[#This Row],[Quantity in Bags]])*N(tFeedPur[[#This Row],[Price per Bag]]) | J6: =IFERROR(tFeedPur[[#This Row],[Total Cost]]/tFeedPur[[#This Row],[Total Quantity in kg]],0) | K6: Transfer | L6: INV-1002 | M6: SAMPLE DATA - delete or replace | N6: =COUNTIF(INDEX(tFeedPur[[Feed Type]],1):tFeedPur[[#This Row],[Feed Type]],tFeedPur[[#This Row],[Feed Type]]) | O6: =MAX(0,IF((ROW()-ROW(tFeedPur[[#Headers],[Date]]))=1,0,SUMIFS(INDEX(tFeedPur[[Total Quantity in kg]],1):INDEX(tFeedPur[[Total Quantity in kg]],(ROW()-ROW(tFeedPur[[#Headers],[Date]]))-1),INDEX(tFeedPur[[Feed Type]],1):INDEX(tFeedPur[[Feed Type]],(ROW()-ROW(tFeedPur[[#Headers],[Date]]))-1),tFeedPur[[#This Row],[Feed Type]]))-SUMIFS(tFeedIss[[Quantity Issued in kg]],tFeedIss[[Feed Type]],tFeedPur[[#This Row],[Feed Type]],tFeedIss[[Date]],"<"&tFeedPur[[#This Row],[Date]])) | P6: =IFERROR((tFeedPur[[#This Row],[Stock Before Purchase kg]]*IF(tFeedPur[[#This Row],[Purchase No. of Type]]=1,0,LOOKUP(2,1/(INDEX(tFeedPur[[Feed Type]],1):INDEX(tFeedPur[[Feed Type]],(ROW()-ROW(tFeedPur[[#Headers],[Date]]))-1)=tFeedPur[[#This Row],[Feed Type]]),INDEX(tFeedPur[[Avg Cost per kg After Purchase]],1):INDEX(tFeedPur[[Avg Cost per kg After Purchase]],(ROW()-ROW(tFeedPur[[#Headers],[Date]]))-1)))+N(tFeedPur[[#This Row],[Total Cost]]))/(tFeedPur[[#This Row],[Stock Before Purchase kg]]+N(tFeedPur[[#This Row],[Total Quantity in kg]])),IF(tFeedPur[[#This Row],[Purchase No. of Type]]=1,0,LOOKUP(2,1/(INDEX(tFeedPur[[Feed Type]],1):INDEX(tFeedPur[[Feed Type]],(ROW()-ROW(tFeedPur[[#Headers],[Date]]))-1)=tFeedPur[[#This Row],[Feed Type]]),INDEX(tFeedPur[[Avg Cost per kg After Purchase]],1):INDEX(tFeedPur[[Avg Cost per kg After Purchase]],(ROW()-ROW(tFeedPur[[#Headers],[Date]]))-1)))) | Q6: =IF(AND(tFeedPur[[#This Row],[Date]]="",tFeedPur[[#This Row],[Feed Type]]="",tFeedPur[[#This Row],[Quantity in Bags]]=""),"",IF(tFeedPur[[#This Row],[Date]]="","Missing date",IF(NOT(ISNUMBER(tFeedPur[[#This Row],[Date]])),"Date is not a valid date",IF(AND((ROW()-ROW(tFeedPur[[#Headers],[Date]]))>1,tFeedPur[[#This Row],[Date]]<INDEX(tFeedPur[[Date]],MAX(1,(ROW()-ROW(tFeedPur[[#Headers],[Date]]))-1))),"Out of date order - insert this row after earlier purchases",IF(tFeedPur[[#This Row],[Feed Type]]="","Missing feed type",IF(COUNTIF(tFeedTypes[[Feed Type]],tFeedPur[[#This Row],[Feed Type]])=0,"Feed type not in LISTS",IF(N(tFeedPur[[#This Row],[Quantity in Bags]])<=0,"Bags must be greater than 0",IF(N(tFeedPur[[#This Row],[Bag Size in kg]])<=0,"Missing bag size",IF(tFeedPur[[#This Row],[Price per Bag]]="","Missing price",IF(tFeedPur[[#This Row],[Payment Method]]="","Missing payment method","OK"))))))))))
A7: 46223 | B7: ="FP-"&TEXT(ROW()-ROW(tFeedPur[[#Headers],[Date]]),"00000") | C7: Finisher | D7: Feed Supplier B (sample) | E7: 12 | F7: 25 | G7: =N(tFeedPur[[#This Row],[Quantity in Bags]])*N(tFeedPur[[#This Row],[Bag Size in kg]]) | H7: 14500 | I7: =N(tFeedPur[[#This Row],[Quantity in Bags]])*N(tFeedPur[[#This Row],[Price per Bag]]) | J7: =IFERROR(tFeedPur[[#This Row],[Total Cost]]/tFeedPur[[#This Row],[Total Quantity in kg]],0) | K7: Cash | L7: RCPT-220 | M7: SAMPLE DATA - delete or replace | N7: =COUNTIF(INDEX(tFeedPur[[Feed Type]],1):tFeedPur[[#This Row],[Feed Type]],tFeedPur[[#This Row],[Feed Type]]) | O7: =MAX(0,IF((ROW()-ROW(tFeedPur[[#Headers],[Date]]))=1,0,SUMIFS(INDEX(tFeedPur[[Total Quantity in kg]],1):INDEX(tFeedPur[[Total Quantity in kg]],(ROW()-ROW(tFeedPur[[#Headers],[Date]]))-1),INDEX(tFeedPur[[Feed Type]],1):INDEX(tFeedPur[[Feed Type]],(ROW()-ROW(tFeedPur[[#Headers],[Date]]))-1),tFeedPur[[#This Row],[Feed Type]]))-SUMIFS(tFeedIss[[Quantity Issued in kg]],tFeedIss[[Feed Type]],tFeedPur[[#This Row],[Feed Type]],tFeedIss[[Date]],"<"&tFeedPur[[#This Row],[Date]])) | P7: =IFERROR((tFeedPur[[#This Row],[Stock Before Purchase kg]]*IF(tFeedPur[[#This Row],[Purchase No. of Type]]=1,0,LOOKUP(2,1/(INDEX(tFeedPur[[Feed Type]],1):INDEX(tFeedPur[[Feed Type]],(ROW()-ROW(tFeedPur[[#Headers],[Date]]))-1)=tFeedPur[[#This Row],[Feed Type]]),INDEX(tFeedPur[[Avg Cost per kg After Purchase]],1):INDEX(tFeedPur[[Avg Cost per kg After Purchase]],(ROW()-ROW(tFeedPur[[#Headers],[Date]]))-1)))+N(tFeedPur[[#This Row],[Total Cost]]))/(tFeedPur[[#This Row],[Stock Before Purchase kg]]+N(tFeedPur[[#This Row],[Total Quantity in kg]])),IF(tFeedPur[[#This Row],[Purchase No. of Type]]=1,0,LOOKUP(2,1/(INDEX(tFeedPur[[Feed Type]],1):INDEX(tFeedPur[[Feed Type]],(ROW()-ROW(tFeedPur[[#Headers],[Date]]))-1)=tFeedPur[[#This Row],[Feed Type]]),INDEX(tFeedPur[[Avg Cost per kg After Purchase]],1):INDEX(tFeedPur[[Avg Cost per kg After Purchase]],(ROW()-ROW(tFeedPur[[#Headers],[Date]]))-1)))) | Q7: =IF(AND(tFeedPur[[#This Row],[Date]]="",tFeedPur[[#This Row],[Feed Type]]="",tFeedPur[[#This Row],[Quantity in Bags]]=""),"",IF(tFeedPur[[#This Row],[Date]]="","Missing date",IF(NOT(ISNUMBER(tFeedPur[[#This Row],[Date]])),"Date is not a valid date",IF(AND((ROW()-ROW(tFeedPur[[#Headers],[Date]]))>1,tFeedPur[[#This Row],[Date]]<INDEX(tFeedPur[[Date]],MAX(1,(ROW()-ROW(tFeedPur[[#Headers],[Date]]))-1))),"Out of date order - insert this row after earlier purchases",IF(tFeedPur[[#This Row],[Feed Type]]="","Missing feed type",IF(COUNTIF(tFeedTypes[[Feed Type]],tFeedPur[[#This Row],[Feed Type]])=0,"Feed type not in LISTS",IF(N(tFeedPur[[#This Row],[Quantity in Bags]])<=0,"Bags must be greater than 0",IF(N(tFeedPur[[#This Row],[Bag Size in kg]])<=0,"Missing bag size",IF(tFeedPur[[#This Row],[Price per Bag]]="","Missing price",IF(tFeedPur[[#This Row],[Payment Method]]="","Missing payment method","OK"))))))))))
A8: 46264 | B8: ="FP-"&TEXT(ROW()-ROW(tFeedPur[[#Headers],[Date]]),"00000") | C8: Starter | D8: Feed Supplier A (sample) | E8: 20 | F8: 25 | G8: =N(tFeedPur[[#This Row],[Quantity in Bags]])*N(tFeedPur[[#This Row],[Bag Size in kg]]) | H8: 15500 | I8: =N(tFeedPur[[#This Row],[Quantity in Bags]])*N(tFeedPur[[#This Row],[Price per Bag]]) | J8: =IFERROR(tFeedPur[[#This Row],[Total Cost]]/tFeedPur[[#This Row],[Total Quantity in kg]],0) | K8: Transfer | L8: INV-1088 | M8: SAMPLE DATA - delete or replace. 20 bags x 25 kg = 500 kg, recorded ONCE then issued to several pens. | N8: =COUNTIF(INDEX(tFeedPur[[Feed Type]],1):tFeedPur[[#This Row],[Feed Type]],tFeedPur[[#This Row],[Feed Type]]) | O8: =MAX(0,IF((ROW()-ROW(tFeedPur[[#Headers],[Date]]))=1,0,SUMIFS(INDEX(tFeedPur[[Total Quantity in kg]],1):INDEX(tFeedPur[[Total Quantity in kg]],(ROW()-ROW(tFeedPur[[#Headers],[Date]]))-1),INDEX(tFeedPur[[Feed Type]],1):INDEX(tFeedPur[[Feed Type]],(ROW()-ROW(tFeedPur[[#Headers],[Date]]))-1),tFeedPur[[#This Row],[Feed Type]]))-SUMIFS(tFeedIss[[Quantity Issued in kg]],tFeedIss[[Feed Type]],tFeedPur[[#This Row],[Feed Type]],tFeedIss[[Date]],"<"&tFeedPur[[#This Row],[Date]])) | P8: =IFERROR((tFeedPur[[#This Row],[Stock Before Purchase kg]]*IF(tFeedPur[[#This Row],[Purchase No. of Type]]=1,0,LOOKUP(2,1/(INDEX(tFeedPur[[Feed Type]],1):INDEX(tFeedPur[[Feed Type]],(ROW()-ROW(tFeedPur[[#Headers],[Date]]))-1)=tFeedPur[[#This Row],[Feed Type]]),INDEX(tFeedPur[[Avg Cost per kg After Purchase]],1):INDEX(tFeedPur[[Avg Cost per kg After Purchase]],(ROW()-ROW(tFeedPur[[#Headers],[Date]]))-1)))+N(tFeedPur[[#This Row],[Total Cost]]))/(tFeedPur[[#This Row],[Stock Before Purchase kg]]+N(tFeedPur[[#This Row],[Total Quantity in kg]])),IF(tFeedPur[[#This Row],[Purchase No. of Type]]=1,0,LOOKUP(2,1/(INDEX(tFeedPur[[Feed Type]],1):INDEX(tFeedPur[[Feed Type]],(ROW()-ROW(tFeedPur[[#Headers],[Date]]))-1)=tFeedPur[[#This Row],[Feed Type]]),INDEX(tFeedPur[[Avg Cost per kg After Purchase]],1):INDEX(tFeedPur[[Avg Cost per kg After Purchase]],(ROW()-ROW(tFeedPur[[#Headers],[Date]]))-1)))) | Q8: =IF(AND(tFeedPur[[#This Row],[Date]]="",tFeedPur[[#This Row],[Feed Type]]="",tFeedPur[[#This Row],[Quantity in Bags]]=""),"",IF(tFeedPur[[#This Row],[Date]]="","Missing date",IF(NOT(ISNUMBER(tFeedPur[[#This Row],[Date]])),"Date is not a valid date",IF(AND((ROW()-ROW(tFeedPur[[#Headers],[Date]]))>1,tFeedPur[[#This Row],[Date]]<INDEX(tFeedPur[[Date]],MAX(1,(ROW()-ROW(tFeedPur[[#Headers],[Date]]))-1))),"Out of date order - insert this row after earlier purchases",IF(tFeedPur[[#This Row],[Feed Type]]="","Missing feed type",IF(COUNTIF(tFeedTypes[[Feed Type]],tFeedPur[[#This Row],[Feed Type]])=0,"Feed type not in LISTS",IF(N(tFeedPur[[#This Row],[Quantity in Bags]])<=0,"Bags must be greater than 0",IF(N(tFeedPur[[#This Row],[Bag Size in kg]])<=0,"Missing bag size",IF(tFeedPur[[#This Row],[Price per Bag]]="","Missing price",IF(tFeedPur[[#This Row],[Payment Method]]="","Missing payment method","OK"))))))))))
A9: 46280 | B9: ="FP-"&TEXT(ROW()-ROW(tFeedPur[[#Headers],[Date]]),"00000") | C9: Starter | D9: Feed Supplier B (sample) | E9: 10 | F9: 25 | G9: =N(tFeedPur[[#This Row],[Quantity in Bags]])*N(tFeedPur[[#This Row],[Bag Size in kg]]) | H9: 16500 | I9: =N(tFeedPur[[#This Row],[Quantity in Bags]])*N(tFeedPur[[#This Row],[Price per Bag]]) | J9: =IFERROR(tFeedPur[[#This Row],[Total Cost]]/tFeedPur[[#This Row],[Total Quantity in kg]],0) | K9: POS | L9: RCPT-301 | M9: SAMPLE DATA - delete or replace | N9: =COUNTIF(INDEX(tFeedPur[[Feed Type]],1):tFeedPur[[#This Row],[Feed Type]],tFeedPur[[#This Row],[Feed Type]]) | O9: =MAX(0,IF((ROW()-ROW(tFeedPur[[#Headers],[Date]]))=1,0,SUMIFS(INDEX(tFeedPur[[Total Quantity in kg]],1):INDEX(tFeedPur[[Total Quantity in kg]],(ROW()-ROW(tFeedPur[[#Headers],[Date]]))-1),INDEX(tFeedPur[[Feed Type]],1):INDEX(tFeedPur[[Feed Type]],(ROW()-ROW(tFeedPur[[#Headers],[Date]]))-1),tFeedPur[[#This Row],[Feed Type]]))-SUMIFS(tFeedIss[[Quantity Issued in kg]],tFeedIss[[Feed Type]],tFeedPur[[#This Row],[Feed Type]],tFeedIss[[Date]],"<"&tFeedPur[[#This Row],[Date]])) | P9: =IFERROR((tFeedPur[[#This Row],[Stock Before Purchase kg]]*IF(tFeedPur[[#This Row],[Purchase No. of Type]]=1,0,LOOKUP(2,1/(INDEX(tFeedPur[[Feed Type]],1):INDEX(tFeedPur[[Feed Type]],(ROW()-ROW(tFeedPur[[#Headers],[Date]]))-1)=tFeedPur[[#This Row],[Feed Type]]),INDEX(tFeedPur[[Avg Cost per kg After Purchase]],1):INDEX(tFeedPur[[Avg Cost per kg After Purchase]],(ROW()-ROW(tFeedPur[[#Headers],[Date]]))-1)))+N(tFeedPur[[#This Row],[Total Cost]]))/(tFeedPur[[#This Row],[Stock Before Purchase kg]]+N(tFeedPur[[#This Row],[Total Quantity in kg]])),IF(tFeedPur[[#This Row],[Purchase No. of Type]]=1,0,LOOKUP(2,1/(INDEX(tFeedPur[[Feed Type]],1):INDEX(tFeedPur[[Feed Type]],(ROW()-ROW(tFeedPur[[#Headers],[Date]]))-1)=tFeedPur[[#This Row],[Feed Type]]),INDEX(tFeedPur[[Avg Cost per kg After Purchase]],1):INDEX(tFeedPur[[Avg Cost per kg After Purchase]],(ROW()-ROW(tFeedPur[[#Headers],[Date]]))-1)))) | Q9: =IF(AND(tFeedPur[[#This Row],[Date]]="",tFeedPur[[#This Row],[Feed Type]]="",tFeedPur[[#This Row],[Quantity in Bags]]=""),"",IF(tFeedPur[[#This Row],[Date]]="","Missing date",IF(NOT(ISNUMBER(tFeedPur[[#This Row],[Date]])),"Date is not a valid date",IF(AND((ROW()-ROW(tFeedPur[[#Headers],[Date]]))>1,tFeedPur[[#This Row],[Date]]<INDEX(tFeedPur[[Date]],MAX(1,(ROW()-ROW(tFeedPur[[#Headers],[Date]]))-1))),"Out of date order - insert this row after earlier purchases",IF(tFeedPur[[#This Row],[Feed Type]]="","Missing feed type",IF(COUNTIF(tFeedTypes[[Feed Type]],tFeedPur[[#This Row],[Feed Type]])=0,"Feed type not in LISTS",IF(N(tFeedPur[[#This Row],[Quantity in Bags]])<=0,"Bags must be greater than 0",IF(N(tFeedPur[[#This Row],[Bag Size in kg]])<=0,"Missing bag size",IF(tFeedPur[[#This Row],[Price per Bag]]="","Missing price",IF(tFeedPur[[#This Row],[Payment Method]]="","Missing payment method","OK"))))))))))
A10: 46280 | B10: ="FP-"&TEXT(ROW()-ROW(tFeedPur[[#Headers],[Date]]),"00000") | C10: Grower | D10: Feed Supplier A (sample) | E10: 20 | F10: 25 | G10: =N(tFeedPur[[#This Row],[Quantity in Bags]])*N(tFeedPur[[#This Row],[Bag Size in kg]]) | H10: 16000 | I10: =N(tFeedPur[[#This Row],[Quantity in Bags]])*N(tFeedPur[[#This Row],[Price per Bag]]) | J10: =IFERROR(tFeedPur[[#This Row],[Total Cost]]/tFeedPur[[#This Row],[Total Quantity in kg]],0) | K10: Credit | L10: INV-1102 | M10: SAMPLE DATA - delete or replace | N10: =COUNTIF(INDEX(tFeedPur[[Feed Type]],1):tFeedPur[[#This Row],[Feed Type]],tFeedPur[[#This Row],[Feed Type]]) | O10: =MAX(0,IF((ROW()-ROW(tFeedPur[[#Headers],[Date]]))=1,0,SUMIFS(INDEX(tFeedPur[[Total Quantity in kg]],1):INDEX(tFeedPur[[Total Quantity in kg]],(ROW()-ROW(tFeedPur[[#Headers],[Date]]))-1),INDEX(tFeedPur[[Feed Type]],1):INDEX(tFeedPur[[Feed Type]],(ROW()-ROW(tFeedPur[[#Headers],[Date]]))-1),tFeedPur[[#This Row],[Feed Type]]))-SUMIFS(tFeedIss[[Quantity Issued in kg]],tFeedIss[[Feed Type]],tFeedPur[[#This Row],[Feed Type]],tFeedIss[[Date]],"<"&tFeedPur[[#This Row],[Date]])) | P10: =IFERROR((tFeedPur[[#This Row],[Stock Before Purchase kg]]*IF(tFeedPur[[#This Row],[Purchase No. of Type]]=1,0,LOOKUP(2,1/(INDEX(tFeedPur[[Feed Type]],1):INDEX(tFeedPur[[Feed Type]],(ROW()-ROW(tFeedPur[[#Headers],[Date]]))-1)=tFeedPur[[#This Row],[Feed Type]]),INDEX(tFeedPur[[Avg Cost per kg After Purchase]],1):INDEX(tFeedPur[[Avg Cost per kg After Purchase]],(ROW()-ROW(tFeedPur[[#Headers],[Date]]))-1)))+N(tFeedPur[[#This Row],[Total Cost]]))/(tFeedPur[[#This Row],[Stock Before Purchase kg]]+N(tFeedPur[[#This Row],[Total Quantity in kg]])),IF(tFeedPur[[#This Row],[Purchase No. of Type]]=1,0,LOOKUP(2,1/(INDEX(tFeedPur[[Feed Type]],1):INDEX(tFeedPur[[Feed Type]],(ROW()-ROW(tFeedPur[[#Headers],[Date]]))-1)=tFeedPur[[#This Row],[Feed Type]]),INDEX(tFeedPur[[Avg Cost per kg After Purchase]],1):INDEX(tFeedPur[[Avg Cost per kg After Purchase]],(ROW()-ROW(tFeedPur[[#Headers],[Date]]))-1)))) | Q10: =IF(AND(tFeedPur[[#This Row],[Date]]="",tFeedPur[[#This Row],[Feed Type]]="",tFeedPur[[#This Row],[Quantity in Bags]]=""),"",IF(tFeedPur[[#This Row],[Date]]="","Missing date",IF(NOT(ISNUMBER(tFeedPur[[#This Row],[Date]])),"Date is not a valid date",IF(AND((ROW()-ROW(tFeedPur[[#Headers],[Date]]))>1,tFeedPur[[#This Row],[Date]]<INDEX(tFeedPur[[Date]],MAX(1,(ROW()-ROW(tFeedPur[[#Headers],[Date]]))-1))),"Out of date order - insert this row after earlier purchases",IF(tFeedPur[[#This Row],[Feed Type]]="","Missing feed type",IF(COUNTIF(tFeedTypes[[Feed Type]],tFeedPur[[#This Row],[Feed Type]])=0,"Feed type not in LISTS",IF(N(tFeedPur[[#This Row],[Quantity in Bags]])<=0,"Bags must be greater than 0",IF(N(tFeedPur[[#This Row],[Bag Size in kg]])<=0,"Missing bag size",IF(tFeedPur[[#This Row],[Price per Bag]]="","Missing price",IF(tFeedPur[[#This Row],[Payment Method]]="","Missing payment method","OK"))))))))))

Sheet FEED_ISSUES
A1: FEED ISSUES
A2: Each time feed leaves the store for a pen, record it here. This reduces inventory and charges the cost (weighted-average) to the pen & batch. Record only what happened.
A3: ■ GREEN header = you enter / select ■ GREY header = automatic (do not type) Add a new record by typing in the first empty row directly under the table.
A4: Date | B4: Issue ID | C4: Feed Type | D4: Pen ID | E4: Batch ID | F4: Quantity Issued in kg | G4: Cost per kg | H4: Total Cost | I4: Issued By | J4: Notes | K4: Animal Type | L4: Store Balance on Date kg | M4: Check
A5: 46205 | B5: ="FI-"&TEXT(ROW()-ROW(tFeedIss[[#Headers],[Date]]),"00000") | C5: Starter | D5: P006 | E5: BROILER-JUL-001 | F5: 150 | G5: =IFERROR(LOOKUP(2,1/((tFeedPur[[Feed Type]]=tFeedIss[[#This Row],[Feed Type]])*(tFeedPur[[Date]]<=tFeedIss[[#This Row],[Date]])),tFeedPur[[Avg Cost per kg After Purchase]]),0) | H5: =N(tFeedIss[[#This Row],[Quantity Issued in kg]])*tFeedIss[[#This Row],[Cost per kg]] | I5: Attendant 1 | J5: SAMPLE DATA - delete or replace | K5: =IFERROR(INDEX(tBatches[[Animal Type]],MATCH(tFeedIss[[#This Row],[Batch ID]],tBatches[[Batch ID]],0)),"") | L5: =SUMIFS(tFeedPur[[Total Quantity in kg]],tFeedPur[[Feed Type]],tFeedIss[[#This Row],[Feed Type]],tFeedPur[[Date]],"<="&tFeedIss[[#This Row],[Date]])-SUMIFS(tFeedIss[[Quantity Issued in kg]],tFeedIss[[Feed Type]],tFeedIss[[#This Row],[Feed Type]],tFeedIss[[Date]],"<="&tFeedIss[[#This Row],[Date]]) | M5: =IF(AND(tFeedIss[[#This Row],[Date]]="",tFeedIss[[#This Row],[Feed Type]]="",tFeedIss[[#This Row],[Pen ID]]="",tFeedIss[[#This Row],[Batch ID]]="",tFeedIss[[#This Row],[Quantity Issued in kg]]=""),"",IF(tFeedIss[[#This Row],[Date]]="","Missing date",IF(NOT(ISNUMBER(tFeedIss[[#This Row],[Date]])),"Date is not a valid date",IF(tFeedIss[[#This Row],[Feed Type]]="","Missing feed type",IF(COUNTIF(tFeedTypes[[Feed Type]],tFeedIss[[#This Row],[Feed Type]])=0,"Feed type not in LISTS",IF(tFeedIss[[#This Row],[Pen ID]]="","Missing Pen ID",IF(COUNTIF(tPens[[Pen ID]],tFeedIss[[#This Row],[Pen ID]])=0,"Pen "&tFeedIss[[#This Row],[Pen ID]]&" is not in PEN_REGISTER",IF(tFeedIss[[#This Row],[Batch ID]]="","Missing Batch ID",IF(COUNTIF(tBatches[[Batch ID]],tFeedIss[[#This Row],[Batch ID]])=0,"Batch "&tFeedIss[[#This Row],[Batch ID]]&" is not in BATCH_REGISTER",IF(COUNTIFS(tBatches[[Batch ID]],tFeedIss[[#This Row],[Batch ID]],tBatches[[Pen ID]],tFeedIss[[#This Row],[Pen ID]])=0,"Batch "&tFeedIss[[#This Row],[Batch ID]]&" belongs to pen "&INDEX(tBatches[[Pen ID]],MATCH(tFeedIss[[#This Row],[Batch ID]],tBatches[[Batch ID]],0)),IF(tFeedIss[[#This Row],[Date]]<INDEX(tBatches[[Batch Start Date]],MATCH(tFeedIss[[#This Row],[Batch ID]],tBatches[[Batch ID]],0)),"Date is before the batch start date",IF(AND(N(INDEX(tBatches[[Closing Date]],MATCH(tFeedIss[[#This Row],[Batch ID]],tBatches[[Batch ID]],0)))>0,tFeedIss[[#This Row],[Date]]>INDEX(tBatches[[Closing Date]],MATCH(tFeedIss[[#This Row],[Batch ID]],tBatches[[Batch ID]],0))),"Date is after the batch closing date",IF(N(tFeedIss[[#This Row],[Quantity Issued in kg]])<=0,"Quantity must be greater than 0",IF(tFeedIss[[#This Row],[Cost per kg]]=0,"No purchase of this feed on/before this date",IF(tFeedIss[[#This Row],[Store Balance on Date kg]]<-0.0001,"EXCEEDS STOCK by "&TEXT(-tFeedIss[[#This Row],[Store Balance on Date kg]],"#,##0.0")&" kg","OK")))))))))))))))
A6: 46223 | B6: ="FI-"&TEXT(ROW()-ROW(tFeedIss[[#Headers],[Date]]),"00000") | C6: Starter | D6: P006 | E6: BROILER-JUL-001 | F6: 150 | G6: =IFERROR(LOOKUP(2,1/((tFeedPur[[Feed Type]]=tFeedIss[[#This Row],[Feed Type]])*(tFeedPur[[Date]]<=tFeedIss[[#This Row],[Date]])),tFeedPur[[Avg Cost per kg After Purchase]]),0) | H6: =N(tFeedIss[[#This Row],[Quantity Issued in kg]])*tFeedIss[[#This Row],[Cost per kg]] | I6: Attendant 1 | J6: SAMPLE DATA - delete or replace | K6: =IFERROR(INDEX(tBatches[[Animal Type]],MATCH(tFeedIss[[#This Row],[Batch ID]],tBatches[[Batch ID]],0)),"") | L6: =SUMIFS(tFeedPur[[Total Quantity in kg]],tFeedPur[[Feed Type]],tFeedIss[[#This Row],[Feed Type]],tFeedPur[[Date]],"<="&tFeedIss[[#This Row],[Date]])-SUMIFS(tFeedIss[[Quantity Issued in kg]],tFeedIss[[Feed Type]],tFeedIss[[#This Row],[Feed Type]],tFeedIss[[Date]],"<="&tFeedIss[[#This Row],[Date]]) | M6: =IF(AND(tFeedIss[[#This Row],[Date]]="",tFeedIss[[#This Row],[Feed Type]]="",tFeedIss[[#This Row],[Pen ID]]="",tFeedIss[[#This Row],[Batch ID]]="",tFeedIss[[#This Row],[Quantity Issued in kg]]=""),"",IF(tFeedIss[[#This Row],[Date]]="","Missing date",IF(NOT(ISNUMBER(tFeedIss[[#This Row],[Date]])),"Date is not a valid date",IF(tFeedIss[[#This Row],[Feed Type]]="","Missing feed type",IF(COUNTIF(tFeedTypes[[Feed Type]],tFeedIss[[#This Row],[Feed Type]])=0,"Feed type not in LISTS",IF(tFeedIss[[#This Row],[Pen ID]]="","Missing Pen ID",IF(COUNTIF(tPens[[Pen ID]],tFeedIss[[#This Row],[Pen ID]])=0,"Pen "&tFeedIss[[#This Row],[Pen ID]]&" is not in PEN_REGISTER",IF(tFeedIss[[#This Row],[Batch ID]]="","Missing Batch ID",IF(COUNTIF(tBatches[[Batch ID]],tFeedIss[[#This Row],[Batch ID]])=0,"Batch "&tFeedIss[[#This Row],[Batch ID]]&" is not in BATCH_REGISTER",IF(COUNTIFS(tBatches[[Batch ID]],tFeedIss[[#This Row],[Batch ID]],tBatches[[Pen ID]],tFeedIss[[#This Row],[Pen ID]])=0,"Batch "&tFeedIss[[#This Row],[Batch ID]]&" belongs to pen "&INDEX(tBatches[[Pen ID]],MATCH(tFeedIss[[#This Row],[Batch ID]],tBatches[[Batch ID]],0)),IF(tFeedIss[[#This Row],[Date]]<INDEX(tBatches[[Batch Start Date]],MATCH(tFeedIss[[#This Row],[Batch ID]],tBatches[[Batch ID]],0)),"Date is before the batch start date",IF(AND(N(INDEX(tBatches[[Closing Date]],MATCH(tFeedIss[[#This Row],[Batch ID]],tBatches[[Batch ID]],0)))>0,tFeedIss[[#This Row],[Date]]>INDEX(tBatches[[Closing Date]],MATCH(tFeedIss[[#This Row],[Batch ID]],tBatches[[Batch ID]],0))),"Date is after the batch closing date",IF(N(tFeedIss[[#This Row],[Quantity Issued in kg]])<=0,"Quantity must be greater than 0",IF(tFeedIss[[#This Row],[Cost per kg]]=0,"No purchase of this feed on/before this date",IF(tFeedIss[[#This Row],[Store Balance on Date kg]]<-0.0001,"EXCEEDS STOCK by "&TEXT(-tFeedIss[[#This Row],[Store Balance on Date kg]],"#,##0.0")&" kg","OK")))))))))))))))
A7: 46228 | B7: ="FI-"&TEXT(ROW()-ROW(tFeedIss[[#Headers],[Date]]),"00000") | C7: Finisher | D7: P006 | E7: BROILER-JUL-001 | F7: 150 | G7: =IFERROR(LOOKUP(2,1/((tFeedPur[[Feed Type]]=tFeedIss[[#This Row],[Feed Type]])*(tFeedPur[[Date]]<=tFeedIss[[#This Row],[Date]])),tFeedPur[[Avg Cost per kg After Purchase]]),0) | H7: =N(tFeedIss[[#This Row],[Quantity Issued in kg]])*tFeedIss[[#This Row],[Cost per kg]] | I7: Attendant 1 | J7: SAMPLE DATA - delete or replace | K7: =IFERROR(INDEX(tBatches[[Animal Type]],MATCH(tFeedIss[[#This Row],[Batch ID]],tBatches[[Batch ID]],0)),"") | L7: =SUMIFS(tFeedPur[[Total Quantity in kg]],tFeedPur[[Feed Type]],tFeedIss[[#This Row],[Feed Type]],tFeedPur[[Date]],"<="&tFeedIss[[#This Row],[Date]])-SUMIFS(tFeedIss[[Quantity Issued in kg]],tFeedIss[[Feed Type]],tFeedIss[[#This Row],[Feed Type]],tFeedIss[[Date]],"<="&tFeedIss[[#This Row],[Date]]) | M7: =IF(AND(tFeedIss[[#This Row],[Date]]="",tFeedIss[[#This Row],[Feed Type]]="",tFeedIss[[#This Row],[Pen ID]]="",tFeedIss[[#This Row],[Batch ID]]="",tFeedIss[[#This Row],[Quantity Issued in kg]]=""),"",IF(tFeedIss[[#This Row],[Date]]="","Missing date",IF(NOT(ISNUMBER(tFeedIss[[#This Row],[Date]])),"Date is not a valid date",IF(tFeedIss[[#This Row],[Feed Type]]="","Missing feed type",IF(COUNTIF(tFeedTypes[[Feed Type]],tFeedIss[[#This Row],[Feed Type]])=0,"Feed type not in LISTS",IF(tFeedIss[[#This Row],[Pen ID]]="","Missing Pen ID",IF(COUNTIF(tPens[[Pen ID]],tFeedIss[[#This Row],[Pen ID]])=0,"Pen "&tFeedIss[[#This Row],[Pen ID]]&" is not in PEN_REGISTER",IF(tFeedIss[[#This Row],[Batch ID]]="","Missing Batch ID",IF(COUNTIF(tBatches[[Batch ID]],tFeedIss[[#This Row],[Batch ID]])=0,"Batch "&tFeedIss[[#This Row],[Batch ID]]&" is not in BATCH_REGISTER",IF(COUNTIFS(tBatches[[Batch ID]],tFeedIss[[#This Row],[Batch ID]],tBatches[[Pen ID]],tFeedIss[[#This Row],[Pen ID]])=0,"Batch "&tFeedIss[[#This Row],[Batch ID]]&" belongs to pen "&INDEX(tBatches[[Pen ID]],MATCH(tFeedIss[[#This Row],[Batch ID]],tBatches[[Batch ID]],0)),IF(tFeedIss[[#This Row],[Date]]<INDEX(tBatches[[Batch Start Date]],MATCH(tFeedIss[[#This Row],[Batch ID]],tBatches[[Batch ID]],0)),"Date is before the batch start date",IF(AND(N(INDEX(tBatches[[Closing Date]],MATCH(tFeedIss[[#This Row],[Batch ID]],tBatches[[Batch ID]],0)))>0,tFeedIss[[#This Row],[Date]]>INDEX(tBatches[[Closing Date]],MATCH(tFeedIss[[#This Row],[Batch ID]],tBatches[[Batch ID]],0))),"Date is after the batch closing date",IF(N(tFeedIss[[#This Row],[Quantity Issued in kg]])<=0,"Quantity must be greater than 0",IF(tFeedIss[[#This Row],[Cost per kg]]=0,"No purchase of this feed on/before this date",IF(tFeedIss[[#This Row],[Store Balance on Date kg]]<-0.0001,"EXCEEDS STOCK by "&TEXT(-tFeedIss[[#This Row],[Store Balance on Date kg]],"#,##0.0")&" kg","OK")))))))))))))))
A8: 46244 | B8: ="FI-"&TEXT(ROW()-ROW(tFeedIss[[#Headers],[Date]]),"00000") | C8: Finisher | D8: P006 | E8: BROILER-JUL-001 | F8: 140 | G8: =IFERROR(LOOKUP(2,1/((tFeedPur[[Feed Type]]=tFeedIss[[#This Row],[Feed Type]])*(tFeedPur[[Date]]<=tFeedIss[[#This Row],[Date]])),tFeedPur[[Avg Cost per kg After Purchase]]),0) | H8: =N(tFeedIss[[#This Row],[Quantity Issued in kg]])*tFeedIss[[#This Row],[Cost per kg]] | I8: Attendant 1 | J8: SAMPLE DATA - delete or replace | K8: =IFERROR(INDEX(tBatches[[Animal Type]],MATCH(tFeedIss[[#This Row],[Batch ID]],tBatches[[Batch ID]],0)),"") | L8: =SUMIFS(tFeedPur[[Total Quantity in kg]],tFeedPur[[Feed Type]],tFeedIss[[#This Row],[Feed Type]],tFeedPur[[Date]],"<="&tFeedIss[[#This Row],[Date]])-SUMIFS(tFeedIss[[Quantity Issued in kg]],tFeedIss[[Feed Type]],tFeedIss[[#This Row],[Feed Type]],tFeedIss[[Date]],"<="&tFeedIss[[#This Row],[Date]]) | M8: =IF(AND(tFeedIss[[#This Row],[Date]]="",tFeedIss[[#This Row],[Feed Type]]="",tFeedIss[[#This Row],[Pen ID]]="",tFeedIss[[#This Row],[Batch ID]]="",tFeedIss[[#This Row],[Quantity Issued in kg]]=""),"",IF(tFeedIss[[#This Row],[Date]]="","Missing date",IF(NOT(ISNUMBER(tFeedIss[[#This Row],[Date]])),"Date is not a valid date",IF(tFeedIss[[#This Row],[Feed Type]]="","Missing feed type",IF(COUNTIF(tFeedTypes[[Feed Type]],tFeedIss[[#This Row],[Feed Type]])=0,"Feed type not in LISTS",IF(tFeedIss[[#This Row],[Pen ID]]="","Missing Pen ID",IF(COUNTIF(tPens[[Pen ID]],tFeedIss[[#This Row],[Pen ID]])=0,"Pen "&tFeedIss[[#This Row],[Pen ID]]&" is not in PEN_REGISTER",IF(tFeedIss[[#This Row],[Batch ID]]="","Missing Batch ID",IF(COUNTIF(tBatches[[Batch ID]],tFeedIss[[#This Row],[Batch ID]])=0,"Batch "&tFeedIss[[#This Row],[Batch ID]]&" is not in BATCH_REGISTER",IF(COUNTIFS(tBatches[[Batch ID]],tFeedIss[[#This Row],[Batch ID]],tBatches[[Pen ID]],tFeedIss[[#This Row],[Pen ID]])=0,"Batch "&tFeedIss[[#This Row],[Batch ID]]&" belongs to pen "&INDEX(tBatches[[Pen ID]],MATCH(tFeedIss[[#This Row],[Batch ID]],tBatches[[Batch ID]],0)),IF(tFeedIss[[#This Row],[Date]]<INDEX(tBatches[[Batch Start Date]],MATCH(tFeedIss[[#This Row],[Batch ID]],tBatches[[Batch ID]],0)),"Date is before the batch start date",IF(AND(N(INDEX(tBatches[[Closing Date]],MATCH(tFeedIss[[#This Row],[Batch ID]],tBatches[[Batch ID]],0)))>0,tFeedIss[[#This Row],[Date]]>INDEX(tBatches[[Closing Date]],MATCH(tFeedIss[[#This Row],[Batch ID]],tBatches[[Batch ID]],0))),"Date is after the batch closing date",IF(N(tFeedIss[[#This Row],[Quantity Issued in kg]])<=0,"Quantity must be greater than 0",IF(tFeedIss[[#This Row],[Cost per kg]]=0,"No purchase of this feed on/before this date",IF(tFeedIss[[#This Row],[Store Balance on Date kg]]<-0.0001,"EXCEEDS STOCK by "&TEXT(-tFeedIss[[#This Row],[Store Balance on Date kg]],"#,##0.0")&" kg","OK")))))))))))))))
A9: 46205 | B9: ="FI-"&TEXT(ROW()-ROW(tFeedIss[[#Headers],[Date]]),"00000") | C9: Layer Mash | D9: P005 | E9: LAYER-JUN-001 | F9: 200 | G9: =IFERROR(LOOKUP(2,1/((tFeedPur[[Feed Type]]=tFeedIss[[#This Row],[Feed Type]])*(tFeedPur[[Date]]<=tFeedIss[[#This Row],[Date]])),tFeedPur[[Avg Cost per kg After Purchase]]),0) | H9: =N(tFeedIss[[#This Row],[Quantity Issued in kg]])*tFeedIss[[#This Row],[Cost per kg]] | I9: Attendant 1 | J9: SAMPLE DATA - delete or replace | K9: =IFERROR(INDEX(tBatches[[Animal Type]],MATCH(tFeedIss[[#This Row],[Batch ID]],tBatches[[Batch ID]],0)),"") | L9: =SUMIFS(tFeedPur[[Total Quantity in kg]],tFeedPur[[Feed Type]],tFeedIss[[#This Row],[Feed Type]],tFeedPur[[Date]],"<="&tFeedIss[[#This Row],[Date]])-SUMIFS(tFeedIss[[Quantity Issued in kg]],tFeedIss[[Feed Type]],tFeedIss[[#This Row],[Feed Type]],tFeedIss[[Date]],"<="&tFeedIss[[#This Row],[Date]]) | M9: =IF(AND(tFeedIss[[#This Row],[Date]]="",tFeedIss[[#This Row],[Feed Type]]="",tFeedIss[[#This Row],[Pen ID]]="",tFeedIss[[#This Row],[Batch ID]]="",tFeedIss[[#This Row],[Quantity Issued in kg]]=""),"",IF(tFeedIss[[#This Row],[Date]]="","Missing date",IF(NOT(ISNUMBER(tFeedIss[[#This Row],[Date]])),"Date is not a valid date",IF(tFeedIss[[#This Row],[Feed Type]]="","Missing feed type",IF(COUNTIF(tFeedTypes[[Feed Type]],tFeedIss[[#This Row],[Feed Type]])=0,"Feed type not in LISTS",IF(tFeedIss[[#This Row],[Pen ID]]="","Missing Pen ID",IF(COUNTIF(tPens[[Pen ID]],tFeedIss[[#This Row],[Pen ID]])=0,"Pen "&tFeedIss[[#This Row],[Pen ID]]&" is not in PEN_REGISTER",IF(tFeedIss[[#This Row],[Batch ID]]="","Missing Batch ID",IF(COUNTIF(tBatches[[Batch ID]],tFeedIss[[#This Row],[Batch ID]])=0,"Batch "&tFeedIss[[#This Row],[Batch ID]]&" is not in BATCH_REGISTER",IF(COUNTIFS(tBatches[[Batch ID]],tFeedIss[[#This Row],[Batch ID]],tBatches[[Pen ID]],tFeedIss[[#This Row],[Pen ID]])=0,"Batch "&tFeedIss[[#This Row],[Batch ID]]&" belongs to pen "&INDEX(tBatches[[Pen ID]],MATCH(tFeedIss[[#This Row],[Batch ID]],tBatches[[Batch ID]],0)),IF(tFeedIss[[#This Row],[Date]]<INDEX(tBatches[[Batch Start Date]],MATCH(tFeedIss[[#This Row],[Batch ID]],tBatches[[Batch ID]],0)),"Date is before the batch start date",IF(AND(N(INDEX(tBatches[[Closing Date]],MATCH(tFeedIss[[#This Row],[Batch ID]],tBatches[[Batch ID]],0)))>0,tFeedIss[[#This Row],[Date]]>INDEX(tBatches[[Closing Date]],MATCH(tFeedIss[[#This Row],[Batch ID]],tBatches[[Batch ID]],0))),"Date is after the batch closing date",IF(N(tFeedIss[[#This Row],[Quantity Issued in kg]])<=0,"Quantity must be greater than 0",IF(tFeedIss[[#This Row],[Cost per kg]]=0,"No purchase of this feed on/before this date",IF(tFeedIss[[#This Row],[Store Balance on Date kg]]<-0.0001,"EXCEEDS STOCK by "&TEXT(-tFeedIss[[#This Row],[Store Balance on Date kg]],"#,##0.0")&" kg","OK")))))))))))))))
A10: 46235 | B10: ="FI-"&TEXT(ROW()-ROW(tFeedIss[[#Headers],[Date]]),"00000") | C10: Layer Mash | D10: P005 | E10: LAYER-JUN-001 | F10: 200 | G10: =IFERROR(LOOKUP(2,1/((tFeedPur[[Feed Type]]=tFeedIss[[#This Row],[Feed Type]])*(tFeedPur[[Date]]<=tFeedIss[[#This Row],[Date]])),tFeedPur[[Avg Cost per kg After Purchase]]),0) | H10: =N(tFeedIss[[#This Row],[Quantity Issued in kg]])*tFeedIss[[#This Row],[Cost per kg]] | I10: Attendant 1 | J10: SAMPLE DATA - delete or replace | K10: =IFERROR(INDEX(tBatches[[Animal Type]],MATCH(tFeedIss[[#This Row],[Batch ID]],tBatches[[Batch ID]],0)),"") | L10: =SUMIFS(tFeedPur[[Total Quantity in kg]],tFeedPur[[Feed Type]],tFeedIss[[#This Row],[Feed Type]],tFeedPur[[Date]],"<="&tFeedIss[[#This Row],[Date]])-SUMIFS(tFeedIss[[Quantity Issued in kg]],tFeedIss[[Feed Type]],tFeedIss[[#This Row],[Feed Type]],tFeedIss[[Date]],"<="&tFeedIss[[#This Row],[Date]]) | M10: =IF(AND(tFeedIss[[#This Row],[Date]]="",tFeedIss[[#This Row],[Feed Type]]="",tFeedIss[[#This Row],[Pen ID]]="",tFeedIss[[#This Row],[Batch ID]]="",tFeedIss[[#This Row],[Quantity Issued in kg]]=""),"",IF(tFeedIss[[#This Row],[Date]]="","Missing date",IF(NOT(ISNUMBER(tFeedIss[[#This Row],[Date]])),"Date is not a valid date",IF(tFeedIss[[#This Row],[Feed Type]]="","Missing feed type",IF(COUNTIF(tFeedTypes[[Feed Type]],tFeedIss[[#This Row],[Feed Type]])=0,"Feed type not in LISTS",IF(tFeedIss[[#This Row],[Pen ID]]="","Missing Pen ID",IF(COUNTIF(tPens[[Pen ID]],tFeedIss[[#This Row],[Pen ID]])=0,"Pen "&tFeedIss[[#This Row],[Pen ID]]&" is not in PEN_REGISTER",IF(tFeedIss[[#This Row],[Batch ID]]="","Missing Batch ID",IF(COUNTIF(tBatches[[Batch ID]],tFeedIss[[#This Row],[Batch ID]])=0,"Batch "&tFeedIss[[#This Row],[Batch ID]]&" is not in BATCH_REGISTER",IF(COUNTIFS(tBatches[[Batch ID]],tFeedIss[[#This Row],[Batch ID]],tBatches[[Pen ID]],tFeedIss[[#This Row],[Pen ID]])=0,"Batch "&tFeedIss[[#This Row],[Batch ID]]&" belongs to pen "&INDEX(tBatches[[Pen ID]],MATCH(tFeedIss[[#This Row],[Batch ID]],tBatches[[Batch ID]],0)),IF(tFeedIss[[#This Row],[Date]]<INDEX(tBatches[[Batch Start Date]],MATCH(tFeedIss[[#This Row],[Batch ID]],tBatches[[Batch ID]],0)),"Date is before the batch start date",IF(AND(N(INDEX(tBatches[[Closing Date]],MATCH(tFeedIss[[#This Row],[Batch ID]],tBatches[[Batch ID]],0)))>0,tFeedIss[[#This Row],[Date]]>INDEX(tBatches[[Closing Date]],MATCH(tFeedIss[[#This Row],[Batch ID]],tBatches[[Batch ID]],0))),"Date is after the batch closing date",IF(N(tFeedIss[[#This Row],[Quantity Issued in kg]])<=0,"Quantity must be greater than 0",IF(tFeedIss[[#This Row],[Cost per kg]]=0,"No purchase of this feed on/before this date",IF(tFeedIss[[#This Row],[Store Balance on Date kg]]<-0.0001,"EXCEEDS STOCK by "&TEXT(-tFeedIss[[#This Row],[Store Balance on Date kg]],"#,##0.0")&" kg","OK")))))))))))))))
A11: 46266 | B11: ="FI-"&TEXT(ROW()-ROW(tFeedIss[[#Headers],[Date]]),"00000") | C11: Layer Mash | D11: P005 | E11: LAYER-JUN-001 | F11: 60 | G11: =IFERROR(LOOKUP(2,1/((tFeedPur[[Feed Type]]=tFeedIss[[#This Row],[Feed Type]])*(tFeedPur[[Date]]<=tFeedIss[[#This Row],[Date]])),tFeedPur[[Avg Cost per kg After Purchase]]),0) | H11: =N(tFeedIss[[#This Row],[Quantity Issued in kg]])*tFeedIss[[#This Row],[Cost per kg]] | I11: Attendant 1 | J11: SAMPLE DATA - delete or replace | K11: =IFERROR(INDEX(tBatches[[Animal Type]],MATCH(tFeedIss[[#This Row],[Batch ID]],tBatches[[Batch ID]],0)),"") | L11: =SUMIFS(tFeedPur[[Total Quantity in kg]],tFeedPur[[Feed Type]],tFeedIss[[#This Row],[Feed Type]],tFeedPur[[Date]],"<="&tFeedIss[[#This Row],[Date]])-SUMIFS(tFeedIss[[Quantity Issued in kg]],tFeedIss[[Feed Type]],tFeedIss[[#This Row],[Feed Type]],tFeedIss[[Date]],"<="&tFeedIss[[#This Row],[Date]]) | M11: =IF(AND(tFeedIss[[#This Row],[Date]]="",tFeedIss[[#This Row],[Feed Type]]="",tFeedIss[[#This Row],[Pen ID]]="",tFeedIss[[#This Row],[Batch ID]]="",tFeedIss[[#This Row],[Quantity Issued in kg]]=""),"",IF(tFeedIss[[#This Row],[Date]]="","Missing date",IF(NOT(ISNUMBER(tFeedIss[[#This Row],[Date]])),"Date is not a valid date",IF(tFeedIss[[#This Row],[Feed Type]]="","Missing feed type",IF(COUNTIF(tFeedTypes[[Feed Type]],tFeedIss[[#This Row],[Feed Type]])=0,"Feed type not in LISTS",IF(tFeedIss[[#This Row],[Pen ID]]="","Missing Pen ID",IF(COUNTIF(tPens[[Pen ID]],tFeedIss[[#This Row],[Pen ID]])=0,"Pen "&tFeedIss[[#This Row],[Pen ID]]&" is not in PEN_REGISTER",IF(tFeedIss[[#This Row],[Batch ID]]="","Missing Batch ID",IF(COUNTIF(tBatches[[Batch ID]],tFeedIss[[#This Row],[Batch ID]])=0,"Batch "&tFeedIss[[#This Row],[Batch ID]]&" is not in BATCH_REGISTER",IF(COUNTIFS(tBatches[[Batch ID]],tFeedIss[[#This Row],[Batch ID]],tBatches[[Pen ID]],tFeedIss[[#This Row],[Pen ID]])=0,"Batch "&tFeedIss[[#This Row],[Batch ID]]&" belongs to pen "&INDEX(tBatches[[Pen ID]],MATCH(tFeedIss[[#This Row],[Batch ID]],tBatches[[Batch ID]],0)),IF(tFeedIss[[#This Row],[Date]]<INDEX(tBatches[[Batch Start Date]],MATCH(tFeedIss[[#This Row],[Batch ID]],tBatches[[Batch ID]],0)),"Date is before the batch start date",IF(AND(N(INDEX(tBatches[[Closing Date]],MATCH(tFeedIss[[#This Row],[Batch ID]],tBatches[[Batch ID]],0)))>0,tFeedIss[[#This Row],[Date]]>INDEX(tBatches[[Closing Date]],MATCH(tFeedIss[[#This Row],[Batch ID]],tBatches[[Batch ID]],0))),"Date is after the batch closing date",IF(N(tFeedIss[[#This Row],[Quantity Issued in kg]])<=0,"Quantity must be greater than 0",IF(tFeedIss[[#This Row],[Cost per kg]]=0,"No purchase of this feed on/before this date",IF(tFeedIss[[#This Row],[Store Balance on Date kg]]<-0.0001,"EXCEEDS STOCK by "&TEXT(-tFeedIss[[#This Row],[Store Balance on Date kg]],"#,##0.0")&" kg","OK")))))))))))))))
A12: 46267 | B12: ="FI-"&TEXT(ROW()-ROW(tFeedIss[[#Headers],[Date]]),"00000") | C12: Starter | D12: P001 | E12: BROILER-SEP-001 | F12: 40 | G12: =IFERROR(LOOKUP(2,1/((tFeedPur[[Feed Type]]=tFeedIss[[#This Row],[Feed Type]])*(tFeedPur[[Date]]<=tFeedIss[[#This Row],[Date]])),tFeedPur[[Avg Cost per kg After Purchase]]),0) | H12: =N(tFeedIss[[#This Row],[Quantity Issued in kg]])*tFeedIss[[#This Row],[Cost per kg]] | I12: Attendant 1 | J12: SAMPLE DATA - delete or replace. Same 500 kg Starter purchase shared across pens. | K12: =IFERROR(INDEX(tBatches[[Animal Type]],MATCH(tFeedIss[[#This Row],[Batch ID]],tBatches[[Batch ID]],0)),"") | L12: =SUMIFS(tFeedPur[[Total Quantity in kg]],tFeedPur[[Feed Type]],tFeedIss[[#This Row],[Feed Type]],tFeedPur[[Date]],"<="&tFeedIss[[#This Row],[Date]])-SUMIFS(tFeedIss[[Quantity Issued in kg]],tFeedIss[[Feed Type]],tFeedIss[[#This Row],[Feed Type]],tFeedIss[[Date]],"<="&tFeedIss[[#This Row],[Date]]) | M12: =IF(AND(tFeedIss[[#This Row],[Date]]="",tFeedIss[[#This Row],[Feed Type]]="",tFeedIss[[#This Row],[Pen ID]]="",tFeedIss[[#This Row],[Batch ID]]="",tFeedIss[[#This Row],[Quantity Issued in kg]]=""),"",IF(tFeedIss[[#This Row],[Date]]="","Missing date",IF(NOT(ISNUMBER(tFeedIss[[#This Row],[Date]])),"Date is not a valid date",IF(tFeedIss[[#This Row],[Feed Type]]="","Missing feed type",IF(COUNTIF(tFeedTypes[[Feed Type]],tFeedIss[[#This Row],[Feed Type]])=0,"Feed type not in LISTS",IF(tFeedIss[[#This Row],[Pen ID]]="","Missing Pen ID",IF(COUNTIF(tPens[[Pen ID]],tFeedIss[[#This Row],[Pen ID]])=0,"Pen "&tFeedIss[[#This Row],[Pen ID]]&" is not in PEN_REGISTER",IF(tFeedIss[[#This Row],[Batch ID]]="","Missing Batch ID",IF(COUNTIF(tBatches[[Batch ID]],tFeedIss[[#This Row],[Batch ID]])=0,"Batch "&tFeedIss[[#This Row],[Batch ID]]&" is not in BATCH_REGISTER",IF(COUNTIFS(tBatches[[Batch ID]],tFeedIss[[#This Row],[Batch ID]],tBatches[[Pen ID]],tFeedIss[[#This Row],[Pen ID]])=0,"Batch "&tFeedIss[[#This Row],[Batch ID]]&" belongs to pen "&INDEX(tBatches[[Pen ID]],MATCH(tFeedIss[[#This Row],[Batch ID]],tBatches[[Batch ID]],0)),IF(tFeedIss[[#This Row],[Date]]<INDEX(tBatches[[Batch Start Date]],MATCH(tFeedIss[[#This Row],[Batch ID]],tBatches[[Batch ID]],0)),"Date is before the batch start date",IF(AND(N(INDEX(tBatches[[Closing Date]],MATCH(tFeedIss[[#This Row],[Batch ID]],tBatches[[Batch ID]],0)))>0,tFeedIss[[#This Row],[Date]]>INDEX(tBatches[[Closing Date]],MATCH(tFeedIss[[#This Row],[Batch ID]],tBatches[[Batch ID]],0))),"Date is after the batch closing date",IF(N(tFeedIss[[#This Row],[Quantity Issued in kg]])<=0,"Quantity must be greater than 0",IF(tFeedIss[[#This Row],[Cost per kg]]=0,"No purchase of this feed on/before this date",IF(tFeedIss[[#This Row],[Store Balance on Date kg]]<-0.0001,"EXCEEDS STOCK by "&TEXT(-tFeedIss[[#This Row],[Store Balance on Date kg]],"#,##0.0")&" kg","OK")))))))))))))))
A13: 46267 | B13: ="FI-"&TEXT(ROW()-ROW(tFeedIss[[#Headers],[Date]]),"00000") | C13: Starter | D13: P002 | E13: BROILER-SEP-002 | F13: 60 | G13: =IFERROR(LOOKUP(2,1/((tFeedPur[[Feed Type]]=tFeedIss[[#This Row],[Feed Type]])*(tFeedPur[[Date]]<=tFeedIss[[#This Row],[Date]])),tFeedPur[[Avg Cost per kg After Purchase]]),0) | H13: =N(tFeedIss[[#This Row],[Quantity Issued in kg]])*tFeedIss[[#This Row],[Cost per kg]] | I13: Attendant 1 | J13: SAMPLE DATA - delete or replace. Same 500 kg Starter purchase shared across pens. | K13: =IFERROR(INDEX(tBatches[[Animal Type]],MATCH(tFeedIss[[#This Row],[Batch ID]],tBatches[[Batch ID]],0)),"") | L13: =SUMIFS(tFeedPur[[Total Quantity in kg]],tFeedPur[[Feed Type]],tFeedIss[[#This Row],[Feed Type]],tFeedPur[[Date]],"<="&tFeedIss[[#This Row],[Date]])-SUMIFS(tFeedIss[[Quantity Issued in kg]],tFeedIss[[Feed Type]],tFeedIss[[#This Row],[Feed Type]],tFeedIss[[Date]],"<="&tFeedIss[[#This Row],[Date]]) | M13: =IF(AND(tFeedIss[[#This Row],[Date]]="",tFeedIss[[#This Row],[Feed Type]]="",tFeedIss[[#This Row],[Pen ID]]="",tFeedIss[[#This Row],[Batch ID]]="",tFeedIss[[#This Row],[Quantity Issued in kg]]=""),"",IF(tFeedIss[[#This Row],[Date]]="","Missing date",IF(NOT(ISNUMBER(tFeedIss[[#This Row],[Date]])),"Date is not a valid date",IF(tFeedIss[[#This Row],[Feed Type]]="","Missing feed type",IF(COUNTIF(tFeedTypes[[Feed Type]],tFeedIss[[#This Row],[Feed Type]])=0,"Feed type not in LISTS",IF(tFeedIss[[#This Row],[Pen ID]]="","Missing Pen ID",IF(COUNTIF(tPens[[Pen ID]],tFeedIss[[#This Row],[Pen ID]])=0,"Pen "&tFeedIss[[#This Row],[Pen ID]]&" is not in PEN_REGISTER",IF(tFeedIss[[#This Row],[Batch ID]]="","Missing Batch ID",IF(COUNTIF(tBatches[[Batch ID]],tFeedIss[[#This Row],[Batch ID]])=0,"Batch "&tFeedIss[[#This Row],[Batch ID]]&" is not in BATCH_REGISTER",IF(COUNTIFS(tBatches[[Batch ID]],tFeedIss[[#This Row],[Batch ID]],tBatches[[Pen ID]],tFeedIss[[#This Row],[Pen ID]])=0,"Batch "&tFeedIss[[#This Row],[Batch ID]]&" belongs to pen "&INDEX(tBatches[[Pen ID]],MATCH(tFeedIss[[#This Row],[Batch ID]],tBatches[[Batch ID]],0)),IF(tFeedIss[[#This Row],[Date]]<INDEX(tBatches[[Batch Start Date]],MATCH(tFeedIss[[#This Row],[Batch ID]],tBatches[[Batch ID]],0)),"Date is before the batch start date",IF(AND(N(INDEX(tBatches[[Closing Date]],MATCH(tFeedIss[[#This Row],[Batch ID]],tBatches[[Batch ID]],0)))>0,tFeedIss[[#This Row],[Date]]>INDEX(tBatches[[Closing Date]],MATCH(tFeedIss[[#This Row],[Batch ID]],tBatches[[Batch ID]],0))),"Date is after the batch closing date",IF(N(tFeedIss[[#This Row],[Quantity Issued in kg]])<=0,"Quantity must be greater than 0",IF(tFeedIss[[#This Row],[Cost per kg]]=0,"No purchase of this feed on/before this date",IF(tFeedIss[[#This Row],[Store Balance on Date kg]]<-0.0001,"EXCEEDS STOCK by "&TEXT(-tFeedIss[[#This Row],[Store Balance on Date kg]],"#,##0.0")&" kg","OK")))))))))))))))
A14: 46267 | B14: ="FI-"&TEXT(ROW()-ROW(tFeedIss[[#Headers],[Date]]),"00000") | C14: Starter | D14: P003 | E14: BROILER-SEP-003 | F14: 35 | G14: =IFERROR(LOOKUP(2,1/((tFeedPur[[Feed Type]]=tFeedIss[[#This Row],[Feed Type]])*(tFeedPur[[Date]]<=tFeedIss[[#This Row],[Date]])),tFeedPur[[Avg Cost per kg After Purchase]]),0) | H14: =N(tFeedIss[[#This Row],[Quantity Issued in kg]])*tFeedIss[[#This Row],[Cost per kg]] | I14: Attendant 1 | J14: SAMPLE DATA - delete or replace. Same 500 kg Starter purchase shared across pens. | K14: =IFERROR(INDEX(tBatches[[Animal Type]],MATCH(tFeedIss[[#This Row],[Batch ID]],tBatches[[Batch ID]],0)),"") | L14: =SUMIFS(tFeedPur[[Total Quantity in kg]],tFeedPur[[Feed Type]],tFeedIss[[#This Row],[Feed Type]],tFeedPur[[Date]],"<="&tFeedIss[[#This Row],[Date]])-SUMIFS(tFeedIss[[Quantity Issued in kg]],tFeedIss[[Feed Type]],tFeedIss[[#This Row],[Feed Type]],tFeedIss[[Date]],"<="&tFeedIss[[#This Row],[Date]]) | M14: =IF(AND(tFeedIss[[#This Row],[Date]]="",tFeedIss[[#This Row],[Feed Type]]="",tFeedIss[[#This Row],[Pen ID]]="",tFeedIss[[#This Row],[Batch ID]]="",tFeedIss[[#This Row],[Quantity Issued in kg]]=""),"",IF(tFeedIss[[#This Row],[Date]]="","Missing date",IF(NOT(ISNUMBER(tFeedIss[[#This Row],[Date]])),"Date is not a valid date",IF(tFeedIss[[#This Row],[Feed Type]]="","Missing feed type",IF(COUNTIF(tFeedTypes[[Feed Type]],tFeedIss[[#This Row],[Feed Type]])=0,"Feed type not in LISTS",IF(tFeedIss[[#This Row],[Pen ID]]="","Missing Pen ID",IF(COUNTIF(tPens[[Pen ID]],tFeedIss[[#This Row],[Pen ID]])=0,"Pen "&tFeedIss[[#This Row],[Pen ID]]&" is not in PEN_REGISTER",IF(tFeedIss[[#This Row],[Batch ID]]="","Missing Batch ID",IF(COUNTIF(tBatches[[Batch ID]],tFeedIss[[#This Row],[Batch ID]])=0,"Batch "&tFeedIss[[#This Row],[Batch ID]]&" is not in BATCH_REGISTER",IF(COUNTIFS(tBatches[[Batch ID]],tFeedIss[[#This Row],[Batch ID]],tBatches[[Pen ID]],tFeedIss[[#This Row],[Pen ID]])=0,"Batch "&tFeedIss[[#This Row],[Batch ID]]&" belongs to pen "&INDEX(tBatches[[Pen ID]],MATCH(tFeedIss[[#This Row],[Batch ID]],tBatches[[Batch ID]],0)),IF(tFeedIss[[#This Row],[Date]]<INDEX(tBatches[[Batch Start Date]],MATCH(tFeedIss[[#This Row],[Batch ID]],tBatches[[Batch ID]],0)),"Date is before the batch start date",IF(AND(N(INDEX(tBatches[[Closing Date]],MATCH(tFeedIss[[#This Row],[Batch ID]],tBatches[[Batch ID]],0)))>0,tFeedIss[[#This Row],[Date]]>INDEX(tBatches[[Closing Date]],MATCH(tFeedIss[[#This Row],[Batch ID]],tBatches[[Batch ID]],0))),"Date is after the batch closing date",IF(N(tFeedIss[[#This Row],[Quantity Issued in kg]])<=0,"Quantity must be greater than 0",IF(tFeedIss[[#This Row],[Cost per kg]]=0,"No purchase of this feed on/before this date",IF(tFeedIss[[#This Row],[Store Balance on Date kg]]<-0.0001,"EXCEEDS STOCK by "&TEXT(-tFeedIss[[#This Row],[Store Balance on Date kg]],"#,##0.0")&" kg","OK")))))))))))))))
A15: 46267 | B15: ="FI-"&TEXT(ROW()-ROW(tFeedIss[[#Headers],[Date]]),"00000") | C15: Starter | D15: P004 | E15: BROILER-SEP-004 | F15: 50 | G15: =IFERROR(LOOKUP(2,1/((tFeedPur[[Feed Type]]=tFeedIss[[#This Row],[Feed Type]])*(tFeedPur[[Date]]<=tFeedIss[[#This Row],[Date]])),tFeedPur[[Avg Cost per kg After Purchase]]),0) | H15: =N(tFeedIss[[#This Row],[Quantity Issued in kg]])*tFeedIss[[#This Row],[Cost per kg]] | I15: Attendant 1 | J15: SAMPLE DATA - delete or replace. Same 500 kg Starter purchase shared across pens. | K15: =IFERROR(INDEX(tBatches[[Animal Type]],MATCH(tFeedIss[[#This Row],[Batch ID]],tBatches[[Batch ID]],0)),"") | L15: =SUMIFS(tFeedPur[[Total Quantity in kg]],tFeedPur[[Feed Type]],tFeedIss[[#This Row],[Feed Type]],tFeedPur[[Date]],"<="&tFeedIss[[#This Row],[Date]])-SUMIFS(tFeedIss[[Quantity Issued in kg]],tFeedIss[[Feed Type]],tFeedIss[[#This Row],[Feed Type]],tFeedIss[[Date]],"<="&tFeedIss[[#This Row],[Date]]) | M15: =IF(AND(tFeedIss[[#This Row],[Date]]="",tFeedIss[[#This Row],[Feed Type]]="",tFeedIss[[#This Row],[Pen ID]]="",tFeedIss[[#This Row],[Batch ID]]="",tFeedIss[[#This Row],[Quantity Issued in kg]]=""),"",IF(tFeedIss[[#This Row],[Date]]="","Missing date",IF(NOT(ISNUMBER(tFeedIss[[#This Row],[Date]])),"Date is not a valid date",IF(tFeedIss[[#This Row],[Feed Type]]="","Missing feed type",IF(COUNTIF(tFeedTypes[[Feed Type]],tFeedIss[[#This Row],[Feed Type]])=0,"Feed type not in LISTS",IF(tFeedIss[[#This Row],[Pen ID]]="","Missing Pen ID",IF(COUNTIF(tPens[[Pen ID]],tFeedIss[[#This Row],[Pen ID]])=0,"Pen "&tFeedIss[[#This Row],[Pen ID]]&" is not in PEN_REGISTER",IF(tFeedIss[[#This Row],[Batch ID]]="","Missing Batch ID",IF(COUNTIF(tBatches[[Batch ID]],tFeedIss[[#This Row],[Batch ID]])=0,"Batch "&tFeedIss[[#This Row],[Batch ID]]&" is not in BATCH_REGISTER",IF(COUNTIFS(tBatches[[Batch ID]],tFeedIss[[#This Row],[Batch ID]],tBatches[[Pen ID]],tFeedIss[[#This Row],[Pen ID]])=0,"Batch "&tFeedIss[[#This Row],[Batch ID]]&" belongs to pen "&INDEX(tBatches[[Pen ID]],MATCH(tFeedIss[[#This Row],[Batch ID]],tBatches[[Batch ID]],0)),IF(tFeedIss[[#This Row],[Date]]<INDEX(tBatches[[Batch Start Date]],MATCH(tFeedIss[[#This Row],[Batch ID]],tBatches[[Batch ID]],0)),"Date is before the batch start date",IF(AND(N(INDEX(tBatches[[Closing Date]],MATCH(tFeedIss[[#This Row],[Batch ID]],tBatches[[Batch ID]],0)))>0,tFeedIss[[#This Row],[Date]]>INDEX(tBatches[[Closing Date]],MATCH(tFeedIss[[#This Row],[Batch ID]],tBatches[[Batch ID]],0))),"Date is after the batch closing date",IF(N(tFeedIss[[#This Row],[Quantity Issued in kg]])<=0,"Quantity must be greater than 0",IF(tFeedIss[[#This Row],[Cost per kg]]=0,"No purchase of this feed on/before this date",IF(tFeedIss[[#This Row],[Store Balance on Date kg]]<-0.0001,"EXCEEDS STOCK by "&TEXT(-tFeedIss[[#This Row],[Store Balance on Date kg]],"#,##0.0")&" kg","OK")))))))))))))))
A16: 46275 | B16: ="FI-"&TEXT(ROW()-ROW(tFeedIss[[#Headers],[Date]]),"00000") | C16: Starter | D16: P001 | E16: BROILER-SEP-001 | F16: 60 | G16: =IFERROR(LOOKUP(2,1/((tFeedPur[[Feed Type]]=tFeedIss[[#This Row],[Feed Type]])*(tFeedPur[[Date]]<=tFeedIss[[#This Row],[Date]])),tFeedPur[[Avg Cost per kg After Purchase]]),0) | H16: =N(tFeedIss[[#This Row],[Quantity Issued in kg]])*tFeedIss[[#This Row],[Cost per kg]] | I16: Attendant 1 | J16: SAMPLE DATA - delete or replace | K16: =IFERROR(INDEX(tBatches[[Animal Type]],MATCH(tFeedIss[[#This Row],[Batch ID]],tBatches[[Batch ID]],0)),"") | L16: =SUMIFS(tFeedPur[[Total Quantity in kg]],tFeedPur[[Feed Type]],tFeedIss[[#This Row],[Feed Type]],tFeedPur[[Date]],"<="&tFeedIss[[#This Row],[Date]])-SUMIFS(tFeedIss[[Quantity Issued in kg]],tFeedIss[[Feed Type]],tFeedIss[[#This Row],[Feed Type]],tFeedIss[[Date]],"<="&tFeedIss[[#This Row],[Date]]) | M16: =IF(AND(tFeedIss[[#This Row],[Date]]="",tFeedIss[[#This Row],[Feed Type]]="",tFeedIss[[#This Row],[Pen ID]]="",tFeedIss[[#This Row],[Batch ID]]="",tFeedIss[[#This Row],[Quantity Issued in kg]]=""),"",IF(tFeedIss[[#This Row],[Date]]="","Missing date",IF(NOT(ISNUMBER(tFeedIss[[#This Row],[Date]])),"Date is not a valid date",IF(tFeedIss[[#This Row],[Feed Type]]="","Missing feed type",IF(COUNTIF(tFeedTypes[[Feed Type]],tFeedIss[[#This Row],[Feed Type]])=0,"Feed type not in LISTS",IF(tFeedIss[[#This Row],[Pen ID]]="","Missing Pen ID",IF(COUNTIF(tPens[[Pen ID]],tFeedIss[[#This Row],[Pen ID]])=0,"Pen "&tFeedIss[[#This Row],[Pen ID]]&" is not in PEN_REGISTER",IF(tFeedIss[[#This Row],[Batch ID]]="","Missing Batch ID",IF(COUNTIF(tBatches[[Batch ID]],tFeedIss[[#This Row],[Batch ID]])=0,"Batch "&tFeedIss[[#This Row],[Batch ID]]&" is not in BATCH_REGISTER",IF(COUNTIFS(tBatches[[Batch ID]],tFeedIss[[#This Row],[Batch ID]],tBatches[[Pen ID]],tFeedIss[[#This Row],[Pen ID]])=0,"Batch "&tFeedIss[[#This Row],[Batch ID]]&" belongs to pen "&INDEX(tBatches[[Pen ID]],MATCH(tFeedIss[[#This Row],[Batch ID]],tBatches[[Batch ID]],0)),IF(tFeedIss[[#This Row],[Date]]<INDEX(tBatches[[Batch Start Date]],MATCH(tFeedIss[[#This Row],[Batch ID]],tBatches[[Batch ID]],0)),"Date is before the batch start date",IF(AND(N(INDEX(tBatches[[Closing Date]],MATCH(tFeedIss[[#This Row],[Batch ID]],tBatches[[Batch ID]],0)))>0,tFeedIss[[#This Row],[Date]]>INDEX(tBatches[[Closing Date]],MATCH(tFeedIss[[#This Row],[Batch ID]],tBatches[[Batch ID]],0))),"Date is after the batch closing date",IF(N(tFeedIss[[#This Row],[Quantity Issued in kg]])<=0,"Quantity must be greater than 0",IF(tFeedIss[[#This Row],[Cost per kg]]=0,"No purchase of this feed on/before this date",IF(tFeedIss[[#This Row],[Store Balance on Date kg]]<-0.0001,"EXCEEDS STOCK by "&TEXT(-tFeedIss[[#This Row],[Store Balance on Date kg]],"#,##0.0")&" kg","OK")))))))))))))))
... A28: 46290 | B28: ="FI-"&TEXT(ROW()-ROW(tFeedIss[[#Headers],[Date]]),"00000") | C28: Starter | D28: P003 | E28: BROILER-SEP-003 | F28: 50 | G28: =IFERROR(LOOKUP(2,1/((tFeedPur[[Feed Type]]=tFeedIss[[#This Row],[Feed Type]])*(tFeedPur[[Date]]<=tFeedIss[[#This Row],[Date]])),tFeedPur[[Avg Cost per kg After Purchase]]),0) | H28: =N(tFeedIss[[#This Row],[Quantity Issued in kg]])*tFeedIss[[#This Row],[Cost per kg]] | I28: Attendant 1 | J28: SAMPLE DATA - delete or replace | K28: =IFERROR(INDEX(tBatches[[Animal Type]],MATCH(tFeedIss[[#This Row],[Batch ID]],tBatches[[Batch ID]],0)),"") | L28: =SUMIFS(tFeedPur[[Total Quantity in kg]],tFeedPur[[Feed Type]],tFeedIss[[#This Row],[Feed Type]],tFeedPur[[Date]],"<="&tFeedIss[[#This Row],[Date]])-SUMIFS(tFeedIss[[Quantity Issued in kg]],tFeedIss[[Feed Type]],tFeedIss[[#This Row],[Feed Type]],tFeedIss[[Date]],"<="&tFeedIss[[#This Row],[Date]]) | M28: =IF(AND(tFeedIss[[#This Row],[Date]]="",tFeedIss[[#This Row],[Feed Type]]="",tFeedIss[[#This Row],[Pen ID]]="",tFeedIss[[#This Row],[Batch ID]]="",tFeedIss[[#This Row],[Quantity Issued in kg]]=""),"",IF(tFeedIss[[#This Row],[Date]]="","Missing date",IF(NOT(ISNUMBER(tFeedIss[[#This Row],[Date]])),"Date is not a valid date",IF(tFeedIss[[#This Row],[Feed Type]]="","Missing feed type",IF(COUNTIF(tFeedTypes[[Feed Type]],tFeedIss[[#This Row],[Feed Type]])=0,"Feed type not in LISTS",IF(tFeedIss[[#This Row],[Pen ID]]="","Missing Pen ID",IF(COUNTIF(tPens[[Pen ID]],tFeedIss[[#This Row],[Pen ID]])=0,"Pen "&tFeedIss[[#This Row],[Pen ID]]&" is not in PEN_REGISTER",IF(tFeedIss[[#This Row],[Batch ID]]="","Missing Batch ID",IF(COUNTIF(tBatches[[Batch ID]],tFeedIss[[#This Row],[Batch ID]])=0,"Batch "&tFeedIss[[#This Row],[Batch ID]]&" is not in BATCH_REGISTER",IF(COUNTIFS(tBatches[[Batch ID]],tFeedIss[[#This Row],[Batch ID]],tBatches[[Pen ID]],tFeedIss[[#This Row],[Pen ID]])=0,"Batch "&tFeedIss[[#This Row],[Batch ID]]&" belongs to pen "&INDEX(tBatches[[Pen ID]],MATCH(tFeedIss[[#This Row],[Batch ID]],tBatches[[Batch ID]],0)),IF(tFeedIss[[#This Row],[Date]]<INDEX(tBatches[[Batch Start Date]],MATCH(tFeedIss[[#This Row],[Batch ID]],tBatches[[Batch ID]],0)),"Date is before the batch start date",IF(AND(N(INDEX(tBatches[[Closing Date]],MATCH(tFeedIss[[#This Row],[Batch ID]],tBatches[[Batch ID]],0)))>0,tFeedIss[[#This Row],[Date]]>INDEX(tBatches[[Closing Date]],MATCH(tFeedIss[[#This Row],[Batch ID]],tBatches[[Batch ID]],0))),"Date is after the batch closing date",IF(N(tFeedIss[[#This Row],[Quantity Issued in kg]])<=0,"Quantity must be greater than 0",IF(tFeedIss[[#This Row],[Cost per kg]]=0,"No purchase of this feed on/before this date",IF(tFeedIss[[#This Row],[Store Balance on Date kg]]<-0.0001,"EXCEEDS STOCK by "&TEXT(-tFeedIss[[#This Row],[Store Balance on Date kg]],"#,##0.0")&" kg","OK")))))))))))))))

Sheet DRUG_PURCHASES
A1: DRUG PURCHASES
A2: Record each drug/vaccine purchase once. Unused drugs remain inventory. Quantities are in the drug's Stock Unit set on LISTS (ml, g, doses, tablets ...).
A3: ■ GREEN header = you enter / select ■ GREY header = automatic (do not type) Add a new record by typing in the first empty row directly under the table.
A4: Date | B4: Purchase ID | C4: Drug Name | D4: Form/Concentration | E4: Supplier | F4: Quantity Purchased | G4: Unit | H4: Unit Cost | I4: Total Cost | J4: Expiry Date | K4: Batch Number | L4: Payment Method | M4: Notes | N4: Remaining in Lot | O4: Purchase No. of Drug | P4: Stock Before Purchase | Q4: Avg Cost per Unit After Purchase | R4: Expiry Status | S4: Check
A5: 46174 | B5: ="DP-"&TEXT(ROW()-ROW(tDrugPur[[#Headers],[Date]]),"00000") | C5: Dewormer | D5: =IFERROR(INDEX(tDrugs[[Form/Concentration]],MATCH(tDrugPur[[#This Row],[Drug Name]],tDrugs[[Drug Name]],0))&"","") | E5: Vet Store (sample) | F5: 200 | G5: =IFERROR(INDEX(tDrugs[[Stock Unit]],MATCH(tDrugPur[[#This Row],[Drug Name]],tDrugs[[Drug Name]],0))&"","") | H5: 15 | I5: =N(tDrugPur[[#This Row],[Quantity Purchased]])*N(tDrugPur[[#This Row],[Unit Cost]]) | J5: 46538 | K5: DW0601 | L5: Cash | M5: SAMPLE DATA - delete or replace | N5: =IF(tDrugPur[[#This Row],[Batch Number]]="","",N(tDrugPur[[#This Row],[Quantity Purchased]])-SUMIFS(tDrugUse[[Quantity Used]],tDrugUse[[Drug Name]],tDrugPur[[#This Row],[Drug Name]],tDrugUse[[Drug Batch Number]],tDrugPur[[#This Row],[Batch Number]])) | O5: =COUNTIF(INDEX(tDrugPur[[Drug Name]],1):tDrugPur[[#This Row],[Drug Name]],tDrugPur[[#This Row],[Drug Name]]) | P5: =MAX(0,IF((ROW()-ROW(tDrugPur[[#Headers],[Date]]))=1,0,SUMIFS(INDEX(tDrugPur[[Quantity Purchased]],1):INDEX(tDrugPur[[Quantity Purchased]],(ROW()-ROW(tDrugPur[[#Headers],[Date]]))-1),INDEX(tDrugPur[[Drug Name]],1):INDEX(tDrugPur[[Drug Name]],(ROW()-ROW(tDrugPur[[#Headers],[Date]]))-1),tDrugPur[[#This Row],[Drug Name]]))-SUMIFS(tDrugUse[[Quantity Used]],tDrugUse[[Drug Name]],tDrugPur[[#This Row],[Drug Name]],tDrugUse[[Date]],"<"&tDrugPur[[#This Row],[Date]])) | Q5: =IFERROR((tDrugPur[[#This Row],[Stock Before Purchase]]*IF(tDrugPur[[#This Row],[Purchase No. of Drug]]=1,0,LOOKUP(2,1/(INDEX(tDrugPur[[Drug Name]],1):INDEX(tDrugPur[[Drug Name]],(ROW()-ROW(tDrugPur[[#Headers],[Date]]))-1)=tDrugPur[[#This Row],[Drug Name]]),INDEX(tDrugPur[[Avg Cost per Unit After Purchase]],1):INDEX(tDrugPur[[Avg Cost per Unit After Purchase]],(ROW()-ROW(tDrugPur[[#Headers],[Date]]))-1)))+N(tDrugPur[[#This Row],[Total Cost]]))/(tDrugPur[[#This Row],[Stock Before Purchase]]+N(tDrugPur[[#This Row],[Quantity Purchased]])),IF(tDrugPur[[#This Row],[Purchase No. of Drug]]=1,0,LOOKUP(2,1/(INDEX(tDrugPur[[Drug Name]],1):INDEX(tDrugPur[[Drug Name]],(ROW()-ROW(tDrugPur[[#Headers],[Date]]))-1)=tDrugPur[[#This Row],[Drug Name]]),INDEX(tDrugPur[[Avg Cost per Unit After Purchase]],1):INDEX(tDrugPur[[Avg Cost per Unit After Purchase]],(ROW()-ROW(tDrugPur[[#Headers],[Date]]))-1)))) | R5: =IF(N(tDrugPur[[#This Row],[Expiry Date]])=0,"",IF(AND(tDrugPur[[#This Row],[Remaining in Lot]]<>"",N(tDrugPur[[#This Row],[Remaining in Lot]])<=0),"Used up",IF(tDrugPur[[#This Row],[Expiry Date]]<TODAY(),"EXPIRED",IF(tDrugPur[[#This Row],[Expiry Date]]-TODAY()<=ExpiryWarnDays,"Expires in "&(tDrugPur[[#This Row],[Expiry Date]]-TODAY())&" days","OK")))) | S5: =IF(AND(tDrugPur[[#This Row],[Date]]="",tDrugPur[[#This Row],[Drug Name]]="",tDrugPur[[#This Row],[Quantity Purchased]]=""),"",IF(tDrugPur[[#This Row],[Date]]="","Missing date",IF(NOT(ISNUMBER(tDrugPur[[#This Row],[Date]])),"Date is not a valid date",IF(AND((ROW()-ROW(tDrugPur[[#Headers],[Date]]))>1,tDrugPur[[#This Row],[Date]]<INDEX(tDrugPur[[Date]],MAX(1,(ROW()-ROW(tDrugPur[[#Headers],[Date]]))-1))),"Out of date order - insert this row after earlier purchases",IF(tDrugPur[[#This Row],[Drug Name]]="","Missing drug name",IF(COUNTIF(tDrugs[[Drug Name]],tDrugPur[[#This Row],[Drug Name]])=0,"Drug not in LISTS",IF(N(tDrugPur[[#This Row],[Quantity Purchased]])<=0,"Quantity must be greater than 0",IF(tDrugPur[[#This Row],[Unit Cost]]="","Missing unit cost",IF(N(tDrugPur[[#This Row],[Expiry Date]])=0,"Missing expiry date",IF(tDrugPur[[#This Row],[Payment Method]]="","Missing payment method","OK"))))))))))
A6: 46204 | B6: ="DP-"&TEXT(ROW()-ROW(tDrugPur[[#Headers],[Date]]),"00000") | C6: Anticoccidial | D6: =IFERROR(INDEX(tDrugs[[Form/Concentration]],MATCH(tDrugPur[[#This Row],[Drug Name]],tDrugs[[Drug Name]],0))&"","") | E6: Vet Store (sample) | F6: 500 | G6: =IFERROR(INDEX(tDrugs[[Stock Unit]],MATCH(tDrugPur[[#This Row],[Drug Name]],tDrugs[[Drug Name]],0))&"","") | H6: 12 | I6: =N(tDrugPur[[#This Row],[Quantity Purchased]])*N(tDrugPur[[#This Row],[Unit Cost]]) | J6: 46266 | K6: AC0701 | L6: Cash | M6: SAMPLE DATA - delete or replace | N6: =IF(tDrugPur[[#This Row],[Batch Number]]="","",N(tDrugPur[[#This Row],[Quantity Purchased]])-SUMIFS(tDrugUse[[Quantity Used]],tDrugUse[[Drug Name]],tDrugPur[[#This Row],[Drug Name]],tDrugUse[[Drug Batch Number]],tDrugPur[[#This Row],[Batch Number]])) | O6: =COUNTIF(INDEX(tDrugPur[[Drug Name]],1):tDrugPur[[#This Row],[Drug Name]],tDrugPur[[#This Row],[Drug Name]]) | P6: =MAX(0,IF((ROW()-ROW(tDrugPur[[#Headers],[Date]]))=1,0,SUMIFS(INDEX(tDrugPur[[Quantity Purchased]],1):INDEX(tDrugPur[[Quantity Purchased]],(ROW()-ROW(tDrugPur[[#Headers],[Date]]))-1),INDEX(tDrugPur[[Drug Name]],1):INDEX(tDrugPur[[Drug Name]],(ROW()-ROW(tDrugPur[[#Headers],[Date]]))-1),tDrugPur[[#This Row],[Drug Name]]))-SUMIFS(tDrugUse[[Quantity Used]],tDrugUse[[Drug Name]],tDrugPur[[#This Row],[Drug Name]],tDrugUse[[Date]],"<"&tDrugPur[[#This Row],[Date]])) | Q6: =IFERROR((tDrugPur[[#This Row],[Stock Before Purchase]]*IF(tDrugPur[[#This Row],[Purchase No. of Drug]]=1,0,LOOKUP(2,1/(INDEX(tDrugPur[[Drug Name]],1):INDEX(tDrugPur[[Drug Name]],(ROW()-ROW(tDrugPur[[#Headers],[Date]]))-1)=tDrugPur[[#This Row],[Drug Name]]),INDEX(tDrugPur[[Avg Cost per Unit After Purchase]],1):INDEX(tDrugPur[[Avg Cost per Unit After Purchase]],(ROW()-ROW(tDrugPur[[#Headers],[Date]]))-1)))+N(tDrugPur[[#This Row],[Total Cost]]))/(tDrugPur[[#This Row],[Stock Before Purchase]]+N(tDrugPur[[#This Row],[Quantity Purchased]])),IF(tDrugPur[[#This Row],[Purchase No. of Drug]]=1,0,LOOKUP(2,1/(INDEX(tDrugPur[[Drug Name]],1):INDEX(tDrugPur[[Drug Name]],(ROW()-ROW(tDrugPur[[#Headers],[Date]]))-1)=tDrugPur[[#This Row],[Drug Name]]),INDEX(tDrugPur[[Avg Cost per Unit After Purchase]],1):INDEX(tDrugPur[[Avg Cost per Unit After Purchase]],(ROW()-ROW(tDrugPur[[#Headers],[Date]]))-1)))) | R6: =IF(N(tDrugPur[[#This Row],[Expiry Date]])=0,"",IF(AND(tDrugPur[[#This Row],[Remaining in Lot]]<>"",N(tDrugPur[[#This Row],[Remaining in Lot]])<=0),"Used up",IF(tDrugPur[[#This Row],[Expiry Date]]<TODAY(),"EXPIRED",IF(tDrugPur[[#This Row],[Expiry Date]]-TODAY()<=ExpiryWarnDays,"Expires in "&(tDrugPur[[#This Row],[Expiry Date]]-TODAY())&" days","OK")))) | S6: =IF(AND(tDrugPur[[#This Row],[Date]]="",tDrugPur[[#This Row],[Drug Name]]="",tDrugPur[[#This Row],[Quantity Purchased]]=""),"",IF(tDrugPur[[#This Row],[Date]]="","Missing date",IF(NOT(ISNUMBER(tDrugPur[[#This Row],[Date]])),"Date is not a valid date",IF(AND((ROW()-ROW(tDrugPur[[#Headers],[Date]]))>1,tDrugPur[[#This Row],[Date]]<INDEX(tDrugPur[[Date]],MAX(1,(ROW()-ROW(tDrugPur[[#Headers],[Date]]))-1))),"Out of date order - insert this row after earlier purchases",IF(tDrugPur[[#This Row],[Drug Name]]="","Missing drug name",IF(COUNTIF(tDrugs[[Drug Name]],tDrugPur[[#This Row],[Drug Name]])=0,"Drug not in LISTS",IF(N(tDrugPur[[#This Row],[Quantity Purchased]])<=0,"Quantity must be greater than 0",IF(tDrugPur[[#This Row],[Unit Cost]]="","Missing unit cost",IF(N(tDrugPur[[#This Row],[Expiry Date]])=0,"Missing expiry date",IF(tDrugPur[[#This Row],[Payment Method]]="","Missing payment method","OK"))))))))))
A7: 46262 | B7: ="DP-"&TEXT(ROW()-ROW(tDrugPur[[#Headers],[Date]]),"00000") | C7: Multivitamin | D7: =IFERROR(INDEX(tDrugs[[Form/Concentration]],MATCH(tDrugPur[[#This Row],[Drug Name]],tDrugs[[Drug Name]],0))&"","") | E7: Vet Store (sample) | F7: 1000 | G7: =IFERROR(INDEX(tDrugs[[Stock Unit]],MATCH(tDrugPur[[#This Row],[Drug Name]],tDrugs[[Drug Name]],0))&"","") | H7: 8 | I7: =N(tDrugPur[[#This Row],[Quantity Purchased]])*N(tDrugPur[[#This Row],[Unit Cost]]) | J7: 46568 | K7: MV2408 | L7: Transfer | M7: SAMPLE DATA - delete or replace | N7: =IF(tDrugPur[[#This Row],[Batch Number]]="","",N(tDrugPur[[#This Row],[Quantity Purchased]])-SUMIFS(tDrugUse[[Quantity Used]],tDrugUse[[Drug Name]],tDrugPur[[#This Row],[Drug Name]],tDrugUse[[Drug Batch Number]],tDrugPur[[#This Row],[Batch Number]])) | O7: =COUNTIF(INDEX(tDrugPur[[Drug Name]],1):tDrugPur[[#This Row],[Drug Name]],tDrugPur[[#This Row],[Drug Name]]) | P7: =MAX(0,IF((ROW()-ROW(tDrugPur[[#Headers],[Date]]))=1,0,SUMIFS(INDEX(tDrugPur[[Quantity Purchased]],1):INDEX(tDrugPur[[Quantity Purchased]],(ROW()-ROW(tDrugPur[[#Headers],[Date]]))-1),INDEX(tDrugPur[[Drug Name]],1):INDEX(tDrugPur[[Drug Name]],(ROW()-ROW(tDrugPur[[#Headers],[Date]]))-1),tDrugPur[[#This Row],[Drug Name]]))-SUMIFS(tDrugUse[[Quantity Used]],tDrugUse[[Drug Name]],tDrugPur[[#This Row],[Drug Name]],tDrugUse[[Date]],"<"&tDrugPur[[#This Row],[Date]])) | Q7: =IFERROR((tDrugPur[[#This Row],[Stock Before Purchase]]*IF(tDrugPur[[#This Row],[Purchase No. of Drug]]=1,0,LOOKUP(2,1/(INDEX(tDrugPur[[Drug Name]],1):INDEX(tDrugPur[[Drug Name]],(ROW()-ROW(tDrugPur[[#Headers],[Date]]))-1)=tDrugPur[[#This Row],[Drug Name]]),INDEX(tDrugPur[[Avg Cost per Unit After Purchase]],1):INDEX(tDrugPur[[Avg Cost per Unit After Purchase]],(ROW()-ROW(tDrugPur[[#Headers],[Date]]))-1)))+N(tDrugPur[[#This Row],[Total Cost]]))/(tDrugPur[[#This Row],[Stock Before Purchase]]+N(tDrugPur[[#This Row],[Quantity Purchased]])),IF(tDrugPur[[#This Row],[Purchase No. of Drug]]=1,0,LOOKUP(2,1/(INDEX(tDrugPur[[Drug Name]],1):INDEX(tDrugPur[[Drug Name]],(ROW()-ROW(tDrugPur[[#Headers],[Date]]))-1)=tDrugPur[[#This Row],[Drug Name]]),INDEX(tDrugPur[[Avg Cost per Unit After Purchase]],1):INDEX(tDrugPur[[Avg Cost per Unit After Purchase]],(ROW()-ROW(tDrugPur[[#Headers],[Date]]))-1)))) | R7: =IF(N(tDrugPur[[#This Row],[Expiry Date]])=0,"",IF(AND(tDrugPur[[#This Row],[Remaining in Lot]]<>"",N(tDrugPur[[#This Row],[Remaining in Lot]])<=0),"Used up",IF(tDrugPur[[#This Row],[Expiry Date]]<TODAY(),"EXPIRED",IF(tDrugPur[[#This Row],[Expiry Date]]-TODAY()<=ExpiryWarnDays,"Expires in "&(tDrugPur[[#This Row],[Expiry Date]]-TODAY())&" days","OK")))) | S7: =IF(AND(tDrugPur[[#This Row],[Date]]="",tDrugPur[[#This Row],[Drug Name]]="",tDrugPur[[#This Row],[Quantity Purchased]]=""),"",IF(tDrugPur[[#This Row],[Date]]="","Missing date",IF(NOT(ISNUMBER(tDrugPur[[#This Row],[Date]])),"Date is not a valid date",IF(AND((ROW()-ROW(tDrugPur[[#Headers],[Date]]))>1,tDrugPur[[#This Row],[Date]]<INDEX(tDrugPur[[Date]],MAX(1,(ROW()-ROW(tDrugPur[[#Headers],[Date]]))-1))),"Out of date order - insert this row after earlier purchases",IF(tDrugPur[[#This Row],[Drug Name]]="","Missing drug name",IF(COUNTIF(tDrugs[[Drug Name]],tDrugPur[[#This Row],[Drug Name]])=0,"Drug not in LISTS",IF(N(tDrugPur[[#This Row],[Quantity Purchased]])<=0,"Quantity must be greater than 0",IF(tDrugPur[[#This Row],[Unit Cost]]="","Missing unit cost",IF(N(tDrugPur[[#This Row],[Expiry Date]])=0,"Missing expiry date",IF(tDrugPur[[#This Row],[Payment Method]]="","Missing payment method","OK"))))))))))
A8: 46262 | B8: ="DP-"&TEXT(ROW()-ROW(tDrugPur[[#Headers],[Date]]),"00000") | C8: Antibiotic A | D8: =IFERROR(INDEX(tDrugs[[Form/Concentration]],MATCH(tDrugPur[[#This Row],[Drug Name]],tDrugs[[Drug Name]],0))&"","") | E8: Vet Store (sample) | F8: 500 | G8: =IFERROR(INDEX(tDrugs[[Stock Unit]],MATCH(tDrugPur[[#This Row],[Drug Name]],tDrugs[[Drug Name]],0))&"","") | H8: 30 | I8: =N(tDrugPur[[#This Row],[Quantity Purchased]])*N(tDrugPur[[#This Row],[Unit Cost]]) | J8: 46310 | K8: AB0826 | L8: Transfer | M8: SAMPLE DATA - delete or replace | N8: =IF(tDrugPur[[#This Row],[Batch Number]]="","",N(tDrugPur[[#This Row],[Quantity Purchased]])-SUMIFS(tDrugUse[[Quantity Used]],tDrugUse[[Drug Name]],tDrugPur[[#This Row],[Drug Name]],tDrugUse[[Drug Batch Number]],tDrugPur[[#This Row],[Batch Number]])) | O8: =COUNTIF(INDEX(tDrugPur[[Drug Name]],1):tDrugPur[[#This Row],[Drug Name]],tDrugPur[[#This Row],[Drug Name]]) | P8: =MAX(0,IF((ROW()-ROW(tDrugPur[[#Headers],[Date]]))=1,0,SUMIFS(INDEX(tDrugPur[[Quantity Purchased]],1):INDEX(tDrugPur[[Quantity Purchased]],(ROW()-ROW(tDrugPur[[#Headers],[Date]]))-1),INDEX(tDrugPur[[Drug Name]],1):INDEX(tDrugPur[[Drug Name]],(ROW()-ROW(tDrugPur[[#Headers],[Date]]))-1),tDrugPur[[#This Row],[Drug Name]]))-SUMIFS(tDrugUse[[Quantity Used]],tDrugUse[[Drug Name]],tDrugPur[[#This Row],[Drug Name]],tDrugUse[[Date]],"<"&tDrugPur[[#This Row],[Date]])) | Q8: =IFERROR((tDrugPur[[#This Row],[Stock Before Purchase]]*IF(tDrugPur[[#This Row],[Purchase No. of Drug]]=1,0,LOOKUP(2,1/(INDEX(tDrugPur[[Drug Name]],1):INDEX(tDrugPur[[Drug Name]],(ROW()-ROW(tDrugPur[[#Headers],[Date]]))-1)=tDrugPur[[#This Row],[Drug Name]]),INDEX(tDrugPur[[Avg Cost per Unit After Purchase]],1):INDEX(tDrugPur[[Avg Cost per Unit After Purchase]],(ROW()-ROW(tDrugPur[[#Headers],[Date]]))-1)))+N(tDrugPur[[#This Row],[Total Cost]]))/(tDrugPur[[#This Row],[Stock Before Purchase]]+N(tDrugPur[[#This Row],[Quantity Purchased]])),IF(tDrugPur[[#This Row],[Purchase No. of Drug]]=1,0,LOOKUP(2,1/(INDEX(tDrugPur[[Drug Name]],1):INDEX(tDrugPur[[Drug Name]],(ROW()-ROW(tDrugPur[[#Headers],[Date]]))-1)=tDrugPur[[#This Row],[Drug Name]]),INDEX(tDrugPur[[Avg Cost per Unit After Purchase]],1):INDEX(tDrugPur[[Avg Cost per Unit After Purchase]],(ROW()-ROW(tDrugPur[[#Headers],[Date]]))-1)))) | R8: =IF(N(tDrugPur[[#This Row],[Expiry Date]])=0,"",IF(AND(tDrugPur[[#This Row],[Remaining in Lot]]<>"",N(tDrugPur[[#This Row],[Remaining in Lot]])<=0),"Used up",IF(tDrugPur[[#This Row],[Expiry Date]]<TODAY(),"EXPIRED",IF(tDrugPur[[#This Row],[Expiry Date]]-TODAY()<=ExpiryWarnDays,"Expires in "&(tDrugPur[[#This Row],[Expiry Date]]-TODAY())&" days","OK")))) | S8: =IF(AND(tDrugPur[[#This Row],[Date]]="",tDrugPur[[#This Row],[Drug Name]]="",tDrugPur[[#This Row],[Quantity Purchased]]=""),"",IF(tDrugPur[[#This Row],[Date]]="","Missing date",IF(NOT(ISNUMBER(tDrugPur[[#This Row],[Date]])),"Date is not a valid date",IF(AND((ROW()-ROW(tDrugPur[[#Headers],[Date]]))>1,tDrugPur[[#This Row],[Date]]<INDEX(tDrugPur[[Date]],MAX(1,(ROW()-ROW(tDrugPur[[#Headers],[Date]]))-1))),"Out of date order - insert this row after earlier purchases",IF(tDrugPur[[#This Row],[Drug Name]]="","Missing drug name",IF(COUNTIF(tDrugs[[Drug Name]],tDrugPur[[#This Row],[Drug Name]])=0,"Drug not in LISTS",IF(N(tDrugPur[[#This Row],[Quantity Purchased]])<=0,"Quantity must be greater than 0",IF(tDrugPur[[#This Row],[Unit Cost]]="","Missing unit cost",IF(N(tDrugPur[[#This Row],[Expiry Date]])=0,"Missing expiry date",IF(tDrugPur[[#This Row],[Payment Method]]="","Missing payment method","OK"))))))))))
A9: 46262 | B9: ="DP-"&TEXT(ROW()-ROW(tDrugPur[[#Headers],[Date]]),"00000") | C9: ND Vaccine (Lasota) | D9: =IFERROR(INDEX(tDrugs[[Form/Concentration]],MATCH(tDrugPur[[#This Row],[Drug Name]],tDrugs[[Drug Name]],0))&"","") | E9: Vet Store (sample) | F9: 4000 | G9: =IFERROR(INDEX(tDrugs[[Stock Unit]],MATCH(tDrugPur[[#This Row],[Drug Name]],tDrugs[[Drug Name]],0))&"","") | H9: 2.5 | I9: =N(tDrugPur[[#This Row],[Quantity Purchased]])*N(tDrugPur[[#This Row],[Unit Cost]]) | J9: 46387 | K9: ND1001 | L9: Transfer | M9: SAMPLE DATA - delete or replace | N9: =IF(tDrugPur[[#This Row],[Batch Number]]="","",N(tDrugPur[[#This Row],[Quantity Purchased]])-SUMIFS(tDrugUse[[Quantity Used]],tDrugUse[[Drug Name]],tDrugPur[[#This Row],[Drug Name]],tDrugUse[[Drug Batch Number]],tDrugPur[[#This Row],[Batch Number]])) | O9: =COUNTIF(INDEX(tDrugPur[[Drug Name]],1):tDrugPur[[#This Row],[Drug Name]],tDrugPur[[#This Row],[Drug Name]]) | P9: =MAX(0,IF((ROW()-ROW(tDrugPur[[#Headers],[Date]]))=1,0,SUMIFS(INDEX(tDrugPur[[Quantity Purchased]],1):INDEX(tDrugPur[[Quantity Purchased]],(ROW()-ROW(tDrugPur[[#Headers],[Date]]))-1),INDEX(tDrugPur[[Drug Name]],1):INDEX(tDrugPur[[Drug Name]],(ROW()-ROW(tDrugPur[[#Headers],[Date]]))-1),tDrugPur[[#This Row],[Drug Name]]))-SUMIFS(tDrugUse[[Quantity Used]],tDrugUse[[Drug Name]],tDrugPur[[#This Row],[Drug Name]],tDrugUse[[Date]],"<"&tDrugPur[[#This Row],[Date]])) | Q9: =IFERROR((tDrugPur[[#This Row],[Stock Before Purchase]]*IF(tDrugPur[[#This Row],[Purchase No. of Drug]]=1,0,LOOKUP(2,1/(INDEX(tDrugPur[[Drug Name]],1):INDEX(tDrugPur[[Drug Name]],(ROW()-ROW(tDrugPur[[#Headers],[Date]]))-1)=tDrugPur[[#This Row],[Drug Name]]),INDEX(tDrugPur[[Avg Cost per Unit After Purchase]],1):INDEX(tDrugPur[[Avg Cost per Unit After Purchase]],(ROW()-ROW(tDrugPur[[#Headers],[Date]]))-1)))+N(tDrugPur[[#This Row],[Total Cost]]))/(tDrugPur[[#This Row],[Stock Before Purchase]]+N(tDrugPur[[#This Row],[Quantity Purchased]])),IF(tDrugPur[[#This Row],[Purchase No. of Drug]]=1,0,LOOKUP(2,1/(INDEX(tDrugPur[[Drug Name]],1):INDEX(tDrugPur[[Drug Name]],(ROW()-ROW(tDrugPur[[#Headers],[Date]]))-1)=tDrugPur[[#This Row],[Drug Name]]),INDEX(tDrugPur[[Avg Cost per Unit After Purchase]],1):INDEX(tDrugPur[[Avg Cost per Unit After Purchase]],(ROW()-ROW(tDrugPur[[#Headers],[Date]]))-1)))) | R9: =IF(N(tDrugPur[[#This Row],[Expiry Date]])=0,"",IF(AND(tDrugPur[[#This Row],[Remaining in Lot]]<>"",N(tDrugPur[[#This Row],[Remaining in Lot]])<=0),"Used up",IF(tDrugPur[[#This Row],[Expiry Date]]<TODAY(),"EXPIRED",IF(tDrugPur[[#This Row],[Expiry Date]]-TODAY()<=ExpiryWarnDays,"Expires in "&(tDrugPur[[#This Row],[Expiry Date]]-TODAY())&" days","OK")))) | S9: =IF(AND(tDrugPur[[#This Row],[Date]]="",tDrugPur[[#This Row],[Drug Name]]="",tDrugPur[[#This Row],[Quantity Purchased]]=""),"",IF(tDrugPur[[#This Row],[Date]]="","Missing date",IF(NOT(ISNUMBER(tDrugPur[[#This Row],[Date]])),"Date is not a valid date",IF(AND((ROW()-ROW(tDrugPur[[#Headers],[Date]]))>1,tDrugPur[[#This Row],[Date]]<INDEX(tDrugPur[[Date]],MAX(1,(ROW()-ROW(tDrugPur[[#Headers],[Date]]))-1))),"Out of date order - insert this row after earlier purchases",IF(tDrugPur[[#This Row],[Drug Name]]="","Missing drug name",IF(COUNTIF(tDrugs[[Drug Name]],tDrugPur[[#This Row],[Drug Name]])=0,"Drug not in LISTS",IF(N(tDrugPur[[#This Row],[Quantity Purchased]])<=0,"Quantity must be greater than 0",IF(tDrugPur[[#This Row],[Unit Cost]]="","Missing unit cost",IF(N(tDrugPur[[#This Row],[Expiry Date]])=0,"Missing expiry date",IF(tDrugPur[[#This Row],[Payment Method]]="","Missing payment method","OK"))))))))))

Sheet DRUG_USAGE
A1: DRUG USAGE
A2: One row per administration per pen/batch. The same drug used in several pens at different dosages = separate rows. Cost is charged to the batch at weighted-average cost.
A3: ■ GREEN header = you enter / select ■ GREY header = automatic (do not type) Add a new record by typing in the first empty row directly under the table.
A4: Date | B4: Usage ID | C4: Drug Name | D4: Pen ID | E4: Batch ID | F4: Reason | G4: Dosage | H4: Quantity Used | I4: Unit | J4: Cost per Unit | K4: Total Cost | L4: Drug Batch Number | M4: Administered By | N4: Notes | O4: Animal Type | P4: Store Balance on Date | Q4: Check
A5: 46208 | B5: ="DU-"&TEXT(ROW()-ROW(tDrugUse[[#Headers],[Date]]),"00000") | C5: Anticoccidial | D5: P006 | E5: BROILER-JUL-001 | F5: Prevention | G5: 1 ml per litre, 3 days | H5: 150 | I5: =IFERROR(INDEX(tDrugs[[Stock Unit]],MATCH(tDrugUse[[#This Row],[Drug Name]],tDrugs[[Drug Name]],0))&"","") | J5: =IFERROR(LOOKUP(2,1/((tDrugPur[[Drug Name]]=tDrugUse[[#This Row],[Drug Name]])*(tDrugPur[[Date]]<=tDrugUse[[#This Row],[Date]])),tDrugPur[[Avg Cost per Unit After Purchase]]),0) | K5: =N(tDrugUse[[#This Row],[Quantity Used]])*tDrugUse[[#This Row],[Cost per Unit]] | L5: AC0701 | M5: Farm Manager | N5: SAMPLE DATA - delete or replace | O5: =IFERROR(INDEX(tBatches[[Animal Type]],MATCH(tDrugUse[[#This Row],[Batch ID]],tBatches[[Batch ID]],0)),"") | P5: =SUMIFS(tDrugPur[[Quantity Purchased]],tDrugPur[[Drug Name]],tDrugUse[[#This Row],[Drug Name]],tDrugPur[[Date]],"<="&tDrugUse[[#This Row],[Date]])-SUMIFS(tDrugUse[[Quantity Used]],tDrugUse[[Drug Name]],tDrugUse[[#This Row],[Drug Name]],tDrugUse[[Date]],"<="&tDrugUse[[#This Row],[Date]]) | Q5: =IF(AND(tDrugUse[[#This Row],[Date]]="",tDrugUse[[#This Row],[Drug Name]]="",tDrugUse[[#This Row],[Pen ID]]="",tDrugUse[[#This Row],[Batch ID]]="",tDrugUse[[#This Row],[Quantity Used]]=""),"",IF(tDrugUse[[#This Row],[Date]]="","Missing date",IF(NOT(ISNUMBER(tDrugUse[[#This Row],[Date]])),"Date is not a valid date",IF(tDrugUse[[#This Row],[Drug Name]]="","Missing drug name",IF(COUNTIF(tDrugs[[Drug Name]],tDrugUse[[#This Row],[Drug Name]])=0,"Drug not in LISTS",IF(tDrugUse[[#This Row],[Pen ID]]="","Missing Pen ID",IF(COUNTIF(tPens[[Pen ID]],tDrugUse[[#This Row],[Pen ID]])=0,"Pen "&tDrugUse[[#This Row],[Pen ID]]&" is not in PEN_REGISTER",IF(tDrugUse[[#This Row],[Batch ID]]="","Missing Batch ID",IF(COUNTIF(tBatches[[Batch ID]],tDrugUse[[#This Row],[Batch ID]])=0,"Batch "&tDrugUse[[#This Row],[Batch ID]]&" is not in BATCH_REGISTER",IF(COUNTIFS(tBatches[[Batch ID]],tDrugUse[[#This Row],[Batch ID]],tBatches[[Pen ID]],tDrugUse[[#This Row],[Pen ID]])=0,"Batch "&tDrugUse[[#This Row],[Batch ID]]&" belongs to pen "&INDEX(tBatches[[Pen ID]],MATCH(tDrugUse[[#This Row],[Batch ID]],tBatches[[Batch ID]],0)),IF(tDrugUse[[#This Row],[Date]]<INDEX(tBatches[[Batch Start Date]],MATCH(tDrugUse[[#This Row],[Batch ID]],tBatches[[Batch ID]],0)),"Date is before the batch start date",IF(AND(N(INDEX(tBatches[[Closing Date]],MATCH(tDrugUse[[#This Row],[Batch ID]],tBatches[[Batch ID]],0)))>0,tDrugUse[[#This Row],[Date]]>INDEX(tBatches[[Closing Date]],MATCH(tDrugUse[[#This Row],[Batch ID]],tBatches[[Batch ID]],0))),"Date is after the batch closing date",IF(N(tDrugUse[[#This Row],[Quantity Used]])<=0,"Quantity must be greater than 0",IF(tDrugUse[[#This Row],[Cost per Unit]]=0,"No purchase of this drug on/before this date",IF(tDrugUse[[#This Row],[Store Balance on Date]]<-0.0001,"EXCEEDS STOCK by "&TEXT(-tDrugUse[[#This Row],[Store Balance on Date]],"#,##0.0")&" "&tDrugUse[[#This Row],[Unit]],IF(AND(tDrugUse[[#This Row],[Drug Batch Number]]<>"",COUNTIFS(tDrugPur[[Drug Name]],tDrugUse[[#This Row],[Drug Name]],tDrugPur[[Batch Number]],tDrugUse[[#This Row],[Drug Batch Number]])=0),"Drug batch number not found in purchases",IF(AND(tDrugUse[[#This Row],[Drug Batch Number]]<>"",N(_xlfn.MAXIFS(tDrugPur[[Expiry Date]],tDrugPur[[Drug Name]],tDrugUse[[#This Row],[Drug Name]],tDrugPur[[Batch Number]],tDrugUse[[#This Row],[Drug Batch Number]]))>0,tDrugUse[[#This Row],[Date]]>_xlfn.MAXIFS(tDrugPur[[Expiry Date]],tDrugPur[[Drug Name]],tDrugUse[[#This Row],[Drug Name]],tDrugPur[[Batch Number]],tDrugUse[[#This Row],[Drug Batch Number]])),"Lot was expired on "&TEXT(_xlfn.MAXIFS(tDrugPur[[Expiry Date]],tDrugPur[[Drug Name]],tDrugUse[[#This Row],[Drug Name]],tDrugPur[[Batch Number]],tDrugUse[[#This Row],[Drug Batch Number]]),"dd/mm/yyyy"),"OK")))))))))))))))))
A6: 46235 | B6: ="DU-"&TEXT(ROW()-ROW(tDrugUse[[#Headers],[Date]]),"00000") | C6: Dewormer | D6: P005 | E6: LAYER-JUN-001 | F6: Deworming | G6: As per label | H6: 100 | I6: =IFERROR(INDEX(tDrugs[[Stock Unit]],MATCH(tDrugUse[[#This Row],[Drug Name]],tDrugs[[Drug Name]],0))&"","") | J6: =IFERROR(LOOKUP(2,1/((tDrugPur[[Drug Name]]=tDrugUse[[#This Row],[Drug Name]])*(tDrugPur[[Date]]<=tDrugUse[[#This Row],[Date]])),tDrugPur[[Avg Cost per Unit After Purchase]]),0) | K6: =N(tDrugUse[[#This Row],[Quantity Used]])*tDrugUse[[#This Row],[Cost per Unit]] | L6: DW0601 | M6: Farm Manager | N6: SAMPLE DATA - delete or replace | O6: =IFERROR(INDEX(tBatches[[Animal Type]],MATCH(tDrugUse[[#This Row],[Batch ID]],tBatches[[Batch ID]],0)),"") | P6: =SUMIFS(tDrugPur[[Quantity Purchased]],tDrugPur[[Drug Name]],tDrugUse[[#This Row],[Drug Name]],tDrugPur[[Date]],"<="&tDrugUse[[#This Row],[Date]])-SUMIFS(tDrugUse[[Quantity Used]],tDrugUse[[Drug Name]],tDrugUse[[#This Row],[Drug Name]],tDrugUse[[Date]],"<="&tDrugUse[[#This Row],[Date]]) | Q6: =IF(AND(tDrugUse[[#This Row],[Date]]="",tDrugUse[[#This Row],[Drug Name]]="",tDrugUse[[#This Row],[Pen ID]]="",tDrugUse[[#This Row],[Batch ID]]="",tDrugUse[[#This Row],[Quantity Used]]=""),"",IF(tDrugUse[[#This Row],[Date]]="","Missing date",IF(NOT(ISNUMBER(tDrugUse[[#This Row],[Date]])),"Date is not a valid date",IF(tDrugUse[[#This Row],[Drug Name]]="","Missing drug name",IF(COUNTIF(tDrugs[[Drug Name]],tDrugUse[[#This Row],[Drug Name]])=0,"Drug not in LISTS",IF(tDrugUse[[#This Row],[Pen ID]]="","Missing Pen ID",IF(COUNTIF(tPens[[Pen ID]],tDrugUse[[#This Row],[Pen ID]])=0,"Pen "&tDrugUse[[#This Row],[Pen ID]]&" is not in PEN_REGISTER",IF(tDrugUse[[#This Row],[Batch ID]]="","Missing Batch ID",IF(COUNTIF(tBatches[[Batch ID]],tDrugUse[[#This Row],[Batch ID]])=0,"Batch "&tDrugUse[[#This Row],[Batch ID]]&" is not in BATCH_REGISTER",IF(COUNTIFS(tBatches[[Batch ID]],tDrugUse[[#This Row],[Batch ID]],tBatches[[Pen ID]],tDrugUse[[#This Row],[Pen ID]])=0,"Batch "&tDrugUse[[#This Row],[Batch ID]]&" belongs to pen "&INDEX(tBatches[[Pen ID]],MATCH(tDrugUse[[#This Row],[Batch ID]],tBatches[[Batch ID]],0)),IF(tDrugUse[[#This Row],[Date]]<INDEX(tBatches[[Batch Start Date]],MATCH(tDrugUse[[#This Row],[Batch ID]],tBatches[[Batch ID]],0)),"Date is before the batch start date",IF(AND(N(INDEX(tBatches[[Closing Date]],MATCH(tDrugUse[[#This Row],[Batch ID]],tBatches[[Batch ID]],0)))>0,tDrugUse[[#This Row],[Date]]>INDEX(tBatches[[Closing Date]],MATCH(tDrugUse[[#This Row],[Batch ID]],tBatches[[Batch ID]],0))),"Date is after the batch closing date",IF(N(tDrugUse[[#This Row],[Quantity Used]])<=0,"Quantity must be greater than 0",IF(tDrugUse[[#This Row],[Cost per Unit]]=0,"No purchase of this drug on/before this date",IF(tDrugUse[[#This Row],[Store Balance on Date]]<-0.0001,"EXCEEDS STOCK by "&TEXT(-tDrugUse[[#This Row],[Store Balance on Date]],"#,##0.0")&" "&tDrugUse[[#This Row],[Unit]],IF(AND(tDrugUse[[#This Row],[Drug Batch Number]]<>"",COUNTIFS(tDrugPur[[Drug Name]],tDrugUse[[#This Row],[Drug Name]],tDrugPur[[Batch Number]],tDrugUse[[#This Row],[Drug Batch Number]])=0),"Drug batch number not found in purchases",IF(AND(tDrugUse[[#This Row],[Drug Batch Number]]<>"",N(_xlfn.MAXIFS(tDrugPur[[Expiry Date]],tDrugPur[[Drug Name]],tDrugUse[[#This Row],[Drug Name]],tDrugPur[[Batch Number]],tDrugUse[[#This Row],[Drug Batch Number]]))>0,tDrugUse[[#This Row],[Date]]>_xlfn.MAXIFS(tDrugPur[[Expiry Date]],tDrugPur[[Drug Name]],tDrugUse[[#This Row],[Drug Name]],tDrugPur[[Batch Number]],tDrugUse[[#This Row],[Drug Batch Number]])),"Lot was expired on "&TEXT(_xlfn.MAXIFS(tDrugPur[[Expiry Date]],tDrugPur[[Drug Name]],tDrugUse[[#This Row],[Drug Name]],tDrugPur[[Batch Number]],tDrugUse[[#This Row],[Drug Batch Number]]),"dd/mm/yyyy"),"OK")))))))))))))))))
A7: 46268 | B7: ="DU-"&TEXT(ROW()-ROW(tDrugUse[[#Headers],[Date]]),"00000") | C7: Multivitamin | D7: P001 | E7: BROILER-SEP-001 | F7: Vitamin / Supplement | G7: 10 ml per 20 litres | H7: 50 | I7: =IFERROR(INDEX(tDrugs[[Stock Unit]],MATCH(tDrugUse[[#This Row],[Drug Name]],tDrugs[[Drug Name]],0))&"","") | J7: =IFERROR(LOOKUP(2,1/((tDrugPur[[Drug Name]]=tDrugUse[[#This Row],[Drug Name]])*(tDrugPur[[Date]]<=tDrugUse[[#This Row],[Date]])),tDrugPur[[Avg Cost per Unit After Purchase]]),0) | K7: =N(tDrugUse[[#This Row],[Quantity Used]])*tDrugUse[[#This Row],[Cost per Unit]] | L7: MV2408 | M7: Farm Manager | N7: SAMPLE DATA - delete or replace. Same drug, different pens & dosages = separate records. | O7: =IFERROR(INDEX(tBatches[[Animal Type]],MATCH(tDrugUse[[#This Row],[Batch ID]],tBatches[[Batch ID]],0)),"") | P7: =SUMIFS(tDrugPur[[Quantity Purchased]],tDrugPur[[Drug Name]],tDrugUse[[#This Row],[Drug Name]],tDrugPur[[Date]],"<="&tDrugUse[[#This Row],[Date]])-SUMIFS(tDrugUse[[Quantity Used]],tDrugUse[[Drug Name]],tDrugUse[[#This Row],[Drug Name]],tDrugUse[[Date]],"<="&tDrugUse[[#This Row],[Date]]) | Q7: =IF(AND(tDrugUse[[#This Row],[Date]]="",tDrugUse[[#This Row],[Drug Name]]="",tDrugUse[[#This Row],[Pen ID]]="",tDrugUse[[#This Row],[Batch ID]]="",tDrugUse[[#This Row],[Quantity Used]]=""),"",IF(tDrugUse[[#This Row],[Date]]="","Missing date",IF(NOT(ISNUMBER(tDrugUse[[#This Row],[Date]])),"Date is not a valid date",IF(tDrugUse[[#This Row],[Drug Name]]="","Missing drug name",IF(COUNTIF(tDrugs[[Drug Name]],tDrugUse[[#This Row],[Drug Name]])=0,"Drug not in LISTS",IF(tDrugUse[[#This Row],[Pen ID]]="","Missing Pen ID",IF(COUNTIF(tPens[[Pen ID]],tDrugUse[[#This Row],[Pen ID]])=0,"Pen "&tDrugUse[[#This Row],[Pen ID]]&" is not in PEN_REGISTER",IF(tDrugUse[[#This Row],[Batch ID]]="","Missing Batch ID",IF(COUNTIF(tBatches[[Batch ID]],tDrugUse[[#This Row],[Batch ID]])=0,"Batch "&tDrugUse[[#This Row],[Batch ID]]&" is not in BATCH_REGISTER",IF(COUNTIFS(tBatches[[Batch ID]],tDrugUse[[#This Row],[Batch ID]],tBatches[[Pen ID]],tDrugUse[[#This Row],[Pen ID]])=0,"Batch "&tDrugUse[[#This Row],[Batch ID]]&" belongs to pen "&INDEX(tBatches[[Pen ID]],MATCH(tDrugUse[[#This Row],[Batch ID]],tBatches[[Batch ID]],0)),IF(tDrugUse[[#This Row],[Date]]<INDEX(tBatches[[Batch Start Date]],MATCH(tDrugUse[[#This Row],[Batch ID]],tBatches[[Batch ID]],0)),"Date is before the batch start date",IF(AND(N(INDEX(tBatches[[Closing Date]],MATCH(tDrugUse[[#This Row],[Batch ID]],tBatches[[Batch ID]],0)))>0,tDrugUse[[#This Row],[Date]]>INDEX(tBatches[[Closing Date]],MATCH(tDrugUse[[#This Row],[Batch ID]],tBatches[[Batch ID]],0))),"Date is after the batch closing date",IF(N(tDrugUse[[#This Row],[Quantity Used]])<=0,"Quantity must be greater than 0",IF(tDrugUse[[#This Row],[Cost per Unit]]=0,"No purchase of this drug on/before this date",IF(tDrugUse[[#This Row],[Store Balance on Date]]<-0.0001,"EXCEEDS STOCK by "&TEXT(-tDrugUse[[#This Row],[Store Balance on Date]],"#,##0.0")&" "&tDrugUse[[#This Row],[Unit]],IF(AND(tDrugUse[[#This Row],[Drug Batch Number]]<>"",COUNTIFS(tDrugPur[[Drug Name]],tDrugUse[[#This Row],[Drug Name]],tDrugPur[[Batch Number]],tDrugUse[[#This Row],[Drug Batch Number]])=0),"Drug batch number not found in purchases",IF(AND(tDrugUse[[#This Row],[Drug Batch Number]]<>"",N(_xlfn.MAXIFS(tDrugPur[[Expiry Date]],tDrugPur[[Drug Name]],tDrugUse[[#This Row],[Drug Name]],tDrugPur[[Batch Number]],tDrugUse[[#This Row],[Drug Batch Number]]))>0,tDrugUse[[#This Row],[Date]]>_xlfn.MAXIFS(tDrugPur[[Expiry Date]],tDrugPur[[Drug Name]],tDrugUse[[#This Row],[Drug Name]],tDrugPur[[Batch Number]],tDrugUse[[#This Row],[Drug Batch Number]])),"Lot was expired on "&TEXT(_xlfn.MAXIFS(tDrugPur[[Expiry Date]],tDrugPur[[Drug Name]],tDrugUse[[#This Row],[Drug Name]],tDrugPur[[Batch Number]],tDrugUse[[#This Row],[Drug Batch Number]]),"dd/mm/yyyy"),"OK")))))))))))))))))
A8: 46268 | B8: ="DU-"&TEXT(ROW()-ROW(tDrugUse[[#Headers],[Date]]),"00000") | C8: Multivitamin | D8: P002 | E8: BROILER-SEP-002 | F8: Vitamin / Supplement | G8: 5 ml per 20 litres | H8: 30 | I8: =IFERROR(INDEX(tDrugs[[Stock Unit]],MATCH(tDrugUse[[#This Row],[Drug Name]],tDrugs[[Drug Name]],0))&"","") | J8: =IFERROR(LOOKUP(2,1/((tDrugPur[[Drug Name]]=tDrugUse[[#This Row],[Drug Name]])*(tDrugPur[[Date]]<=tDrugUse[[#This Row],[Date]])),tDrugPur[[Avg Cost per Unit After Purchase]]),0) | K8: =N(tDrugUse[[#This Row],[Quantity Used]])*tDrugUse[[#This Row],[Cost per Unit]] | L8: MV2408 | M8: Farm Manager | N8: SAMPLE DATA - delete or replace. Same drug, different pens & dosages = separate records. | O8: =IFERROR(INDEX(tBatches[[Animal Type]],MATCH(tDrugUse[[#This Row],[Batch ID]],tBatches[[Batch ID]],0)),"") | P8: =SUMIFS(tDrugPur[[Quantity Purchased]],tDrugPur[[Drug Name]],tDrugUse[[#This Row],[Drug Name]],tDrugPur[[Date]],"<="&tDrugUse[[#This Row],[Date]])-SUMIFS(tDrugUse[[Quantity Used]],tDrugUse[[Drug Name]],tDrugUse[[#This Row],[Drug Name]],tDrugUse[[Date]],"<="&tDrugUse[[#This Row],[Date]]) | Q8: =IF(AND(tDrugUse[[#This Row],[Date]]="",tDrugUse[[#This Row],[Drug Name]]="",tDrugUse[[#This Row],[Pen ID]]="",tDrugUse[[#This Row],[Batch ID]]="",tDrugUse[[#This Row],[Quantity Used]]=""),"",IF(tDrugUse[[#This Row],[Date]]="","Missing date",IF(NOT(ISNUMBER(tDrugUse[[#This Row],[Date]])),"Date is not a valid date",IF(tDrugUse[[#This Row],[Drug Name]]="","Missing drug name",IF(COUNTIF(tDrugs[[Drug Name]],tDrugUse[[#This Row],[Drug Name]])=0,"Drug not in LISTS",IF(tDrugUse[[#This Row],[Pen ID]]="","Missing Pen ID",IF(COUNTIF(tPens[[Pen ID]],tDrugUse[[#This Row],[Pen ID]])=0,"Pen "&tDrugUse[[#This Row],[Pen ID]]&" is not in PEN_REGISTER",IF(tDrugUse[[#This Row],[Batch ID]]="","Missing Batch ID",IF(COUNTIF(tBatches[[Batch ID]],tDrugUse[[#This Row],[Batch ID]])=0,"Batch "&tDrugUse[[#This Row],[Batch ID]]&" is not in BATCH_REGISTER",IF(COUNTIFS(tBatches[[Batch ID]],tDrugUse[[#This Row],[Batch ID]],tBatches[[Pen ID]],tDrugUse[[#This Row],[Pen ID]])=0,"Batch "&tDrugUse[[#This Row],[Batch ID]]&" belongs to pen "&INDEX(tBatches[[Pen ID]],MATCH(tDrugUse[[#This Row],[Batch ID]],tBatches[[Batch ID]],0)),IF(tDrugUse[[#This Row],[Date]]<INDEX(tBatches[[Batch Start Date]],MATCH(tDrugUse[[#This Row],[Batch ID]],tBatches[[Batch ID]],0)),"Date is before the batch start date",IF(AND(N(INDEX(tBatches[[Closing Date]],MATCH(tDrugUse[[#This Row],[Batch ID]],tBatches[[Batch ID]],0)))>0,tDrugUse[[#This Row],[Date]]>INDEX(tBatches[[Closing Date]],MATCH(tDrugUse[[#This Row],[Batch ID]],tBatches[[Batch ID]],0))),"Date is after the batch closing date",IF(N(tDrugUse[[#This Row],[Quantity Used]])<=0,"Quantity must be greater than 0",IF(tDrugUse[[#This Row],[Cost per Unit]]=0,"No purchase of this drug on/before this date",IF(tDrugUse[[#This Row],[Store Balance on Date]]<-0.0001,"EXCEEDS STOCK by "&TEXT(-tDrugUse[[#This Row],[Store Balance on Date]],"#,##0.0")&" "&tDrugUse[[#This Row],[Unit]],IF(AND(tDrugUse[[#This Row],[Drug Batch Number]]<>"",COUNTIFS(tDrugPur[[Drug Name]],tDrugUse[[#This Row],[Drug Name]],tDrugPur[[Batch Number]],tDrugUse[[#This Row],[Drug Batch Number]])=0),"Drug batch number not found in purchases",IF(AND(tDrugUse[[#This Row],[Drug Batch Number]]<>"",N(_xlfn.MAXIFS(tDrugPur[[Expiry Date]],tDrugPur[[Drug Name]],tDrugUse[[#This Row],[Drug Name]],tDrugPur[[Batch Number]],tDrugUse[[#This Row],[Drug Batch Number]]))>0,tDrugUse[[#This Row],[Date]]>_xlfn.MAXIFS(tDrugPur[[Expiry Date]],tDrugPur[[Drug Name]],tDrugUse[[#This Row],[Drug Name]],tDrugPur[[Batch Number]],tDrugUse[[#This Row],[Drug Batch Number]])),"Lot was expired on "&TEXT(_xlfn.MAXIFS(tDrugPur[[Expiry Date]],tDrugPur[[Drug Name]],tDrugUse[[#This Row],[Drug Name]],tDrugPur[[Batch Number]],tDrugUse[[#This Row],[Drug Batch Number]]),"dd/mm/yyyy"),"OK")))))))))))))))))
A9: 46268 | B9: ="DU-"&TEXT(ROW()-ROW(tDrugUse[[#Headers],[Date]]),"00000") | C9: Multivitamin | D9: P003 | E9: BROILER-SEP-003 | F9: Vitamin / Supplement | G9: 15 ml per 20 litres | H9: 70 | I9: =IFERROR(INDEX(tDrugs[[Stock Unit]],MATCH(tDrugUse[[#This Row],[Drug Name]],tDrugs[[Drug Name]],0))&"","") | J9: =IFERROR(LOOKUP(2,1/((tDrugPur[[Drug Name]]=tDrugUse[[#This Row],[Drug Name]])*(tDrugPur[[Date]]<=tDrugUse[[#This Row],[Date]])),tDrugPur[[Avg Cost per Unit After Purchase]]),0) | K9: =N(tDrugUse[[#This Row],[Quantity Used]])*tDrugUse[[#This Row],[Cost per Unit]] | L9: MV2408 | M9: Farm Manager | N9: SAMPLE DATA - delete or replace. Same drug, different pens & dosages = separate records. | O9: =IFERROR(INDEX(tBatches[[Animal Type]],MATCH(tDrugUse[[#This Row],[Batch ID]],tBatches[[Batch ID]],0)),"") | P9: =SUMIFS(tDrugPur[[Quantity Purchased]],tDrugPur[[Drug Name]],tDrugUse[[#This Row],[Drug Name]],tDrugPur[[Date]],"<="&tDrugUse[[#This Row],[Date]])-SUMIFS(tDrugUse[[Quantity Used]],tDrugUse[[Drug Name]],tDrugUse[[#This Row],[Drug Name]],tDrugUse[[Date]],"<="&tDrugUse[[#This Row],[Date]]) | Q9: =IF(AND(tDrugUse[[#This Row],[Date]]="",tDrugUse[[#This Row],[Drug Name]]="",tDrugUse[[#This Row],[Pen ID]]="",tDrugUse[[#This Row],[Batch ID]]="",tDrugUse[[#This Row],[Quantity Used]]=""),"",IF(tDrugUse[[#This Row],[Date]]="","Missing date",IF(NOT(ISNUMBER(tDrugUse[[#This Row],[Date]])),"Date is not a valid date",IF(tDrugUse[[#This Row],[Drug Name]]="","Missing drug name",IF(COUNTIF(tDrugs[[Drug Name]],tDrugUse[[#This Row],[Drug Name]])=0,"Drug not in LISTS",IF(tDrugUse[[#This Row],[Pen ID]]="","Missing Pen ID",IF(COUNTIF(tPens[[Pen ID]],tDrugUse[[#This Row],[Pen ID]])=0,"Pen "&tDrugUse[[#This Row],[Pen ID]]&" is not in PEN_REGISTER",IF(tDrugUse[[#This Row],[Batch ID]]="","Missing Batch ID",IF(COUNTIF(tBatches[[Batch ID]],tDrugUse[[#This Row],[Batch ID]])=0,"Batch "&tDrugUse[[#This Row],[Batch ID]]&" is not in BATCH_REGISTER",IF(COUNTIFS(tBatches[[Batch ID]],tDrugUse[[#This Row],[Batch ID]],tBatches[[Pen ID]],tDrugUse[[#This Row],[Pen ID]])=0,"Batch "&tDrugUse[[#This Row],[Batch ID]]&" belongs to pen "&INDEX(tBatches[[Pen ID]],MATCH(tDrugUse[[#This Row],[Batch ID]],tBatches[[Batch ID]],0)),IF(tDrugUse[[#This Row],[Date]]<INDEX(tBatches[[Batch Start Date]],MATCH(tDrugUse[[#This Row],[Batch ID]],tBatches[[Batch ID]],0)),"Date is before the batch start date",IF(AND(N(INDEX(tBatches[[Closing Date]],MATCH(tDrugUse[[#This Row],[Batch ID]],tBatches[[Batch ID]],0)))>0,tDrugUse[[#This Row],[Date]]>INDEX(tBatches[[Closing Date]],MATCH(tDrugUse[[#This Row],[Batch ID]],tBatches[[Batch ID]],0))),"Date is after the batch closing date",IF(N(tDrugUse[[#This Row],[Quantity Used]])<=0,"Quantity must be greater than 0",IF(tDrugUse[[#This Row],[Cost per Unit]]=0,"No purchase of this drug on/before this date",IF(tDrugUse[[#This Row],[Store Balance on Date]]<-0.0001,"EXCEEDS STOCK by "&TEXT(-tDrugUse[[#This Row],[Store Balance on Date]],"#,##0.0")&" "&tDrugUse[[#This Row],[Unit]],IF(AND(tDrugUse[[#This Row],[Drug Batch Number]]<>"",COUNTIFS(tDrugPur[[Drug Name]],tDrugUse[[#This Row],[Drug Name]],tDrugPur[[Batch Number]],tDrugUse[[#This Row],[Drug Batch Number]])=0),"Drug batch number not found in purchases",IF(AND(tDrugUse[[#This Row],[Drug Batch Number]]<>"",N(_xlfn.MAXIFS(tDrugPur[[Expiry Date]],tDrugPur[[Drug Name]],tDrugUse[[#This Row],[Drug Name]],tDrugPur[[Batch Number]],tDrugUse[[#This Row],[Drug Batch Number]]))>0,tDrugUse[[#This Row],[Date]]>_xlfn.MAXIFS(tDrugPur[[Expiry Date]],tDrugPur[[Drug Name]],tDrugUse[[#This Row],[Drug Name]],tDrugPur[[Batch Number]],tDrugUse[[#This Row],[Drug Batch Number]])),"Lot was expired on "&TEXT(_xlfn.MAXIFS(tDrugPur[[Expiry Date]],tDrugPur[[Drug Name]],tDrugUse[[#This Row],[Drug Name]],tDrugPur[[Batch Number]],tDrugUse[[#This Row],[Drug Batch Number]]),"dd/mm/yyyy"),"OK")))))))))))))))))
A10: 46273 | B10: ="DU-"&TEXT(ROW()-ROW(tDrugUse[[#Headers],[Date]]),"00000") | C10: ND Vaccine (Lasota) | D10: P001 | E10: BROILER-SEP-001 | F10: Vaccination | G10: 1 dose per bird | H10: 500 | I10: =IFERROR(INDEX(tDrugs[[Stock Unit]],MATCH(tDrugUse[[#This Row],[Drug Name]],tDrugs[[Drug Name]],0))&"","") | J10: =IFERROR(LOOKUP(2,1/((tDrugPur[[Drug Name]]=tDrugUse[[#This Row],[Drug Name]])*(tDrugPur[[Date]]<=tDrugUse[[#This Row],[Date]])),tDrugPur[[Avg Cost per Unit After Purchase]]),0) | K10: =N(tDrugUse[[#This Row],[Quantity Used]])*tDrugUse[[#This Row],[Cost per Unit]] | L10: ND1001 | M10: Farm Manager | N10: SAMPLE DATA - delete or replace | O10: =IFERROR(INDEX(tBatches[[Animal Type]],MATCH(tDrugUse[[#This Row],[Batch ID]],tBatches[[Batch ID]],0)),"") | P10: =SUMIFS(tDrugPur[[Quantity Purchased]],tDrugPur[[Drug Name]],tDrugUse[[#This Row],[Drug Name]],tDrugPur[[Date]],"<="&tDrugUse[[#This Row],[Date]])-SUMIFS(tDrugUse[[Quantity Used]],tDrugUse[[Drug Name]],tDrugUse[[#This Row],[Drug Name]],tDrugUse[[Date]],"<="&tDrugUse[[#This Row],[Date]]) | Q10: =IF(AND(tDrugUse[[#This Row],[Date]]="",tDrugUse[[#This Row],[Drug Name]]="",tDrugUse[[#This Row],[Pen ID]]="",tDrugUse[[#This Row],[Batch ID]]="",tDrugUse[[#This Row],[Quantity Used]]=""),"",IF(tDrugUse[[#This Row],[Date]]="","Missing date",IF(NOT(ISNUMBER(tDrugUse[[#This Row],[Date]])),"Date is not a valid date",IF(tDrugUse[[#This Row],[Drug Name]]="","Missing drug name",IF(COUNTIF(tDrugs[[Drug Name]],tDrugUse[[#This Row],[Drug Name]])=0,"Drug not in LISTS",IF(tDrugUse[[#This Row],[Pen ID]]="","Missing Pen ID",IF(COUNTIF(tPens[[Pen ID]],tDrugUse[[#This Row],[Pen ID]])=0,"Pen "&tDrugUse[[#This Row],[Pen ID]]&" is not in PEN_REGISTER",IF(tDrugUse[[#This Row],[Batch ID]]="","Missing Batch ID",IF(COUNTIF(tBatches[[Batch ID]],tDrugUse[[#This Row],[Batch ID]])=0,"Batch "&tDrugUse[[#This Row],[Batch ID]]&" is not in BATCH_REGISTER",IF(COUNTIFS(tBatches[[Batch ID]],tDrugUse[[#This Row],[Batch ID]],tBatches[[Pen ID]],tDrugUse[[#This Row],[Pen ID]])=0,"Batch "&tDrugUse[[#This Row],[Batch ID]]&" belongs to pen "&INDEX(tBatches[[Pen ID]],MATCH(tDrugUse[[#This Row],[Batch ID]],tBatches[[Batch ID]],0)),IF(tDrugUse[[#This Row],[Date]]<INDEX(tBatches[[Batch Start Date]],MATCH(tDrugUse[[#This Row],[Batch ID]],tBatches[[Batch ID]],0)),"Date is before the batch start date",IF(AND(N(INDEX(tBatches[[Closing Date]],MATCH(tDrugUse[[#This Row],[Batch ID]],tBatches[[Batch ID]],0)))>0,tDrugUse[[#This Row],[Date]]>INDEX(tBatches[[Closing Date]],MATCH(tDrugUse[[#This Row],[Batch ID]],tBatches[[Batch ID]],0))),"Date is after the batch closing date",IF(N(tDrugUse[[#This Row],[Quantity Used]])<=0,"Quantity must be greater than 0",IF(tDrugUse[[#This Row],[Cost per Unit]]=0,"No purchase of this drug on/before this date",IF(tDrugUse[[#This Row],[Store Balance on Date]]<-0.0001,"EXCEEDS STOCK by "&TEXT(-tDrugUse[[#This Row],[Store Balance on Date]],"#,##0.0")&" "&tDrugUse[[#This Row],[Unit]],IF(AND(tDrugUse[[#This Row],[Drug Batch Number]]<>"",COUNTIFS(tDrugPur[[Drug Name]],tDrugUse[[#This Row],[Drug Name]],tDrugPur[[Batch Number]],tDrugUse[[#This Row],[Drug Batch Number]])=0),"Drug batch number not found in purchases",IF(AND(tDrugUse[[#This Row],[Drug Batch Number]]<>"",N(_xlfn.MAXIFS(tDrugPur[[Expiry Date]],tDrugPur[[Drug Name]],tDrugUse[[#This Row],[Drug Name]],tDrugPur[[Batch Number]],tDrugUse[[#This Row],[Drug Batch Number]]))>0,tDrugUse[[#This Row],[Date]]>_xlfn.MAXIFS(tDrugPur[[Expiry Date]],tDrugPur[[Drug Name]],tDrugUse[[#This Row],[Drug Name]],tDrugPur[[Batch Number]],tDrugUse[[#This Row],[Drug Batch Number]])),"Lot was expired on "&TEXT(_xlfn.MAXIFS(tDrugPur[[Expiry Date]],tDrugPur[[Drug Name]],tDrugUse[[#This Row],[Drug Name]],tDrugPur[[Batch Number]],tDrugUse[[#This Row],[Drug Batch Number]]),"dd/mm/yyyy"),"OK")))))))))))))))))
A11: 46273 | B11: ="DU-"&TEXT(ROW()-ROW(tDrugUse[[#Headers],[Date]]),"00000") | C11: ND Vaccine (Lasota) | D11: P002 | E11: BROILER-SEP-002 | F11: Vaccination | G11: 1 dose per bird | H11: 600 | I11: =IFERROR(INDEX(tDrugs[[Stock Unit]],MATCH(tDrugUse[[#This Row],[Drug Name]],tDrugs[[Drug Name]],0))&"","") | J11: =IFERROR(LOOKUP(2,1/((tDrugPur[[Drug Name]]=tDrugUse[[#This Row],[Drug Name]])*(tDrugPur[[Date]]<=tDrugUse[[#This Row],[Date]])),tDrugPur[[Avg Cost per Unit After Purchase]]),0) | K11: =N(tDrugUse[[#This Row],[Quantity Used]])*tDrugUse[[#This Row],[Cost per Unit]] | L11: ND1001 | M11: Farm Manager | N11: SAMPLE DATA - delete or replace | O11: =IFERROR(INDEX(tBatches[[Animal Type]],MATCH(tDrugUse[[#This Row],[Batch ID]],tBatches[[Batch ID]],0)),"") | P11: =SUMIFS(tDrugPur[[Quantity Purchased]],tDrugPur[[Drug Name]],tDrugUse[[#This Row],[Drug Name]],tDrugPur[[Date]],"<="&tDrugUse[[#This Row],[Date]])-SUMIFS(tDrugUse[[Quantity Used]],tDrugUse[[Drug Name]],tDrugUse[[#This Row],[Drug Name]],tDrugUse[[Date]],"<="&tDrugUse[[#This Row],[Date]]) | Q11: =IF(AND(tDrugUse[[#This Row],[Date]]="",tDrugUse[[#This Row],[Drug Name]]="",tDrugUse[[#This Row],[Pen ID]]="",tDrugUse[[#This Row],[Batch ID]]="",tDrugUse[[#This Row],[Quantity Used]]=""),"",IF(tDrugUse[[#This Row],[Date]]="","Missing date",IF(NOT(ISNUMBER(tDrugUse[[#This Row],[Date]])),"Date is not a valid date",IF(tDrugUse[[#This Row],[Drug Name]]="","Missing drug name",IF(COUNTIF(tDrugs[[Drug Name]],tDrugUse[[#This Row],[Drug Name]])=0,"Drug not in LISTS",IF(tDrugUse[[#This Row],[Pen ID]]="","Missing Pen ID",IF(COUNTIF(tPens[[Pen ID]],tDrugUse[[#This Row],[Pen ID]])=0,"Pen "&tDrugUse[[#This Row],[Pen ID]]&" is not in PEN_REGISTER",IF(tDrugUse[[#This Row],[Batch ID]]="","Missing Batch ID",IF(COUNTIF(tBatches[[Batch ID]],tDrugUse[[#This Row],[Batch ID]])=0,"Batch "&tDrugUse[[#This Row],[Batch ID]]&" is not in BATCH_REGISTER",IF(COUNTIFS(tBatches[[Batch ID]],tDrugUse[[#This Row],[Batch ID]],tBatches[[Pen ID]],tDrugUse[[#This Row],[Pen ID]])=0,"Batch "&tDrugUse[[#This Row],[Batch ID]]&" belongs to pen "&INDEX(tBatches[[Pen ID]],MATCH(tDrugUse[[#This Row],[Batch ID]],tBatches[[Batch ID]],0)),IF(tDrugUse[[#This Row],[Date]]<INDEX(tBatches[[Batch Start Date]],MATCH(tDrugUse[[#This Row],[Batch ID]],tBatches[[Batch ID]],0)),"Date is before the batch start date",IF(AND(N(INDEX(tBatches[[Closing Date]],MATCH(tDrugUse[[#This Row],[Batch ID]],tBatches[[Batch ID]],0)))>0,tDrugUse[[#This Row],[Date]]>INDEX(tBatches[[Closing Date]],MATCH(tDrugUse[[#This Row],[Batch ID]],tBatches[[Batch ID]],0))),"Date is after the batch closing date",IF(N(tDrugUse[[#This Row],[Quantity Used]])<=0,"Quantity must be greater than 0",IF(tDrugUse[[#This Row],[Cost per Unit]]=0,"No purchase of this drug on/before this date",IF(tDrugUse[[#This Row],[Store Balance on Date]]<-0.0001,"EXCEEDS STOCK by "&TEXT(-tDrugUse[[#This Row],[Store Balance on Date]],"#,##0.0")&" "&tDrugUse[[#This Row],[Unit]],IF(AND(tDrugUse[[#This Row],[Drug Batch Number]]<>"",COUNTIFS(tDrugPur[[Drug Name]],tDrugUse[[#This Row],[Drug Name]],tDrugPur[[Batch Number]],tDrugUse[[#This Row],[Drug Batch Number]])=0),"Drug batch number not found in purchases",IF(AND(tDrugUse[[#This Row],[Drug Batch Number]]<>"",N(_xlfn.MAXIFS(tDrugPur[[Expiry Date]],tDrugPur[[Drug Name]],tDrugUse[[#This Row],[Drug Name]],tDrugPur[[Batch Number]],tDrugUse[[#This Row],[Drug Batch Number]]))>0,tDrugUse[[#This Row],[Date]]>_xlfn.MAXIFS(tDrugPur[[Expiry Date]],tDrugPur[[Drug Name]],tDrugUse[[#This Row],[Drug Name]],tDrugPur[[Batch Number]],tDrugUse[[#This Row],[Drug Batch Number]])),"Lot was expired on "&TEXT(_xlfn.MAXIFS(tDrugPur[[Expiry Date]],tDrugPur[[Drug Name]],tDrugUse[[#This Row],[Drug Name]],tDrugPur[[Batch Number]],tDrugUse[[#This Row],[Drug Batch Number]]),"dd/mm/yyyy"),"OK")))))))))))))))))
A12: 46273 | B12: ="DU-"&TEXT(ROW()-ROW(tDrugUse[[#Headers],[Date]]),"00000") | C12: ND Vaccine (Lasota) | D12: P003 | E12: BROILER-SEP-003 | F12: Vaccination | G12: 1 dose per bird | H12: 450 | I12: =IFERROR(INDEX(tDrugs[[Stock Unit]],MATCH(tDrugUse[[#This Row],[Drug Name]],tDrugs[[Drug Name]],0))&"","") | J12: =IFERROR(LOOKUP(2,1/((tDrugPur[[Drug Name]]=tDrugUse[[#This Row],[Drug Name]])*(tDrugPur[[Date]]<=tDrugUse[[#This Row],[Date]])),tDrugPur[[Avg Cost per Unit After Purchase]]),0) | K12: =N(tDrugUse[[#This Row],[Quantity Used]])*tDrugUse[[#This Row],[Cost per Unit]] | L12: ND1001 | M12: Farm Manager | N12: SAMPLE DATA - delete or replace | O12: =IFERROR(INDEX(tBatches[[Animal Type]],MATCH(tDrugUse[[#This Row],[Batch ID]],tBatches[[Batch ID]],0)),"") | P12: =SUMIFS(tDrugPur[[Quantity Purchased]],tDrugPur[[Drug Name]],tDrugUse[[#This Row],[Drug Name]],tDrugPur[[Date]],"<="&tDrugUse[[#This Row],[Date]])-SUMIFS(tDrugUse[[Quantity Used]],tDrugUse[[Drug Name]],tDrugUse[[#This Row],[Drug Name]],tDrugUse[[Date]],"<="&tDrugUse[[#This Row],[Date]]) | Q12: =IF(AND(tDrugUse[[#This Row],[Date]]="",tDrugUse[[#This Row],[Drug Name]]="",tDrugUse[[#This Row],[Pen ID]]="",tDrugUse[[#This Row],[Batch ID]]="",tDrugUse[[#This Row],[Quantity Used]]=""),"",IF(tDrugUse[[#This Row],[Date]]="","Missing date",IF(NOT(ISNUMBER(tDrugUse[[#This Row],[Date]])),"Date is not a valid date",IF(tDrugUse[[#This Row],[Drug Name]]="","Missing drug name",IF(COUNTIF(tDrugs[[Drug Name]],tDrugUse[[#This Row],[Drug Name]])=0,"Drug not in LISTS",IF(tDrugUse[[#This Row],[Pen ID]]="","Missing Pen ID",IF(COUNTIF(tPens[[Pen ID]],tDrugUse[[#This Row],[Pen ID]])=0,"Pen "&tDrugUse[[#This Row],[Pen ID]]&" is not in PEN_REGISTER",IF(tDrugUse[[#This Row],[Batch ID]]="","Missing Batch ID",IF(COUNTIF(tBatches[[Batch ID]],tDrugUse[[#This Row],[Batch ID]])=0,"Batch "&tDrugUse[[#This Row],[Batch ID]]&" is not in BATCH_REGISTER",IF(COUNTIFS(tBatches[[Batch ID]],tDrugUse[[#This Row],[Batch ID]],tBatches[[Pen ID]],tDrugUse[[#This Row],[Pen ID]])=0,"Batch "&tDrugUse[[#This Row],[Batch ID]]&" belongs to pen "&INDEX(tBatches[[Pen ID]],MATCH(tDrugUse[[#This Row],[Batch ID]],tBatches[[Batch ID]],0)),IF(tDrugUse[[#This Row],[Date]]<INDEX(tBatches[[Batch Start Date]],MATCH(tDrugUse[[#This Row],[Batch ID]],tBatches[[Batch ID]],0)),"Date is before the batch start date",IF(AND(N(INDEX(tBatches[[Closing Date]],MATCH(tDrugUse[[#This Row],[Batch ID]],tBatches[[Batch ID]],0)))>0,tDrugUse[[#This Row],[Date]]>INDEX(tBatches[[Closing Date]],MATCH(tDrugUse[[#This Row],[Batch ID]],tBatches[[Batch ID]],0))),"Date is after the batch closing date",IF(N(tDrugUse[[#This Row],[Quantity Used]])<=0,"Quantity must be greater than 0",IF(tDrugUse[[#This Row],[Cost per Unit]]=0,"No purchase of this drug on/before this date",IF(tDrugUse[[#This Row],[Store Balance on Date]]<-0.0001,"EXCEEDS STOCK by "&TEXT(-tDrugUse[[#This Row],[Store Balance on Date]],"#,##0.0")&" "&tDrugUse[[#This Row],[Unit]],IF(AND(tDrugUse[[#This Row],[Drug Batch Number]]<>"",COUNTIFS(tDrugPur[[Drug Name]],tDrugUse[[#This Row],[Drug Name]],tDrugPur[[Batch Number]],tDrugUse[[#This Row],[Drug Batch Number]])=0),"Drug batch number not found in purchases",IF(AND(tDrugUse[[#This Row],[Drug Batch Number]]<>"",N(_xlfn.MAXIFS(tDrugPur[[Expiry Date]],tDrugPur[[Drug Name]],tDrugUse[[#This Row],[Drug Name]],tDrugPur[[Batch Number]],tDrugUse[[#This Row],[Drug Batch Number]]))>0,tDrugUse[[#This Row],[Date]]>_xlfn.MAXIFS(tDrugPur[[Expiry Date]],tDrugPur[[Drug Name]],tDrugUse[[#This Row],[Drug Name]],tDrugPur[[Batch Number]],tDrugUse[[#This Row],[Drug Batch Number]])),"Lot was expired on "&TEXT(_xlfn.MAXIFS(tDrugPur[[Expiry Date]],tDrugPur[[Drug Name]],tDrugUse[[#This Row],[Drug Name]],tDrugPur[[Batch Number]],tDrugUse[[#This Row],[Drug Batch Number]]),"dd/mm/yyyy"),"OK")))))))))))))))))
A13: 46273 | B13: ="DU-"&TEXT(ROW()-ROW(tDrugUse[[#Headers],[Date]]),"00000") | C13: ND Vaccine (Lasota) | D13: P004 | E13: BROILER-SEP-004 | F13: Vaccination | G13: 1 dose per bird | H13: 550 | I13: =IFERROR(INDEX(tDrugs[[Stock Unit]],MATCH(tDrugUse[[#This Row],[Drug Name]],tDrugs[[Drug Name]],0))&"","") | J13: =IFERROR(LOOKUP(2,1/((tDrugPur[[Drug Name]]=tDrugUse[[#This Row],[Drug Name]])*(tDrugPur[[Date]]<=tDrugUse[[#This Row],[Date]])),tDrugPur[[Avg Cost per Unit After Purchase]]),0) | K13: =N(tDrugUse[[#This Row],[Quantity Used]])*tDrugUse[[#This Row],[Cost per Unit]] | L13: ND1001 | M13: Farm Manager | N13: SAMPLE DATA - delete or replace | O13: =IFERROR(INDEX(tBatches[[Animal Type]],MATCH(tDrugUse[[#This Row],[Batch ID]],tBatches[[Batch ID]],0)),"") | P13: =SUMIFS(tDrugPur[[Quantity Purchased]],tDrugPur[[Drug Name]],tDrugUse[[#This Row],[Drug Name]],tDrugPur[[Date]],"<="&tDrugUse[[#This Row],[Date]])-SUMIFS(tDrugUse[[Quantity Used]],tDrugUse[[Drug Name]],tDrugUse[[#This Row],[Drug Name]],tDrugUse[[Date]],"<="&tDrugUse[[#This Row],[Date]]) | Q13: =IF(AND(tDrugUse[[#This Row],[Date]]="",tDrugUse[[#This Row],[Drug Name]]="",tDrugUse[[#This Row],[Pen ID]]="",tDrugUse[[#This Row],[Batch ID]]="",tDrugUse[[#This Row],[Quantity Used]]=""),"",IF(tDrugUse[[#This Row],[Date]]="","Missing date",IF(NOT(ISNUMBER(tDrugUse[[#This Row],[Date]])),"Date is not a valid date",IF(tDrugUse[[#This Row],[Drug Name]]="","Missing drug name",IF(COUNTIF(tDrugs[[Drug Name]],tDrugUse[[#This Row],[Drug Name]])=0,"Drug not in LISTS",IF(tDrugUse[[#This Row],[Pen ID]]="","Missing Pen ID",IF(COUNTIF(tPens[[Pen ID]],tDrugUse[[#This Row],[Pen ID]])=0,"Pen "&tDrugUse[[#This Row],[Pen ID]]&" is not in PEN_REGISTER",IF(tDrugUse[[#This Row],[Batch ID]]="","Missing Batch ID",IF(COUNTIF(tBatches[[Batch ID]],tDrugUse[[#This Row],[Batch ID]])=0,"Batch "&tDrugUse[[#This Row],[Batch ID]]&" is not in BATCH_REGISTER",IF(COUNTIFS(tBatches[[Batch ID]],tDrugUse[[#This Row],[Batch ID]],tBatches[[Pen ID]],tDrugUse[[#This Row],[Pen ID]])=0,"Batch "&tDrugUse[[#This Row],[Batch ID]]&" belongs to pen "&INDEX(tBatches[[Pen ID]],MATCH(tDrugUse[[#This Row],[Batch ID]],tBatches[[Batch ID]],0)),IF(tDrugUse[[#This Row],[Date]]<INDEX(tBatches[[Batch Start Date]],MATCH(tDrugUse[[#This Row],[Batch ID]],tBatches[[Batch ID]],0)),"Date is before the batch start date",IF(AND(N(INDEX(tBatches[[Closing Date]],MATCH(tDrugUse[[#This Row],[Batch ID]],tBatches[[Batch ID]],0)))>0,tDrugUse[[#This Row],[Date]]>INDEX(tBatches[[Closing Date]],MATCH(tDrugUse[[#This Row],[Batch ID]],tBatches[[Batch ID]],0))),"Date is after the batch closing date",IF(N(tDrugUse[[#This Row],[Quantity Used]])<=0,"Quantity must be greater than 0",IF(tDrugUse[[#This Row],[Cost per Unit]]=0,"No purchase of this drug on/before this date",IF(tDrugUse[[#This Row],[Store Balance on Date]]<-0.0001,"EXCEEDS STOCK by "&TEXT(-tDrugUse[[#This Row],[Store Balance on Date]],"#,##0.0")&" "&tDrugUse[[#This Row],[Unit]],IF(AND(tDrugUse[[#This Row],[Drug Batch Number]]<>"",COUNTIFS(tDrugPur[[Drug Name]],tDrugUse[[#This Row],[Drug Name]],tDrugPur[[Batch Number]],tDrugUse[[#This Row],[Drug Batch Number]])=0),"Drug batch number not found in purchases",IF(AND(tDrugUse[[#This Row],[Drug Batch Number]]<>"",N(_xlfn.MAXIFS(tDrugPur[[Expiry Date]],tDrugPur[[Drug Name]],tDrugUse[[#This Row],[Drug Name]],tDrugPur[[Batch Number]],tDrugUse[[#This Row],[Drug Batch Number]]))>0,tDrugUse[[#This Row],[Date]]>_xlfn.MAXIFS(tDrugPur[[Expiry Date]],tDrugPur[[Drug Name]],tDrugUse[[#This Row],[Drug Name]],tDrugPur[[Batch Number]],tDrugUse[[#This Row],[Drug Batch Number]])),"Lot was expired on "&TEXT(_xlfn.MAXIFS(tDrugPur[[Expiry Date]],tDrugPur[[Drug Name]],tDrugUse[[#This Row],[Drug Name]],tDrugPur[[Batch Number]],tDrugUse[[#This Row],[Drug Batch Number]]),"dd/mm/yyyy"),"OK")))))))))))))))))
A14: 46277 | B14: ="DU-"&TEXT(ROW()-ROW(tDrugUse[[#Headers],[Date]]),"00000") | C14: Antibiotic A | D14: P002 | E14: BROILER-SEP-002 | F14: Treatment | G14: 1 g per 2 litres, 5 days | H14: 40 | I14: =IFERROR(INDEX(tDrugs[[Stock Unit]],MATCH(tDrugUse[[#This Row],[Drug Name]],tDrugs[[Drug Name]],0))&"","") | J14: =IFERROR(LOOKUP(2,1/((tDrugPur[[Drug Name]]=tDrugUse[[#This Row],[Drug Name]])*(tDrugPur[[Date]]<=tDrugUse[[#This Row],[Date]])),tDrugPur[[Avg Cost per Unit After Purchase]]),0) | K14: =N(tDrugUse[[#This Row],[Quantity Used]])*tDrugUse[[#This Row],[Cost per Unit]] | L14: AB0826 | M14: Farm Manager | N14: SAMPLE DATA - delete or replace | O14: =IFERROR(INDEX(tBatches[[Animal Type]],MATCH(tDrugUse[[#This Row],[Batch ID]],tBatches[[Batch ID]],0)),"") | P14: =SUMIFS(tDrugPur[[Quantity Purchased]],tDrugPur[[Drug Name]],tDrugUse[[#This Row],[Drug Name]],tDrugPur[[Date]],"<="&tDrugUse[[#This Row],[Date]])-SUMIFS(tDrugUse[[Quantity Used]],tDrugUse[[Drug Name]],tDrugUse[[#This Row],[Drug Name]],tDrugUse[[Date]],"<="&tDrugUse[[#This Row],[Date]]) | Q14: =IF(AND(tDrugUse[[#This Row],[Date]]="",tDrugUse[[#This Row],[Drug Name]]="",tDrugUse[[#This Row],[Pen ID]]="",tDrugUse[[#This Row],[Batch ID]]="",tDrugUse[[#This Row],[Quantity Used]]=""),"",IF(tDrugUse[[#This Row],[Date]]="","Missing date",IF(NOT(ISNUMBER(tDrugUse[[#This Row],[Date]])),"Date is not a valid date",IF(tDrugUse[[#This Row],[Drug Name]]="","Missing drug name",IF(COUNTIF(tDrugs[[Drug Name]],tDrugUse[[#This Row],[Drug Name]])=0,"Drug not in LISTS",IF(tDrugUse[[#This Row],[Pen ID]]="","Missing Pen ID",IF(COUNTIF(tPens[[Pen ID]],tDrugUse[[#This Row],[Pen ID]])=0,"Pen "&tDrugUse[[#This Row],[Pen ID]]&" is not in PEN_REGISTER",IF(tDrugUse[[#This Row],[Batch ID]]="","Missing Batch ID",IF(COUNTIF(tBatches[[Batch ID]],tDrugUse[[#This Row],[Batch ID]])=0,"Batch "&tDrugUse[[#This Row],[Batch ID]]&" is not in BATCH_REGISTER",IF(COUNTIFS(tBatches[[Batch ID]],tDrugUse[[#This Row],[Batch ID]],tBatches[[Pen ID]],tDrugUse[[#This Row],[Pen ID]])=0,"Batch "&tDrugUse[[#This Row],[Batch ID]]&" belongs to pen "&INDEX(tBatches[[Pen ID]],MATCH(tDrugUse[[#This Row],[Batch ID]],tBatches[[Batch ID]],0)),IF(tDrugUse[[#This Row],[Date]]<INDEX(tBatches[[Batch Start Date]],MATCH(tDrugUse[[#This Row],[Batch ID]],tBatches[[Batch ID]],0)),"Date is before the batch start date",IF(AND(N(INDEX(tBatches[[Closing Date]],MATCH(tDrugUse[[#This Row],[Batch ID]],tBatches[[Batch ID]],0)))>0,tDrugUse[[#This Row],[Date]]>INDEX(tBatches[[Closing Date]],MATCH(tDrugUse[[#This Row],[Batch ID]],tBatches[[Batch ID]],0))),"Date is after the batch closing date",IF(N(tDrugUse[[#This Row],[Quantity Used]])<=0,"Quantity must be greater than 0",IF(tDrugUse[[#This Row],[Cost per Unit]]=0,"No purchase of this drug on/before this date",IF(tDrugUse[[#This Row],[Store Balance on Date]]<-0.0001,"EXCEEDS STOCK by "&TEXT(-tDrugUse[[#This Row],[Store Balance on Date]],"#,##0.0")&" "&tDrugUse[[#This Row],[Unit]],IF(AND(tDrugUse[[#This Row],[Drug Batch Number]]<>"",COUNTIFS(tDrugPur[[Drug Name]],tDrugUse[[#This Row],[Drug Name]],tDrugPur[[Batch Number]],tDrugUse[[#This Row],[Drug Batch Number]])=0),"Drug batch number not found in purchases",IF(AND(tDrugUse[[#This Row],[Drug Batch Number]]<>"",N(_xlfn.MAXIFS(tDrugPur[[Expiry Date]],tDrugPur[[Drug Name]],tDrugUse[[#This Row],[Drug Name]],tDrugPur[[Batch Number]],tDrugUse[[#This Row],[Drug Batch Number]]))>0,tDrugUse[[#This Row],[Date]]>_xlfn.MAXIFS(tDrugPur[[Expiry Date]],tDrugPur[[Drug Name]],tDrugUse[[#This Row],[Drug Name]],tDrugPur[[Batch Number]],tDrugUse[[#This Row],[Drug Batch Number]])),"Lot was expired on "&TEXT(_xlfn.MAXIFS(tDrugPur[[Expiry Date]],tDrugPur[[Drug Name]],tDrugUse[[#This Row],[Drug Name]],tDrugPur[[Batch Number]],tDrugUse[[#This Row],[Drug Batch Number]]),"dd/mm/yyyy"),"OK")))))))))))))))))

Sheet MORTALITY_LOG
A1: MORTALITY LOG
A2: Only record days on which animals died. No entry = no deaths. Current stock updates automatically.
A3: ■ GREEN header = you enter / select ■ GREY header = automatic (do not type) Add a new record by typing in the first empty row directly under the table.
A4: Date | B4: Mortality ID | C4: Pen ID | D4: Batch ID | E4: Number of Deaths | F4: Suspected/Recorded Cause | G4: Age/Day of Batch | H4: Notes | I4: Animal Type | J4: Check
A5: 46207 | B5: ="MO-"&TEXT(ROW()-ROW(tMort[[#Headers],[Date]]),"00000") | C5: P006 | D5: BROILER-JUL-001 | E5: 4 | F5: Unknown | G5: =IFERROR(tMort[[#This Row],[Date]]-INDEX(tBatches[[Batch Start Date]],MATCH(tMort[[#This Row],[Batch ID]],tBatches[[Batch ID]],0))+1,"") | H5: SAMPLE DATA - delete or replace | I5: =IFERROR(INDEX(tBatches[[Animal Type]],MATCH(tMort[[#This Row],[Batch ID]],tBatches[[Batch ID]],0)),"") | J5: =IF(AND(tMort[[#This Row],[Date]]="",tMort[[#This Row],[Pen ID]]="",tMort[[#This Row],[Batch ID]]="",tMort[[#This Row],[Number of Deaths]]=""),"",IF(tMort[[#This Row],[Date]]="","Missing date",IF(NOT(ISNUMBER(tMort[[#This Row],[Date]])),"Date is not a valid date",IF(tMort[[#This Row],[Pen ID]]="","Missing Pen ID",IF(COUNTIF(tPens[[Pen ID]],tMort[[#This Row],[Pen ID]])=0,"Pen "&tMort[[#This Row],[Pen ID]]&" is not in PEN_REGISTER",IF(tMort[[#This Row],[Batch ID]]="","Missing Batch ID",IF(COUNTIF(tBatches[[Batch ID]],tMort[[#This Row],[Batch ID]])=0,"Batch "&tMort[[#This Row],[Batch ID]]&" is not in BATCH_REGISTER",IF(COUNTIFS(tBatches[[Batch ID]],tMort[[#This Row],[Batch ID]],tBatches[[Pen ID]],tMort[[#This Row],[Pen ID]])=0,"Batch "&tMort[[#This Row],[Batch ID]]&" belongs to pen "&INDEX(tBatches[[Pen ID]],MATCH(tMort[[#This Row],[Batch ID]],tBatches[[Batch ID]],0)),IF(tMort[[#This Row],[Date]]<INDEX(tBatches[[Batch Start Date]],MATCH(tMort[[#This Row],[Batch ID]],tBatches[[Batch ID]],0)),"Date is before the batch start date",IF(AND(N(INDEX(tBatches[[Closing Date]],MATCH(tMort[[#This Row],[Batch ID]],tBatches[[Batch ID]],0)))>0,tMort[[#This Row],[Date]]>INDEX(tBatches[[Closing Date]],MATCH(tMort[[#This Row],[Batch ID]],tBatches[[Batch ID]],0))),"Date is after the batch closing date",IF(N(tMort[[#This Row],[Number of Deaths]])<=0,"Number of deaths must be > 0",IF(INDEX(tBatches[[Current Quantity]],MATCH(tMort[[#This Row],[Batch ID]],tBatches[[Batch ID]],0))<0,"Batch stock is negative - check counts","OK"))))))))))))
A6: 46218 | B6: ="MO-"&TEXT(ROW()-ROW(tMort[[#Headers],[Date]]),"00000") | C6: P006 | D6: BROILER-JUL-001 | E6: 3 | F6: Heat stress | G6: =IFERROR(tMort[[#This Row],[Date]]-INDEX(tBatches[[Batch Start Date]],MATCH(tMort[[#This Row],[Batch ID]],tBatches[[Batch ID]],0))+1,"") | H6: SAMPLE DATA - delete or replace | I6: =IFERROR(INDEX(tBatches[[Animal Type]],MATCH(tMort[[#This Row],[Batch ID]],tBatches[[Batch ID]],0)),"") | J6: =IF(AND(tMort[[#This Row],[Date]]="",tMort[[#This Row],[Pen ID]]="",tMort[[#This Row],[Batch ID]]="",tMort[[#This Row],[Number of Deaths]]=""),"",IF(tMort[[#This Row],[Date]]="","Missing date",IF(NOT(ISNUMBER(tMort[[#This Row],[Date]])),"Date is not a valid date",IF(tMort[[#This Row],[Pen ID]]="","Missing Pen ID",IF(COUNTIF(tPens[[Pen ID]],tMort[[#This Row],[Pen ID]])=0,"Pen "&tMort[[#This Row],[Pen ID]]&" is not in PEN_REGISTER",IF(tMort[[#This Row],[Batch ID]]="","Missing Batch ID",IF(COUNTIF(tBatches[[Batch ID]],tMort[[#This Row],[Batch ID]])=0,"Batch "&tMort[[#This Row],[Batch ID]]&" is not in BATCH_REGISTER",IF(COUNTIFS(tBatches[[Batch ID]],tMort[[#This Row],[Batch ID]],tBatches[[Pen ID]],tMort[[#This Row],[Pen ID]])=0,"Batch "&tMort[[#This Row],[Batch ID]]&" belongs to pen "&INDEX(tBatches[[Pen ID]],MATCH(tMort[[#This Row],[Batch ID]],tBatches[[Batch ID]],0)),IF(tMort[[#This Row],[Date]]<INDEX(tBatches[[Batch Start Date]],MATCH(tMort[[#This Row],[Batch ID]],tBatches[[Batch ID]],0)),"Date is before the batch start date",IF(AND(N(INDEX(tBatches[[Closing Date]],MATCH(tMort[[#This Row],[Batch ID]],tBatches[[Batch ID]],0)))>0,tMort[[#This Row],[Date]]>INDEX(tBatches[[Closing Date]],MATCH(tMort[[#This Row],[Batch ID]],tBatches[[Batch ID]],0))),"Date is after the batch closing date",IF(N(tMort[[#This Row],[Number of Deaths]])<=0,"Number of deaths must be > 0",IF(INDEX(tBatches[[Current Quantity]],MATCH(tMort[[#This Row],[Batch ID]],tBatches[[Batch ID]],0))<0,"Batch stock is negative - check counts","OK"))))))))))))
A7: 46236 | B7: ="MO-"&TEXT(ROW()-ROW(tMort[[#Headers],[Date]]),"00000") | C7: P006 | D7: BROILER-JUL-001 | E7: 3 | F7: Smothering / Crushing | G7: =IFERROR(tMort[[#This Row],[Date]]-INDEX(tBatches[[Batch Start Date]],MATCH(tMort[[#This Row],[Batch ID]],tBatches[[Batch ID]],0))+1,"") | H7: SAMPLE DATA - delete or replace | I7: =IFERROR(INDEX(tBatches[[Animal Type]],MATCH(tMort[[#This Row],[Batch ID]],tBatches[[Batch ID]],0)),"") | J7: =IF(AND(tMort[[#This Row],[Date]]="",tMort[[#This Row],[Pen ID]]="",tMort[[#This Row],[Batch ID]]="",tMort[[#This Row],[Number of Deaths]]=""),"",IF(tMort[[#This Row],[Date]]="","Missing date",IF(NOT(ISNUMBER(tMort[[#This Row],[Date]])),"Date is not a valid date",IF(tMort[[#This Row],[Pen ID]]="","Missing Pen ID",IF(COUNTIF(tPens[[Pen ID]],tMort[[#This Row],[Pen ID]])=0,"Pen "&tMort[[#This Row],[Pen ID]]&" is not in PEN_REGISTER",IF(tMort[[#This Row],[Batch ID]]="","Missing Batch ID",IF(COUNTIF(tBatches[[Batch ID]],tMort[[#This Row],[Batch ID]])=0,"Batch "&tMort[[#This Row],[Batch ID]]&" is not in BATCH_REGISTER",IF(COUNTIFS(tBatches[[Batch ID]],tMort[[#This Row],[Batch ID]],tBatches[[Pen ID]],tMort[[#This Row],[Pen ID]])=0,"Batch "&tMort[[#This Row],[Batch ID]]&" belongs to pen "&INDEX(tBatches[[Pen ID]],MATCH(tMort[[#This Row],[Batch ID]],tBatches[[Batch ID]],0)),IF(tMort[[#This Row],[Date]]<INDEX(tBatches[[Batch Start Date]],MATCH(tMort[[#This Row],[Batch ID]],tBatches[[Batch ID]],0)),"Date is before the batch start date",IF(AND(N(INDEX(tBatches[[Closing Date]],MATCH(tMort[[#This Row],[Batch ID]],tBatches[[Batch ID]],0)))>0,tMort[[#This Row],[Date]]>INDEX(tBatches[[Closing Date]],MATCH(tMort[[#This Row],[Batch ID]],tBatches[[Batch ID]],0))),"Date is after the batch closing date",IF(N(tMort[[#This Row],[Number of Deaths]])<=0,"Number of deaths must be > 0",IF(INDEX(tBatches[[Current Quantity]],MATCH(tMort[[#This Row],[Batch ID]],tBatches[[Batch ID]],0))<0,"Batch stock is negative - check counts","OK"))))))))))))
A8: 46254 | B8: ="MO-"&TEXT(ROW()-ROW(tMort[[#Headers],[Date]]),"00000") | C8: P005 | D8: LAYER-JUN-001 | E8: 2 | F8: Unknown | G8: =IFERROR(tMort[[#This Row],[Date]]-INDEX(tBatches[[Batch Start Date]],MATCH(tMort[[#This Row],[Batch ID]],tBatches[[Batch ID]],0))+1,"") | H8: SAMPLE DATA - delete or replace | I8: =IFERROR(INDEX(tBatches[[Animal Type]],MATCH(tMort[[#This Row],[Batch ID]],tBatches[[Batch ID]],0)),"") | J8: =IF(AND(tMort[[#This Row],[Date]]="",tMort[[#This Row],[Pen ID]]="",tMort[[#This Row],[Batch ID]]="",tMort[[#This Row],[Number of Deaths]]=""),"",IF(tMort[[#This Row],[Date]]="","Missing date",IF(NOT(ISNUMBER(tMort[[#This Row],[Date]])),"Date is not a valid date",IF(tMort[[#This Row],[Pen ID]]="","Missing Pen ID",IF(COUNTIF(tPens[[Pen ID]],tMort[[#This Row],[Pen ID]])=0,"Pen "&tMort[[#This Row],[Pen ID]]&" is not in PEN_REGISTER",IF(tMort[[#This Row],[Batch ID]]="","Missing Batch ID",IF(COUNTIF(tBatches[[Batch ID]],tMort[[#This Row],[Batch ID]])=0,"Batch "&tMort[[#This Row],[Batch ID]]&" is not in BATCH_REGISTER",IF(COUNTIFS(tBatches[[Batch ID]],tMort[[#This Row],[Batch ID]],tBatches[[Pen ID]],tMort[[#This Row],[Pen ID]])=0,"Batch "&tMort[[#This Row],[Batch ID]]&" belongs to pen "&INDEX(tBatches[[Pen ID]],MATCH(tMort[[#This Row],[Batch ID]],tBatches[[Batch ID]],0)),IF(tMort[[#This Row],[Date]]<INDEX(tBatches[[Batch Start Date]],MATCH(tMort[[#This Row],[Batch ID]],tBatches[[Batch ID]],0)),"Date is before the batch start date",IF(AND(N(INDEX(tBatches[[Closing Date]],MATCH(tMort[[#This Row],[Batch ID]],tBatches[[Batch ID]],0)))>0,tMort[[#This Row],[Date]]>INDEX(tBatches[[Closing Date]],MATCH(tMort[[#This Row],[Batch ID]],tBatches[[Batch ID]],0))),"Date is after the batch closing date",IF(N(tMort[[#This Row],[Number of Deaths]])<=0,"Number of deaths must be > 0",IF(INDEX(tBatches[[Current Quantity]],MATCH(tMort[[#This Row],[Batch ID]],tBatches[[Batch ID]],0))<0,"Batch stock is negative - check counts","OK"))))))))))))
A9: 46268 | B9: ="MO-"&TEXT(ROW()-ROW(tMort[[#Headers],[Date]]),"00000") | C9: P001 | D9: BROILER-SEP-001 | E9: 2 | F9: Unknown | G9: =IFERROR(tMort[[#This Row],[Date]]-INDEX(tBatches[[Batch Start Date]],MATCH(tMort[[#This Row],[Batch ID]],tBatches[[Batch ID]],0))+1,"") | H9: SAMPLE DATA - delete or replace | I9: =IFERROR(INDEX(tBatches[[Animal Type]],MATCH(tMort[[#This Row],[Batch ID]],tBatches[[Batch ID]],0)),"") | J9: =IF(AND(tMort[[#This Row],[Date]]="",tMort[[#This Row],[Pen ID]]="",tMort[[#This Row],[Batch ID]]="",tMort[[#This Row],[Number of Deaths]]=""),"",IF(tMort[[#This Row],[Date]]="","Missing date",IF(NOT(ISNUMBER(tMort[[#This Row],[Date]])),"Date is not a valid date",IF(tMort[[#This Row],[Pen ID]]="","Missing Pen ID",IF(COUNTIF(tPens[[Pen ID]],tMort[[#This Row],[Pen ID]])=0,"Pen "&tMort[[#This Row],[Pen ID]]&" is not in PEN_REGISTER",IF(tMort[[#This Row],[Batch ID]]="","Missing Batch ID",IF(COUNTIF(tBatches[[Batch ID]],tMort[[#This Row],[Batch ID]])=0,"Batch "&tMort[[#This Row],[Batch ID]]&" is not in BATCH_REGISTER",IF(COUNTIFS(tBatches[[Batch ID]],tMort[[#This Row],[Batch ID]],tBatches[[Pen ID]],tMort[[#This Row],[Pen ID]])=0,"Batch "&tMort[[#This Row],[Batch ID]]&" belongs to pen "&INDEX(tBatches[[Pen ID]],MATCH(tMort[[#This Row],[Batch ID]],tBatches[[Batch ID]],0)),IF(tMort[[#This Row],[Date]]<INDEX(tBatches[[Batch Start Date]],MATCH(tMort[[#This Row],[Batch ID]],tBatches[[Batch ID]],0)),"Date is before the batch start date",IF(AND(N(INDEX(tBatches[[Closing Date]],MATCH(tMort[[#This Row],[Batch ID]],tBatches[[Batch ID]],0)))>0,tMort[[#This Row],[Date]]>INDEX(tBatches[[Closing Date]],MATCH(tMort[[#This Row],[Batch ID]],tBatches[[Batch ID]],0))),"Date is after the batch closing date",IF(N(tMort[[#This Row],[Number of Deaths]])<=0,"Number of deaths must be > 0",IF(INDEX(tBatches[[Current Quantity]],MATCH(tMort[[#This Row],[Batch ID]],tBatches[[Batch ID]],0))<0,"Batch stock is negative - check counts","OK"))))))))))))
A10: 46269 | B10: ="MO-"&TEXT(ROW()-ROW(tMort[[#Headers],[Date]]),"00000") | C10: P002 | D10: BROILER-SEP-002 | E10: 3 | F10: Cold / Chilling | G10: =IFERROR(tMort[[#This Row],[Date]]-INDEX(tBatches[[Batch Start Date]],MATCH(tMort[[#This Row],[Batch ID]],tBatches[[Batch ID]],0))+1,"") | H10: SAMPLE DATA - delete or replace | I10: =IFERROR(INDEX(tBatches[[Animal Type]],MATCH(tMort[[#This Row],[Batch ID]],tBatches[[Batch ID]],0)),"") | J10: =IF(AND(tMort[[#This Row],[Date]]="",tMort[[#This Row],[Pen ID]]="",tMort[[#This Row],[Batch ID]]="",tMort[[#This Row],[Number of Deaths]]=""),"",IF(tMort[[#This Row],[Date]]="","Missing date",IF(NOT(ISNUMBER(tMort[[#This Row],[Date]])),"Date is not a valid date",IF(tMort[[#This Row],[Pen ID]]="","Missing Pen ID",IF(COUNTIF(tPens[[Pen ID]],tMort[[#This Row],[Pen ID]])=0,"Pen "&tMort[[#This Row],[Pen ID]]&" is not in PEN_REGISTER",IF(tMort[[#This Row],[Batch ID]]="","Missing Batch ID",IF(COUNTIF(tBatches[[Batch ID]],tMort[[#This Row],[Batch ID]])=0,"Batch "&tMort[[#This Row],[Batch ID]]&" is not in BATCH_REGISTER",IF(COUNTIFS(tBatches[[Batch ID]],tMort[[#This Row],[Batch ID]],tBatches[[Pen ID]],tMort[[#This Row],[Pen ID]])=0,"Batch "&tMort[[#This Row],[Batch ID]]&" belongs to pen "&INDEX(tBatches[[Pen ID]],MATCH(tMort[[#This Row],[Batch ID]],tBatches[[Batch ID]],0)),IF(tMort[[#This Row],[Date]]<INDEX(tBatches[[Batch Start Date]],MATCH(tMort[[#This Row],[Batch ID]],tBatches[[Batch ID]],0)),"Date is before the batch start date",IF(AND(N(INDEX(tBatches[[Closing Date]],MATCH(tMort[[#This Row],[Batch ID]],tBatches[[Batch ID]],0)))>0,tMort[[#This Row],[Date]]>INDEX(tBatches[[Closing Date]],MATCH(tMort[[#This Row],[Batch ID]],tBatches[[Batch ID]],0))),"Date is after the batch closing date",IF(N(tMort[[#This Row],[Number of Deaths]])<=0,"Number of deaths must be > 0",IF(INDEX(tBatches[[Current Quantity]],MATCH(tMort[[#This Row],[Batch ID]],tBatches[[Batch ID]],0))<0,"Batch stock is negative - check counts","OK"))))))))))))
A11: 46274 | B11: ="MO-"&TEXT(ROW()-ROW(tMort[[#Headers],[Date]]),"00000") | C11: P003 | D11: BROILER-SEP-003 | E11: 1 | F11: Injury | G11: =IFERROR(tMort[[#This Row],[Date]]-INDEX(tBatches[[Batch Start Date]],MATCH(tMort[[#This Row],[Batch ID]],tBatches[[Batch ID]],0))+1,"") | H11: SAMPLE DATA - delete or replace | I11: =IFERROR(INDEX(tBatches[[Animal Type]],MATCH(tMort[[#This Row],[Batch ID]],tBatches[[Batch ID]],0)),"") | J11: =IF(AND(tMort[[#This Row],[Date]]="",tMort[[#This Row],[Pen ID]]="",tMort[[#This Row],[Batch ID]]="",tMort[[#This Row],[Number of Deaths]]=""),"",IF(tMort[[#This Row],[Date]]="","Missing date",IF(NOT(ISNUMBER(tMort[[#This Row],[Date]])),"Date is not a valid date",IF(tMort[[#This Row],[Pen ID]]="","Missing Pen ID",IF(COUNTIF(tPens[[Pen ID]],tMort[[#This Row],[Pen ID]])=0,"Pen "&tMort[[#This Row],[Pen ID]]&" is not in PEN_REGISTER",IF(tMort[[#This Row],[Batch ID]]="","Missing Batch ID",IF(COUNTIF(tBatches[[Batch ID]],tMort[[#This Row],[Batch ID]])=0,"Batch "&tMort[[#This Row],[Batch ID]]&" is not in BATCH_REGISTER",IF(COUNTIFS(tBatches[[Batch ID]],tMort[[#This Row],[Batch ID]],tBatches[[Pen ID]],tMort[[#This Row],[Pen ID]])=0,"Batch "&tMort[[#This Row],[Batch ID]]&" belongs to pen "&INDEX(tBatches[[Pen ID]],MATCH(tMort[[#This Row],[Batch ID]],tBatches[[Batch ID]],0)),IF(tMort[[#This Row],[Date]]<INDEX(tBatches[[Batch Start Date]],MATCH(tMort[[#This Row],[Batch ID]],tBatches[[Batch ID]],0)),"Date is before the batch start date",IF(AND(N(INDEX(tBatches[[Closing Date]],MATCH(tMort[[#This Row],[Batch ID]],tBatches[[Batch ID]],0)))>0,tMort[[#This Row],[Date]]>INDEX(tBatches[[Closing Date]],MATCH(tMort[[#This Row],[Batch ID]],tBatches[[Batch ID]],0))),"Date is after the batch closing date",IF(N(tMort[[#This Row],[Number of Deaths]])<=0,"Number of deaths must be > 0",IF(INDEX(tBatches[[Current Quantity]],MATCH(tMort[[#This Row],[Batch ID]],tBatches[[Batch ID]],0))<0,"Batch stock is negative - check counts","OK"))))))))))))
A12: 46279 | B12: ="MO-"&TEXT(ROW()-ROW(tMort[[#Headers],[Date]]),"00000") | C12: P002 | D12: BROILER-SEP-002 | E12: 2 | F12: Suspected disease | G12: =IFERROR(tMort[[#This Row],[Date]]-INDEX(tBatches[[Batch Start Date]],MATCH(tMort[[#This Row],[Batch ID]],tBatches[[Batch ID]],0))+1,"") | H12: SAMPLE DATA - delete or replace | I12: =IFERROR(INDEX(tBatches[[Animal Type]],MATCH(tMort[[#This Row],[Batch ID]],tBatches[[Batch ID]],0)),"") | J12: =IF(AND(tMort[[#This Row],[Date]]="",tMort[[#This Row],[Pen ID]]="",tMort[[#This Row],[Batch ID]]="",tMort[[#This Row],[Number of Deaths]]=""),"",IF(tMort[[#This Row],[Date]]="","Missing date",IF(NOT(ISNUMBER(tMort[[#This Row],[Date]])),"Date is not a valid date",IF(tMort[[#This Row],[Pen ID]]="","Missing Pen ID",IF(COUNTIF(tPens[[Pen ID]],tMort[[#This Row],[Pen ID]])=0,"Pen "&tMort[[#This Row],[Pen ID]]&" is not in PEN_REGISTER",IF(tMort[[#This Row],[Batch ID]]="","Missing Batch ID",IF(COUNTIF(tBatches[[Batch ID]],tMort[[#This Row],[Batch ID]])=0,"Batch "&tMort[[#This Row],[Batch ID]]&" is not in BATCH_REGISTER",IF(COUNTIFS(tBatches[[Batch ID]],tMort[[#This Row],[Batch ID]],tBatches[[Pen ID]],tMort[[#This Row],[Pen ID]])=0,"Batch "&tMort[[#This Row],[Batch ID]]&" belongs to pen "&INDEX(tBatches[[Pen ID]],MATCH(tMort[[#This Row],[Batch ID]],tBatches[[Batch ID]],0)),IF(tMort[[#This Row],[Date]]<INDEX(tBatches[[Batch Start Date]],MATCH(tMort[[#This Row],[Batch ID]],tBatches[[Batch ID]],0)),"Date is before the batch start date",IF(AND(N(INDEX(tBatches[[Closing Date]],MATCH(tMort[[#This Row],[Batch ID]],tBatches[[Batch ID]],0)))>0,tMort[[#This Row],[Date]]>INDEX(tBatches[[Closing Date]],MATCH(tMort[[#This Row],[Batch ID]],tBatches[[Batch ID]],0))),"Date is after the batch closing date",IF(N(tMort[[#This Row],[Number of Deaths]])<=0,"Number of deaths must be > 0",IF(INDEX(tBatches[[Current Quantity]],MATCH(tMort[[#This Row],[Batch ID]],tBatches[[Batch ID]],0))<0,"Batch stock is negative - check counts","OK"))))))))))))
A13: 46285 | B13: ="MO-"&TEXT(ROW()-ROW(tMort[[#Headers],[Date]]),"00000") | C13: P004 | D13: BROILER-SEP-004 | E13: 2 | F13: Unknown | G13: =IFERROR(tMort[[#This Row],[Date]]-INDEX(tBatches[[Batch Start Date]],MATCH(tMort[[#This Row],[Batch ID]],tBatches[[Batch ID]],0))+1,"") | H13: SAMPLE DATA - delete or replace | I13: =IFERROR(INDEX(tBatches[[Animal Type]],MATCH(tMort[[#This Row],[Batch ID]],tBatches[[Batch ID]],0)),"") | J13: =IF(AND(tMort[[#This Row],[Date]]="",tMort[[#This Row],[Pen ID]]="",tMort[[#This Row],[Batch ID]]="",tMort[[#This Row],[Number of Deaths]]=""),"",IF(tMort[[#This Row],[Date]]="","Missing date",IF(NOT(ISNUMBER(tMort[[#This Row],[Date]])),"Date is not a valid date",IF(tMort[[#This Row],[Pen ID]]="","Missing Pen ID",IF(COUNTIF(tPens[[Pen ID]],tMort[[#This Row],[Pen ID]])=0,"Pen "&tMort[[#This Row],[Pen ID]]&" is not in PEN_REGISTER",IF(tMort[[#This Row],[Batch ID]]="","Missing Batch ID",IF(COUNTIF(tBatches[[Batch ID]],tMort[[#This Row],[Batch ID]])=0,"Batch "&tMort[[#This Row],[Batch ID]]&" is not in BATCH_REGISTER",IF(COUNTIFS(tBatches[[Batch ID]],tMort[[#This Row],[Batch ID]],tBatches[[Pen ID]],tMort[[#This Row],[Pen ID]])=0,"Batch "&tMort[[#This Row],[Batch ID]]&" belongs to pen "&INDEX(tBatches[[Pen ID]],MATCH(tMort[[#This Row],[Batch ID]],tBatches[[Batch ID]],0)),IF(tMort[[#This Row],[Date]]<INDEX(tBatches[[Batch Start Date]],MATCH(tMort[[#This Row],[Batch ID]],tBatches[[Batch ID]],0)),"Date is before the batch start date",IF(AND(N(INDEX(tBatches[[Closing Date]],MATCH(tMort[[#This Row],[Batch ID]],tBatches[[Batch ID]],0)))>0,tMort[[#This Row],[Date]]>INDEX(tBatches[[Closing Date]],MATCH(tMort[[#This Row],[Batch ID]],tBatches[[Batch ID]],0))),"Date is after the batch closing date",IF(N(tMort[[#This Row],[Number of Deaths]])<=0,"Number of deaths must be > 0",IF(INDEX(tBatches[[Current Quantity]],MATCH(tMort[[#This Row],[Batch ID]],tBatches[[Batch ID]],0))<0,"Batch stock is negative - check counts","OK"))))))))))))
A14: 46292 | B14: ="MO-"&TEXT(ROW()-ROW(tMort[[#Headers],[Date]]),"00000") | C14: P001 | D14: BROILER-SEP-001 | E14: 1 | F14: Heat stress | G14: =IFERROR(tMort[[#This Row],[Date]]-INDEX(tBatches[[Batch Start Date]],MATCH(tMort[[#This Row],[Batch ID]],tBatches[[Batch ID]],0))+1,"") | H14: SAMPLE DATA - delete or replace | I14: =IFERROR(INDEX(tBatches[[Animal Type]],MATCH(tMort[[#This Row],[Batch ID]],tBatches[[Batch ID]],0)),"") | J14: =IF(AND(tMort[[#This Row],[Date]]="",tMort[[#This Row],[Pen ID]]="",tMort[[#This Row],[Batch ID]]="",tMort[[#This Row],[Number of Deaths]]=""),"",IF(tMort[[#This Row],[Date]]="","Missing date",IF(NOT(ISNUMBER(tMort[[#This Row],[Date]])),"Date is not a valid date",IF(tMort[[#This Row],[Pen ID]]="","Missing Pen ID",IF(COUNTIF(tPens[[Pen ID]],tMort[[#This Row],[Pen ID]])=0,"Pen "&tMort[[#This Row],[Pen ID]]&" is not in PEN_REGISTER",IF(tMort[[#This Row],[Batch ID]]="","Missing Batch ID",IF(COUNTIF(tBatches[[Batch ID]],tMort[[#This Row],[Batch ID]])=0,"Batch "&tMort[[#This Row],[Batch ID]]&" is not in BATCH_REGISTER",IF(COUNTIFS(tBatches[[Batch ID]],tMort[[#This Row],[Batch ID]],tBatches[[Pen ID]],tMort[[#This Row],[Pen ID]])=0,"Batch "&tMort[[#This Row],[Batch ID]]&" belongs to pen "&INDEX(tBatches[[Pen ID]],MATCH(tMort[[#This Row],[Batch ID]],tBatches[[Batch ID]],0)),IF(tMort[[#This Row],[Date]]<INDEX(tBatches[[Batch Start Date]],MATCH(tMort[[#This Row],[Batch ID]],tBatches[[Batch ID]],0)),"Date is before the batch start date",IF(AND(N(INDEX(tBatches[[Closing Date]],MATCH(tMort[[#This Row],[Batch ID]],tBatches[[Batch ID]],0)))>0,tMort[[#This Row],[Date]]>INDEX(tBatches[[Closing Date]],MATCH(tMort[[#This Row],[Batch ID]],tBatches[[Batch ID]],0))),"Date is after the batch closing date",IF(N(tMort[[#This Row],[Number of Deaths]])<=0,"Number of deaths must be > 0",IF(INDEX(tBatches[[Current Quantity]],MATCH(tMort[[#This Row],[Batch ID]],tBatches[[Batch ID]],0))<0,"Batch stock is negative - check counts","OK"))))))))))))

Sheet PRODUCTION_LOG
A1: PRODUCTION LOG
A2: Weighings and output (eggs etc.) - only when they happen. No daily row needed.
A3: ■ GREEN header = you enter / select ■ GREY header = automatic (do not type) Add a new record by typing in the first empty row directly under the table.
A4: Date | B4: Record ID | C4: Pen ID | D4: Batch ID | E4: Measurement Type | F4: Quantity | G4: Unit | H4: Average Weight kg | I4: Number Sampled | J4: Notes | K4: Animal Type | L4: Age/Day of Batch | M4: Check
A5: 46249 | B5: ="PR-"&TEXT(ROW()-ROW(tProd[[#Headers],[Date]]),"00000") | C5: P006 | D5: BROILER-JUL-001 | E5: Weighing | G5: kg | H5: 2.35 | I5: 20 | J5: SAMPLE DATA - delete or replace | K5: =IFERROR(INDEX(tBatches[[Animal Type]],MATCH(tProd[[#This Row],[Batch ID]],tBatches[[Batch ID]],0)),"") | L5: =IFERROR(tProd[[#This Row],[Date]]-INDEX(tBatches[[Batch Start Date]],MATCH(tProd[[#This Row],[Batch ID]],tBatches[[Batch ID]],0))+1,"") | M5: =IF(AND(tProd[[#This Row],[Date]]="",tProd[[#This Row],[Pen ID]]="",tProd[[#This Row],[Batch ID]]="",tProd[[#This Row],[Measurement Type]]=""),"",IF(tProd[[#This Row],[Date]]="","Missing date",IF(NOT(ISNUMBER(tProd[[#This Row],[Date]])),"Date is not a valid date",IF(tProd[[#This Row],[Pen ID]]="","Missing Pen ID",IF(COUNTIF(tPens[[Pen ID]],tProd[[#This Row],[Pen ID]])=0,"Pen "&tProd[[#This Row],[Pen ID]]&" is not in PEN_REGISTER",IF(tProd[[#This Row],[Batch ID]]="","Missing Batch ID",IF(COUNTIF(tBatches[[Batch ID]],tProd[[#This Row],[Batch ID]])=0,"Batch "&tProd[[#This Row],[Batch ID]]&" is not in BATCH_REGISTER",IF(COUNTIFS(tBatches[[Batch ID]],tProd[[#This Row],[Batch ID]],tBatches[[Pen ID]],tProd[[#This Row],[Pen ID]])=0,"Batch "&tProd[[#This Row],[Batch ID]]&" belongs to pen "&INDEX(tBatches[[Pen ID]],MATCH(tProd[[#This Row],[Batch ID]],tBatches[[Batch ID]],0)),IF(tProd[[#This Row],[Date]]<INDEX(tBatches[[Batch Start Date]],MATCH(tProd[[#This Row],[Batch ID]],tBatches[[Batch ID]],0)),"Date is before the batch start date",IF(AND(N(INDEX(tBatches[[Closing Date]],MATCH(tProd[[#This Row],[Batch ID]],tBatches[[Batch ID]],0)))>0,tProd[[#This Row],[Date]]>INDEX(tBatches[[Closing Date]],MATCH(tProd[[#This Row],[Batch ID]],tBatches[[Batch ID]],0))),"Date is after the batch closing date",IF(tProd[[#This Row],[Measurement Type]]="","Missing measurement type",IF(AND(tProd[[#This Row],[Measurement Type]]="Weighing",N(tProd[[#This Row],[Average Weight kg]])<=0),"Weighing needs an average weight",IF(AND(tProd[[#This Row],[Measurement Type]]<>"Weighing",N(tProd[[#This Row],[Quantity]])<=0),"Output needs a quantity","OK")))))))))))))
A6: 46275 | B6: ="PR-"&TEXT(ROW()-ROW(tProd[[#Headers],[Date]]),"00000") | C6: P005 | D6: LAYER-JUN-001 | E6: Egg Collection | F6: 11 | G6: crates | J6: SAMPLE DATA - delete or replace | K6: =IFERROR(INDEX(tBatches[[Animal Type]],MATCH(tProd[[#This Row],[Batch ID]],tBatches[[Batch ID]],0)),"") | L6: =IFERROR(tProd[[#This Row],[Date]]-INDEX(tBatches[[Batch Start Date]],MATCH(tProd[[#This Row],[Batch ID]],tBatches[[Batch ID]],0))+1,"") | M6: =IF(AND(tProd[[#This Row],[Date]]="",tProd[[#This Row],[Pen ID]]="",tProd[[#This Row],[Batch ID]]="",tProd[[#This Row],[Measurement Type]]=""),"",IF(tProd[[#This Row],[Date]]="","Missing date",IF(NOT(ISNUMBER(tProd[[#This Row],[Date]])),"Date is not a valid date",IF(tProd[[#This Row],[Pen ID]]="","Missing Pen ID",IF(COUNTIF(tPens[[Pen ID]],tProd[[#This Row],[Pen ID]])=0,"Pen "&tProd[[#This Row],[Pen ID]]&" is not in PEN_REGISTER",IF(tProd[[#This Row],[Batch ID]]="","Missing Batch ID",IF(COUNTIF(tBatches[[Batch ID]],tProd[[#This Row],[Batch ID]])=0,"Batch "&tProd[[#This Row],[Batch ID]]&" is not in BATCH_REGISTER",IF(COUNTIFS(tBatches[[Batch ID]],tProd[[#This Row],[Batch ID]],tBatches[[Pen ID]],tProd[[#This Row],[Pen ID]])=0,"Batch "&tProd[[#This Row],[Batch ID]]&" belongs to pen "&INDEX(tBatches[[Pen ID]],MATCH(tProd[[#This Row],[Batch ID]],tBatches[[Batch ID]],0)),IF(tProd[[#This Row],[Date]]<INDEX(tBatches[[Batch Start Date]],MATCH(tProd[[#This Row],[Batch ID]],tBatches[[Batch ID]],0)),"Date is before the batch start date",IF(AND(N(INDEX(tBatches[[Closing Date]],MATCH(tProd[[#This Row],[Batch ID]],tBatches[[Batch ID]],0)))>0,tProd[[#This Row],[Date]]>INDEX(tBatches[[Closing Date]],MATCH(tProd[[#This Row],[Batch ID]],tBatches[[Batch ID]],0))),"Date is after the batch closing date",IF(tProd[[#This Row],[Measurement Type]]="","Missing measurement type",IF(AND(tProd[[#This Row],[Measurement Type]]="Weighing",N(tProd[[#This Row],[Average Weight kg]])<=0),"Weighing needs an average weight",IF(AND(tProd[[#This Row],[Measurement Type]]<>"Weighing",N(tProd[[#This Row],[Quantity]])<=0),"Output needs a quantity","OK")))))))))))))
A7: 46279 | B7: ="PR-"&TEXT(ROW()-ROW(tProd[[#Headers],[Date]]),"00000") | C7: P001 | D7: BROILER-SEP-001 | E7: Weighing | G7: kg | H7: 0.45 | I7: 20 | J7: SAMPLE DATA - delete or replace | K7: =IFERROR(INDEX(tBatches[[Animal Type]],MATCH(tProd[[#This Row],[Batch ID]],tBatches[[Batch ID]],0)),"") | L7: =IFERROR(tProd[[#This Row],[Date]]-INDEX(tBatches[[Batch Start Date]],MATCH(tProd[[#This Row],[Batch ID]],tBatches[[Batch ID]],0))+1,"") | M7: =IF(AND(tProd[[#This Row],[Date]]="",tProd[[#This Row],[Pen ID]]="",tProd[[#This Row],[Batch ID]]="",tProd[[#This Row],[Measurement Type]]=""),"",IF(tProd[[#This Row],[Date]]="","Missing date",IF(NOT(ISNUMBER(tProd[[#This Row],[Date]])),"Date is not a valid date",IF(tProd[[#This Row],[Pen ID]]="","Missing Pen ID",IF(COUNTIF(tPens[[Pen ID]],tProd[[#This Row],[Pen ID]])=0,"Pen "&tProd[[#This Row],[Pen ID]]&" is not in PEN_REGISTER",IF(tProd[[#This Row],[Batch ID]]="","Missing Batch ID",IF(COUNTIF(tBatches[[Batch ID]],tProd[[#This Row],[Batch ID]])=0,"Batch "&tProd[[#This Row],[Batch ID]]&" is not in BATCH_REGISTER",IF(COUNTIFS(tBatches[[Batch ID]],tProd[[#This Row],[Batch ID]],tBatches[[Pen ID]],tProd[[#This Row],[Pen ID]])=0,"Batch "&tProd[[#This Row],[Batch ID]]&" belongs to pen "&INDEX(tBatches[[Pen ID]],MATCH(tProd[[#This Row],[Batch ID]],tBatches[[Batch ID]],0)),IF(tProd[[#This Row],[Date]]<INDEX(tBatches[[Batch Start Date]],MATCH(tProd[[#This Row],[Batch ID]],tBatches[[Batch ID]],0)),"Date is before the batch start date",IF(AND(N(INDEX(tBatches[[Closing Date]],MATCH(tProd[[#This Row],[Batch ID]],tBatches[[Batch ID]],0)))>0,tProd[[#This Row],[Date]]>INDEX(tBatches[[Closing Date]],MATCH(tProd[[#This Row],[Batch ID]],tBatches[[Batch ID]],0))),"Date is after the batch closing date",IF(tProd[[#This Row],[Measurement Type]]="","Missing measurement type",IF(AND(tProd[[#This Row],[Measurement Type]]="Weighing",N(tProd[[#This Row],[Average Weight kg]])<=0),"Weighing needs an average weight",IF(AND(tProd[[#This Row],[Measurement Type]]<>"Weighing",N(tProd[[#This Row],[Quantity]])<=0),"Output needs a quantity","OK")))))))))))))
A8: 46279 | B8: ="PR-"&TEXT(ROW()-ROW(tProd[[#Headers],[Date]]),"00000") | C8: P002 | D8: BROILER-SEP-002 | E8: Weighing | G8: kg | H8: 0.43 | I8: 20 | J8: SAMPLE DATA - delete or replace | K8: =IFERROR(INDEX(tBatches[[Animal Type]],MATCH(tProd[[#This Row],[Batch ID]],tBatches[[Batch ID]],0)),"") | L8: =IFERROR(tProd[[#This Row],[Date]]-INDEX(tBatches[[Batch Start Date]],MATCH(tProd[[#This Row],[Batch ID]],tBatches[[Batch ID]],0))+1,"") | M8: =IF(AND(tProd[[#This Row],[Date]]="",tProd[[#This Row],[Pen ID]]="",tProd[[#This Row],[Batch ID]]="",tProd[[#This Row],[Measurement Type]]=""),"",IF(tProd[[#This Row],[Date]]="","Missing date",IF(NOT(ISNUMBER(tProd[[#This Row],[Date]])),"Date is not a valid date",IF(tProd[[#This Row],[Pen ID]]="","Missing Pen ID",IF(COUNTIF(tPens[[Pen ID]],tProd[[#This Row],[Pen ID]])=0,"Pen "&tProd[[#This Row],[Pen ID]]&" is not in PEN_REGISTER",IF(tProd[[#This Row],[Batch ID]]="","Missing Batch ID",IF(COUNTIF(tBatches[[Batch ID]],tProd[[#This Row],[Batch ID]])=0,"Batch "&tProd[[#This Row],[Batch ID]]&" is not in BATCH_REGISTER",IF(COUNTIFS(tBatches[[Batch ID]],tProd[[#This Row],[Batch ID]],tBatches[[Pen ID]],tProd[[#This Row],[Pen ID]])=0,"Batch "&tProd[[#This Row],[Batch ID]]&" belongs to pen "&INDEX(tBatches[[Pen ID]],MATCH(tProd[[#This Row],[Batch ID]],tBatches[[Batch ID]],0)),IF(tProd[[#This Row],[Date]]<INDEX(tBatches[[Batch Start Date]],MATCH(tProd[[#This Row],[Batch ID]],tBatches[[Batch ID]],0)),"Date is before the batch start date",IF(AND(N(INDEX(tBatches[[Closing Date]],MATCH(tProd[[#This Row],[Batch ID]],tBatches[[Batch ID]],0)))>0,tProd[[#This Row],[Date]]>INDEX(tBatches[[Closing Date]],MATCH(tProd[[#This Row],[Batch ID]],tBatches[[Batch ID]],0))),"Date is after the batch closing date",IF(tProd[[#This Row],[Measurement Type]]="","Missing measurement type",IF(AND(tProd[[#This Row],[Measurement Type]]="Weighing",N(tProd[[#This Row],[Average Weight kg]])<=0),"Weighing needs an average weight",IF(AND(tProd[[#This Row],[Measurement Type]]<>"Weighing",N(tProd[[#This Row],[Quantity]])<=0),"Output needs a quantity","OK")))))))))))))
A9: 46285 | B9: ="PR-"&TEXT(ROW()-ROW(tProd[[#Headers],[Date]]),"00000") | C9: P005 | D9: LAYER-JUN-001 | E9: Egg Collection | F9: 11 | G9: crates | J9: SAMPLE DATA - delete or replace | K9: =IFERROR(INDEX(tBatches[[Animal Type]],MATCH(tProd[[#This Row],[Batch ID]],tBatches[[Batch ID]],0)),"") | L9: =IFERROR(tProd[[#This Row],[Date]]-INDEX(tBatches[[Batch Start Date]],MATCH(tProd[[#This Row],[Batch ID]],tBatches[[Batch ID]],0))+1,"") | M9: =IF(AND(tProd[[#This Row],[Date]]="",tProd[[#This Row],[Pen ID]]="",tProd[[#This Row],[Batch ID]]="",tProd[[#This Row],[Measurement Type]]=""),"",IF(tProd[[#This Row],[Date]]="","Missing date",IF(NOT(ISNUMBER(tProd[[#This Row],[Date]])),"Date is not a valid date",IF(tProd[[#This Row],[Pen ID]]="","Missing Pen ID",IF(COUNTIF(tPens[[Pen ID]],tProd[[#This Row],[Pen ID]])=0,"Pen "&tProd[[#This Row],[Pen ID]]&" is not in PEN_REGISTER",IF(tProd[[#This Row],[Batch ID]]="","Missing Batch ID",IF(COUNTIF(tBatches[[Batch ID]],tProd[[#This Row],[Batch ID]])=0,"Batch "&tProd[[#This Row],[Batch ID]]&" is not in BATCH_REGISTER",IF(COUNTIFS(tBatches[[Batch ID]],tProd[[#This Row],[Batch ID]],tBatches[[Pen ID]],tProd[[#This Row],[Pen ID]])=0,"Batch "&tProd[[#This Row],[Batch ID]]&" belongs to pen "&INDEX(tBatches[[Pen ID]],MATCH(tProd[[#This Row],[Batch ID]],tBatches[[Batch ID]],0)),IF(tProd[[#This Row],[Date]]<INDEX(tBatches[[Batch Start Date]],MATCH(tProd[[#This Row],[Batch ID]],tBatches[[Batch ID]],0)),"Date is before the batch start date",IF(AND(N(INDEX(tBatches[[Closing Date]],MATCH(tProd[[#This Row],[Batch ID]],tBatches[[Batch ID]],0)))>0,tProd[[#This Row],[Date]]>INDEX(tBatches[[Closing Date]],MATCH(tProd[[#This Row],[Batch ID]],tBatches[[Batch ID]],0))),"Date is after the batch closing date",IF(tProd[[#This Row],[Measurement Type]]="","Missing measurement type",IF(AND(tProd[[#This Row],[Measurement Type]]="Weighing",N(tProd[[#This Row],[Average Weight kg]])<=0),"Weighing needs an average weight",IF(AND(tProd[[#This Row],[Measurement Type]]<>"Weighing",N(tProd[[#This Row],[Quantity]])<=0),"Output needs a quantity","OK")))))))))))))
A10: 46286 | B10: ="PR-"&TEXT(ROW()-ROW(tProd[[#Headers],[Date]]),"00000") | C10: P001 | D10: BROILER-SEP-001 | E10: Weighing | G10: kg | H10: 0.86 | I10: 20 | J10: SAMPLE DATA - delete or replace | K10: =IFERROR(INDEX(tBatches[[Animal Type]],MATCH(tProd[[#This Row],[Batch ID]],tBatches[[Batch ID]],0)),"") | L10: =IFERROR(tProd[[#This Row],[Date]]-INDEX(tBatches[[Batch Start Date]],MATCH(tProd[[#This Row],[Batch ID]],tBatches[[Batch ID]],0))+1,"") | M10: =IF(AND(tProd[[#This Row],[Date]]="",tProd[[#This Row],[Pen ID]]="",tProd[[#This Row],[Batch ID]]="",tProd[[#This Row],[Measurement Type]]=""),"",IF(tProd[[#This Row],[Date]]="","Missing date",IF(NOT(ISNUMBER(tProd[[#This Row],[Date]])),"Date is not a valid date",IF(tProd[[#This Row],[Pen ID]]="","Missing Pen ID",IF(COUNTIF(tPens[[Pen ID]],tProd[[#This Row],[Pen ID]])=0,"Pen "&tProd[[#This Row],[Pen ID]]&" is not in PEN_REGISTER",IF(tProd[[#This Row],[Batch ID]]="","Missing Batch ID",IF(COUNTIF(tBatches[[Batch ID]],tProd[[#This Row],[Batch ID]])=0,"Batch "&tProd[[#This Row],[Batch ID]]&" is not in BATCH_REGISTER",IF(COUNTIFS(tBatches[[Batch ID]],tProd[[#This Row],[Batch ID]],tBatches[[Pen ID]],tProd[[#This Row],[Pen ID]])=0,"Batch "&tProd[[#This Row],[Batch ID]]&" belongs to pen "&INDEX(tBatches[[Pen ID]],MATCH(tProd[[#This Row],[Batch ID]],tBatches[[Batch ID]],0)),IF(tProd[[#This Row],[Date]]<INDEX(tBatches[[Batch Start Date]],MATCH(tProd[[#This Row],[Batch ID]],tBatches[[Batch ID]],0)),"Date is before the batch start date",IF(AND(N(INDEX(tBatches[[Closing Date]],MATCH(tProd[[#This Row],[Batch ID]],tBatches[[Batch ID]],0)))>0,tProd[[#This Row],[Date]]>INDEX(tBatches[[Closing Date]],MATCH(tProd[[#This Row],[Batch ID]],tBatches[[Batch ID]],0))),"Date is after the batch closing date",IF(tProd[[#This Row],[Measurement Type]]="","Missing measurement type",IF(AND(tProd[[#This Row],[Measurement Type]]="Weighing",N(tProd[[#This Row],[Average Weight kg]])<=0),"Weighing needs an average weight",IF(AND(tProd[[#This Row],[Measurement Type]]<>"Weighing",N(tProd[[#This Row],[Quantity]])<=0),"Output needs a quantity","OK")))))))))))))
A11: 46286 | B11: ="PR-"&TEXT(ROW()-ROW(tProd[[#Headers],[Date]]),"00000") | C11: P004 | D11: BROILER-SEP-004 | E11: Weighing | G11: kg | H11: 0.8 | I11: 25 | J11: SAMPLE DATA - delete or replace | K11: =IFERROR(INDEX(tBatches[[Animal Type]],MATCH(tProd[[#This Row],[Batch ID]],tBatches[[Batch ID]],0)),"") | L11: =IFERROR(tProd[[#This Row],[Date]]-INDEX(tBatches[[Batch Start Date]],MATCH(tProd[[#This Row],[Batch ID]],tBatches[[Batch ID]],0))+1,"") | M11: =IF(AND(tProd[[#This Row],[Date]]="",tProd[[#This Row],[Pen ID]]="",tProd[[#This Row],[Batch ID]]="",tProd[[#This Row],[Measurement Type]]=""),"",IF(tProd[[#This Row],[Date]]="","Missing date",IF(NOT(ISNUMBER(tProd[[#This Row],[Date]])),"Date is not a valid date",IF(tProd[[#This Row],[Pen ID]]="","Missing Pen ID",IF(COUNTIF(tPens[[Pen ID]],tProd[[#This Row],[Pen ID]])=0,"Pen "&tProd[[#This Row],[Pen ID]]&" is not in PEN_REGISTER",IF(tProd[[#This Row],[Batch ID]]="","Missing Batch ID",IF(COUNTIF(tBatches[[Batch ID]],tProd[[#This Row],[Batch ID]])=0,"Batch "&tProd[[#This Row],[Batch ID]]&" is not in BATCH_REGISTER",IF(COUNTIFS(tBatches[[Batch ID]],tProd[[#This Row],[Batch ID]],tBatches[[Pen ID]],tProd[[#This Row],[Pen ID]])=0,"Batch "&tProd[[#This Row],[Batch ID]]&" belongs to pen "&INDEX(tBatches[[Pen ID]],MATCH(tProd[[#This Row],[Batch ID]],tBatches[[Batch ID]],0)),IF(tProd[[#This Row],[Date]]<INDEX(tBatches[[Batch Start Date]],MATCH(tProd[[#This Row],[Batch ID]],tBatches[[Batch ID]],0)),"Date is before the batch start date",IF(AND(N(INDEX(tBatches[[Closing Date]],MATCH(tProd[[#This Row],[Batch ID]],tBatches[[Batch ID]],0)))>0,tProd[[#This Row],[Date]]>INDEX(tBatches[[Closing Date]],MATCH(tProd[[#This Row],[Batch ID]],tBatches[[Batch ID]],0))),"Date is after the batch closing date",IF(tProd[[#This Row],[Measurement Type]]="","Missing measurement type",IF(AND(tProd[[#This Row],[Measurement Type]]="Weighing",N(tProd[[#This Row],[Average Weight kg]])<=0),"Weighing needs an average weight",IF(AND(tProd[[#This Row],[Measurement Type]]<>"Weighing",N(tProd[[#This Row],[Quantity]])<=0),"Output needs a quantity","OK")))))))))))))
A12: 46292 | B12: ="PR-"&TEXT(ROW()-ROW(tProd[[#Headers],[Date]]),"00000") | C12: P005 | D12: LAYER-JUN-001 | E12: Egg Collection | F12: 10 | G12: crates | J12: SAMPLE DATA - delete or replace | K12: =IFERROR(INDEX(tBatches[[Animal Type]],MATCH(tProd[[#This Row],[Batch ID]],tBatches[[Batch ID]],0)),"") | L12: =IFERROR(tProd[[#This Row],[Date]]-INDEX(tBatches[[Batch Start Date]],MATCH(tProd[[#This Row],[Batch ID]],tBatches[[Batch ID]],0))+1,"") | M12: =IF(AND(tProd[[#This Row],[Date]]="",tProd[[#This Row],[Pen ID]]="",tProd[[#This Row],[Batch ID]]="",tProd[[#This Row],[Measurement Type]]=""),"",IF(tProd[[#This Row],[Date]]="","Missing date",IF(NOT(ISNUMBER(tProd[[#This Row],[Date]])),"Date is not a valid date",IF(tProd[[#This Row],[Pen ID]]="","Missing Pen ID",IF(COUNTIF(tPens[[Pen ID]],tProd[[#This Row],[Pen ID]])=0,"Pen "&tProd[[#This Row],[Pen ID]]&" is not in PEN_REGISTER",IF(tProd[[#This Row],[Batch ID]]="","Missing Batch ID",IF(COUNTIF(tBatches[[Batch ID]],tProd[[#This Row],[Batch ID]])=0,"Batch "&tProd[[#This Row],[Batch ID]]&" is not in BATCH_REGISTER",IF(COUNTIFS(tBatches[[Batch ID]],tProd[[#This Row],[Batch ID]],tBatches[[Pen ID]],tProd[[#This Row],[Pen ID]])=0,"Batch "&tProd[[#This Row],[Batch ID]]&" belongs to pen "&INDEX(tBatches[[Pen ID]],MATCH(tProd[[#This Row],[Batch ID]],tBatches[[Batch ID]],0)),IF(tProd[[#This Row],[Date]]<INDEX(tBatches[[Batch Start Date]],MATCH(tProd[[#This Row],[Batch ID]],tBatches[[Batch ID]],0)),"Date is before the batch start date",IF(AND(N(INDEX(tBatches[[Closing Date]],MATCH(tProd[[#This Row],[Batch ID]],tBatches[[Batch ID]],0)))>0,tProd[[#This Row],[Date]]>INDEX(tBatches[[Closing Date]],MATCH(tProd[[#This Row],[Batch ID]],tBatches[[Batch ID]],0))),"Date is after the batch closing date",IF(tProd[[#This Row],[Measurement Type]]="","Missing measurement type",IF(AND(tProd[[#This Row],[Measurement Type]]="Weighing",N(tProd[[#This Row],[Average Weight kg]])<=0),"Weighing needs an average weight",IF(AND(tProd[[#This Row],[Measurement Type]]<>"Weighing",N(tProd[[#This Row],[Quantity]])<=0),"Output needs a quantity","OK")))))))))))))

Sheet SALES
A1: SALES
A2: Every sale, linked to the pen & batch it came from (GENERAL for farm-wide items such as manure). Animal sales reduce the batch's current stock automatically.
A3: ■ GREEN header = you enter / select ■ GREY header = automatic (do not type) Add a new record by typing in the first empty row directly under the table.
A4: Date | B4: Sale ID | C4: Pen ID | D4: Batch ID | E4: Product | F4: Quantity Sold | G4: Unit Price | H4: Total Revenue | I4: Customer | J4: Payment Method | K4: Reference | L4: Notes | M4: Sale Unit | N4: Heads Removed | O4: Animal Type | P4: Check
A5: 46252 | B5: ="SA-"&TEXT(ROW()-ROW(tSales[[#Headers],[Date]]),"00000") | C5: P006 | D5: BROILER-JUL-001 | E5: Live Birds | F5: 290 | G5: 5500 | H5: =N(tSales[[#This Row],[Quantity Sold]])*N(tSales[[#This Row],[Unit Price]]) | I5: Market Trader (sample) | J5: Transfer | K5: SL-001 | L5: SAMPLE DATA - delete or replace | M5: =IFERROR(INDEX(tProducts[[Sale Unit]],MATCH(tSales[[#This Row],[Product]],tProducts[[Product]],0))&"","") | N5: =IF(IFERROR(INDEX(tProducts[[Reduces Head Count]],MATCH(tSales[[#This Row],[Product]],tProducts[[Product]],0)),"No")="Yes",N(tSales[[#This Row],[Quantity Sold]]),0) | O5: =IFERROR(INDEX(tBatches[[Animal Type]],MATCH(tSales[[#This Row],[Batch ID]],tBatches[[Batch ID]],0)),"") | P5: =IF(AND(tSales[[#This Row],[Date]]="",tSales[[#This Row],[Pen ID]]="",tSales[[#This Row],[Batch ID]]="",tSales[[#This Row],[Product]]="",tSales[[#This Row],[Quantity Sold]]=""),"",IF(tSales[[#This Row],[Date]]="","Missing date",IF(NOT(ISNUMBER(tSales[[#This Row],[Date]])),"Date is not a valid date",IF(tSales[[#This Row],[Product]]="","Missing product",IF(COUNTIF(tProducts[[Product]],tSales[[#This Row],[Product]])=0,"Product not in LISTS",IF(N(tSales[[#This Row],[Quantity Sold]])<=0,"Quantity must be greater than 0",IF(tSales[[#This Row],[Unit Price]]="","Missing unit price",IF(tSales[[#This Row],[Pen ID]]="","Missing Pen ID (or GENERAL)",IF(AND(tSales[[#This Row],[Pen ID]]="GENERAL",tSales[[#This Row],[Batch ID]]<>""),"GENERAL sales cannot carry a batch",IF(AND(tSales[[#This Row],[Pen ID]]="GENERAL",IFERROR(INDEX(tProducts[[Reduces Head Count]],MATCH(tSales[[#This Row],[Product]],tProducts[[Product]],0)),"No")="Yes"),"Animal sales must name the pen & batch",IF(AND(tSales[[#This Row],[Pen ID]]<>"GENERAL",COUNTIF(tPens[[Pen ID]],tSales[[#This Row],[Pen ID]])=0),"Pen "&tSales[[#This Row],[Pen ID]]&" is not in PEN_REGISTER",IF(AND(tSales[[#This Row],[Batch ID]]="",IFERROR(INDEX(tProducts[[Reduces Head Count]],MATCH(tSales[[#This Row],[Product]],tProducts[[Product]],0)),"No")="Yes"),"Missing Batch ID",IF(AND(tSales[[#This Row],[Batch ID]]<>"",COUNTIF(tBatches[[Batch ID]],tSales[[#This Row],[Batch ID]])=0),"Batch is not in BATCH_REGISTER",IF(AND(tSales[[#This Row],[Batch ID]]<>"",COUNTIFS(tBatches[[Batch ID]],tSales[[#This Row],[Batch ID]],tBatches[[Pen ID]],tSales[[#This Row],[Pen ID]])=0),"Batch "&tSales[[#This Row],[Batch ID]]&" belongs to pen "&INDEX(tBatches[[Pen ID]],MATCH(tSales[[#This Row],[Batch ID]],tBatches[[Batch ID]],0)),IF(IFERROR(AND(tSales[[#This Row],[Batch ID]]<>"",tSales[[#This Row],[Date]]<INDEX(tBatches[[Batch Start Date]],MATCH(tSales[[#This Row],[Batch ID]],tBatches[[Batch ID]],0))),FALSE),"Date is before the batch start date",IF(IFERROR(AND(tSales[[#This Row],[Batch ID]]<>"",INDEX(tBatches[[Current Quantity]],MATCH(tSales[[#This Row],[Batch ID]],tBatches[[Batch ID]],0))<0),FALSE),"Sold more animals than the batch holds",IF(tSales[[#This Row],[Payment Method]]="","Missing payment method","OK")))))))))))))))))
A6: 46277 | B6: ="SA-"&TEXT(ROW()-ROW(tSales[[#Headers],[Date]]),"00000") | C6: P005 | D6: LAYER-JUN-001 | E6: Eggs | F6: 20 | G6: 4800 | H6: =N(tSales[[#This Row],[Quantity Sold]])*N(tSales[[#This Row],[Unit Price]]) | I6: Customer A (sample) | J6: Cash | K6: SL-002 | L6: SAMPLE DATA - delete or replace | M6: =IFERROR(INDEX(tProducts[[Sale Unit]],MATCH(tSales[[#This Row],[Product]],tProducts[[Product]],0))&"","") | N6: =IF(IFERROR(INDEX(tProducts[[Reduces Head Count]],MATCH(tSales[[#This Row],[Product]],tProducts[[Product]],0)),"No")="Yes",N(tSales[[#This Row],[Quantity Sold]]),0) | O6: =IFERROR(INDEX(tBatches[[Animal Type]],MATCH(tSales[[#This Row],[Batch ID]],tBatches[[Batch ID]],0)),"") | P6: =IF(AND(tSales[[#This Row],[Date]]="",tSales[[#This Row],[Pen ID]]="",tSales[[#This Row],[Batch ID]]="",tSales[[#This Row],[Product]]="",tSales[[#This Row],[Quantity Sold]]=""),"",IF(tSales[[#This Row],[Date]]="","Missing date",IF(NOT(ISNUMBER(tSales[[#This Row],[Date]])),"Date is not a valid date",IF(tSales[[#This Row],[Product]]="","Missing product",IF(COUNTIF(tProducts[[Product]],tSales[[#This Row],[Product]])=0,"Product not in LISTS",IF(N(tSales[[#This Row],[Quantity Sold]])<=0,"Quantity must be greater than 0",IF(tSales[[#This Row],[Unit Price]]="","Missing unit price",IF(tSales[[#This Row],[Pen ID]]="","Missing Pen ID (or GENERAL)",IF(AND(tSales[[#This Row],[Pen ID]]="GENERAL",tSales[[#This Row],[Batch ID]]<>""),"GENERAL sales cannot carry a batch",IF(AND(tSales[[#This Row],[Pen ID]]="GENERAL",IFERROR(INDEX(tProducts[[Reduces Head Count]],MATCH(tSales[[#This Row],[Product]],tProducts[[Product]],0)),"No")="Yes"),"Animal sales must name the pen & batch",IF(AND(tSales[[#This Row],[Pen ID]]<>"GENERAL",COUNTIF(tPens[[Pen ID]],tSales[[#This Row],[Pen ID]])=0),"Pen "&tSales[[#This Row],[Pen ID]]&" is not in PEN_REGISTER",IF(AND(tSales[[#This Row],[Batch ID]]="",IFERROR(INDEX(tProducts[[Reduces Head Count]],MATCH(tSales[[#This Row],[Product]],tProducts[[Product]],0)),"No")="Yes"),"Missing Batch ID",IF(AND(tSales[[#This Row],[Batch ID]]<>"",COUNTIF(tBatches[[Batch ID]],tSales[[#This Row],[Batch ID]])=0),"Batch is not in BATCH_REGISTER",IF(AND(tSales[[#This Row],[Batch ID]]<>"",COUNTIFS(tBatches[[Batch ID]],tSales[[#This Row],[Batch ID]],tBatches[[Pen ID]],tSales[[#This Row],[Pen ID]])=0),"Batch "&tSales[[#This Row],[Batch ID]]&" belongs to pen "&INDEX(tBatches[[Pen ID]],MATCH(tSales[[#This Row],[Batch ID]],tBatches[[Batch ID]],0)),IF(IFERROR(AND(tSales[[#This Row],[Batch ID]]<>"",tSales[[#This Row],[Date]]<INDEX(tBatches[[Batch Start Date]],MATCH(tSales[[#This Row],[Batch ID]],tBatches[[Batch ID]],0))),FALSE),"Date is before the batch start date",IF(IFERROR(AND(tSales[[#This Row],[Batch ID]]<>"",INDEX(tBatches[[Current Quantity]],MATCH(tSales[[#This Row],[Batch ID]],tBatches[[Batch ID]],0))<0),FALSE),"Sold more animals than the batch holds",IF(tSales[[#This Row],[Payment Method]]="","Missing payment method","OK")))))))))))))))))
A7: 46285 | B7: ="SA-"&TEXT(ROW()-ROW(tSales[[#Headers],[Date]]),"00000") | C7: GENERAL | E7: Manure | F7: 10 | G7: 1000 | H7: =N(tSales[[#This Row],[Quantity Sold]])*N(tSales[[#This Row],[Unit Price]]) | I7: Walk-in Customer | J7: Cash | K7: SL-003 | L7: SAMPLE DATA - delete or replace | M7: =IFERROR(INDEX(tProducts[[Sale Unit]],MATCH(tSales[[#This Row],[Product]],tProducts[[Product]],0))&"","") | N7: =IF(IFERROR(INDEX(tProducts[[Reduces Head Count]],MATCH(tSales[[#This Row],[Product]],tProducts[[Product]],0)),"No")="Yes",N(tSales[[#This Row],[Quantity Sold]]),0) | O7: =IFERROR(INDEX(tBatches[[Animal Type]],MATCH(tSales[[#This Row],[Batch ID]],tBatches[[Batch ID]],0)),"") | P7: =IF(AND(tSales[[#This Row],[Date]]="",tSales[[#This Row],[Pen ID]]="",tSales[[#This Row],[Batch ID]]="",tSales[[#This Row],[Product]]="",tSales[[#This Row],[Quantity Sold]]=""),"",IF(tSales[[#This Row],[Date]]="","Missing date",IF(NOT(ISNUMBER(tSales[[#This Row],[Date]])),"Date is not a valid date",IF(tSales[[#This Row],[Product]]="","Missing product",IF(COUNTIF(tProducts[[Product]],tSales[[#This Row],[Product]])=0,"Product not in LISTS",IF(N(tSales[[#This Row],[Quantity Sold]])<=0,"Quantity must be greater than 0",IF(tSales[[#This Row],[Unit Price]]="","Missing unit price",IF(tSales[[#This Row],[Pen ID]]="","Missing Pen ID (or GENERAL)",IF(AND(tSales[[#This Row],[Pen ID]]="GENERAL",tSales[[#This Row],[Batch ID]]<>""),"GENERAL sales cannot carry a batch",IF(AND(tSales[[#This Row],[Pen ID]]="GENERAL",IFERROR(INDEX(tProducts[[Reduces Head Count]],MATCH(tSales[[#This Row],[Product]],tProducts[[Product]],0)),"No")="Yes"),"Animal sales must name the pen & batch",IF(AND(tSales[[#This Row],[Pen ID]]<>"GENERAL",COUNTIF(tPens[[Pen ID]],tSales[[#This Row],[Pen ID]])=0),"Pen "&tSales[[#This Row],[Pen ID]]&" is not in PEN_REGISTER",IF(AND(tSales[[#This Row],[Batch ID]]="",IFERROR(INDEX(tProducts[[Reduces Head Count]],MATCH(tSales[[#This Row],[Product]],tProducts[[Product]],0)),"No")="Yes"),"Missing Batch ID",IF(AND(tSales[[#This Row],[Batch ID]]<>"",COUNTIF(tBatches[[Batch ID]],tSales[[#This Row],[Batch ID]])=0),"Batch is not in BATCH_REGISTER",IF(AND(tSales[[#This Row],[Batch ID]]<>"",COUNTIFS(tBatches[[Batch ID]],tSales[[#This Row],[Batch ID]],tBatches[[Pen ID]],tSales[[#This Row],[Pen ID]])=0),"Batch "&tSales[[#This Row],[Batch ID]]&" belongs to pen "&INDEX(tBatches[[Pen ID]],MATCH(tSales[[#This Row],[Batch ID]],tBatches[[Batch ID]],0)),IF(IFERROR(AND(tSales[[#This Row],[Batch ID]]<>"",tSales[[#This Row],[Date]]<INDEX(tBatches[[Batch Start Date]],MATCH(tSales[[#This Row],[Batch ID]],tBatches[[Batch ID]],0))),FALSE),"Date is before the batch start date",IF(IFERROR(AND(tSales[[#This Row],[Batch ID]]<>"",INDEX(tBatches[[Current Quantity]],MATCH(tSales[[#This Row],[Batch ID]],tBatches[[Batch ID]],0))<0),FALSE),"Sold more animals than the batch holds",IF(tSales[[#This Row],[Payment Method]]="","Missing payment method","OK")))))))))))))))))
A8: 46290 | B8: ="SA-"&TEXT(ROW()-ROW(tSales[[#Headers],[Date]]),"00000") | C8: P005 | D8: LAYER-JUN-001 | E8: Eggs | F8: 18 | G8: 4900 | H8: =N(tSales[[#This Row],[Quantity Sold]])*N(tSales[[#This Row],[Unit Price]]) | I8: Customer B (sample) | J8: Credit | K8: SL-004 | L8: SAMPLE DATA - delete or replace | M8: =IFERROR(INDEX(tProducts[[Sale Unit]],MATCH(tSales[[#This Row],[Product]],tProducts[[Product]],0))&"","") | N8: =IF(IFERROR(INDEX(tProducts[[Reduces Head Count]],MATCH(tSales[[#This Row],[Product]],tProducts[[Product]],0)),"No")="Yes",N(tSales[[#This Row],[Quantity Sold]]),0) | O8: =IFERROR(INDEX(tBatches[[Animal Type]],MATCH(tSales[[#This Row],[Batch ID]],tBatches[[Batch ID]],0)),"") | P8: =IF(AND(tSales[[#This Row],[Date]]="",tSales[[#This Row],[Pen ID]]="",tSales[[#This Row],[Batch ID]]="",tSales[[#This Row],[Product]]="",tSales[[#This Row],[Quantity Sold]]=""),"",IF(tSales[[#This Row],[Date]]="","Missing date",IF(NOT(ISNUMBER(tSales[[#This Row],[Date]])),"Date is not a valid date",IF(tSales[[#This Row],[Product]]="","Missing product",IF(COUNTIF(tProducts[[Product]],tSales[[#This Row],[Product]])=0,"Product not in LISTS",IF(N(tSales[[#This Row],[Quantity Sold]])<=0,"Quantity must be greater than 0",IF(tSales[[#This Row],[Unit Price]]="","Missing unit price",IF(tSales[[#This Row],[Pen ID]]="","Missing Pen ID (or GENERAL)",IF(AND(tSales[[#This Row],[Pen ID]]="GENERAL",tSales[[#This Row],[Batch ID]]<>""),"GENERAL sales cannot carry a batch",IF(AND(tSales[[#This Row],[Pen ID]]="GENERAL",IFERROR(INDEX(tProducts[[Reduces Head Count]],MATCH(tSales[[#This Row],[Product]],tProducts[[Product]],0)),"No")="Yes"),"Animal sales must name the pen & batch",IF(AND(tSales[[#This Row],[Pen ID]]<>"GENERAL",COUNTIF(tPens[[Pen ID]],tSales[[#This Row],[Pen ID]])=0),"Pen "&tSales[[#This Row],[Pen ID]]&" is not in PEN_REGISTER",IF(AND(tSales[[#This Row],[Batch ID]]="",IFERROR(INDEX(tProducts[[Reduces Head Count]],MATCH(tSales[[#This Row],[Product]],tProducts[[Product]],0)),"No")="Yes"),"Missing Batch ID",IF(AND(tSales[[#This Row],[Batch ID]]<>"",COUNTIF(tBatches[[Batch ID]],tSales[[#This Row],[Batch ID]])=0),"Batch is not in BATCH_REGISTER",IF(AND(tSales[[#This Row],[Batch ID]]<>"",COUNTIFS(tBatches[[Batch ID]],tSales[[#This Row],[Batch ID]],tBatches[[Pen ID]],tSales[[#This Row],[Pen ID]])=0),"Batch "&tSales[[#This Row],[Batch ID]]&" belongs to pen "&INDEX(tBatches[[Pen ID]],MATCH(tSales[[#This Row],[Batch ID]],tBatches[[Batch ID]],0)),IF(IFERROR(AND(tSales[[#This Row],[Batch ID]]<>"",tSales[[#This Row],[Date]]<INDEX(tBatches[[Batch Start Date]],MATCH(tSales[[#This Row],[Batch ID]],tBatches[[Batch ID]],0))),FALSE),"Date is before the batch start date",IF(IFERROR(AND(tSales[[#This Row],[Batch ID]]<>"",INDEX(tBatches[[Current Quantity]],MATCH(tSales[[#This Row],[Batch ID]],tBatches[[Batch ID]],0))<0),FALSE),"Sold more animals than the batch holds",IF(tSales[[#This Row],[Payment Method]]="","Missing payment method","OK")))))))))))))))))

Sheet OTHER_EXPENSES
A1: OTHER EXPENSES
A2: All costs other than feed & drugs (chicks, labour, power, repairs...). Use GENERAL for farm-wide costs; add a Batch ID when the cost belongs to one production cycle.
A3: ■ GREEN header = you enter / select ■ GREY header = automatic (do not type) Add a new record by typing in the first empty row directly under the table.
A4: Date | B4: Expense ID | C4: Category | D4: Description | E4: Pen ID / General | F4: Batch ID (if applicable) | G4: Amount | H4: Payment Method | I4: Reference | J4: Notes | K4: Cost Level | L4: Animal Type | M4: Check
A5: 46174 | B5: ="EX-"&TEXT(ROW()-ROW(tExp[[#Headers],[Date]]),"00000") | C5: Day-old Chicks / Stock Purchase | D5: 400 point-of-lay pullets | E5: P005 | F5: LAYER-JUN-001 | G5: 1400000 | H5: Transfer | J5: SAMPLE DATA - delete or replace | K5: =IF(tExp[[#This Row],[Pen ID / General]]="","",IF(tExp[[#This Row],[Pen ID / General]]="GENERAL","General overhead",IF(tExp[[#This Row],[Batch ID (if applicable)]]="","Pen-level","Batch direct"))) | L5: =IF(tExp[[#This Row],[Batch ID (if applicable)]]<>"",IFERROR(INDEX(tBatches[[Animal Type]],MATCH(tExp[[#This Row],[Batch ID (if applicable)]],tBatches[[Batch ID]],0)),""),IFERROR(INDEX(tPens[[Animal Type]],MATCH(tExp[[#This Row],[Pen ID / General]],tPens[[Pen ID]],0))&"","")) | M5: =IF(AND(tExp[[#This Row],[Date]]="",tExp[[#This Row],[Category]]="",tExp[[#This Row],[Pen ID / General]]="",tExp[[#This Row],[Amount]]=""),"",IF(tExp[[#This Row],[Date]]="","Missing date",IF(NOT(ISNUMBER(tExp[[#This Row],[Date]])),"Date is not a valid date",IF(tExp[[#This Row],[Category]]="","Missing category",IF(N(tExp[[#This Row],[Amount]])<=0,"Amount must be greater than 0",IF(tExp[[#This Row],[Pen ID / General]]="","Enter a Pen ID or GENERAL",IF(AND(tExp[[#This Row],[Pen ID / General]]<>"GENERAL",COUNTIF(tPens[[Pen ID]],tExp[[#This Row],[Pen ID / General]])=0),"Pen "&tExp[[#This Row],[Pen ID / General]]&" is not in PEN_REGISTER",IF(AND(tExp[[#This Row],[Pen ID / General]]="GENERAL",tExp[[#This Row],[Batch ID (if applicable)]]<>""),"GENERAL expenses cannot carry a batch",IF(AND(tExp[[#This Row],[Batch ID (if applicable)]]<>"",COUNTIF(tBatches[[Batch ID]],tExp[[#This Row],[Batch ID (if applicable)]])=0),"Batch is not in BATCH_REGISTER",IF(AND(tExp[[#This Row],[Batch ID (if applicable)]]<>"",COUNTIFS(tBatches[[Batch ID]],tExp[[#This Row],[Batch ID (if applicable)]],tBatches[[Pen ID]],tExp[[#This Row],[Pen ID / General]])=0),"Batch "&tExp[[#This Row],[Batch ID (if applicable)]]&" belongs to pen "&INDEX(tBatches[[Pen ID]],MATCH(tExp[[#This Row],[Batch ID (if applicable)]],tBatches[[Batch ID]],0)),IF(tExp[[#This Row],[Payment Method]]="","Missing payment method","OK")))))))))))
